Workbook

Sheet EGRESOS 2025
A1: Fecha Pago | B1: Mes Devengo | C1: Descripcion | D1: Proveedor | E1: Monto Total | F1: Tipo Doc | G1: Forma Pago | H1: Nombre Cuenta | I1: IVA | J1: Monto Neto | K1: Cuenta | L1: CC
A2: 45323 | B2: 2024-02 | C2: Pago Recurrente VD Google LLC GSUI | E2: 57291 | F2: F | G2: Debito | H2: Plataformas Digitales | I2: 9147 | J2: 48144 | K2: 1.5.1 | L2: CC5
A3: 45324 | B3: 2024-02 | C3: PAGO EN LINEA CHILEXPRESS | E3: 61391 | F3: F | G3: Debito | H3: Despachos B2B (Gaspar) | I3: 9802 | J3: 51589 | K3: 1.7.1 | L3: CC7
A4: 45327 | B4: 2024-02 | C4: Compra Nacional HIP LIDER BUENAVEN | E4: 9480 | F4: F | G4: Credito | H4: Ingredientes | I4: 1514 | J4: 7966 | K4: 1.1.1 | L4: CC1
A5: 45327 | B5: 2024-02 | C5: Compra RAPPI PRIME RAPPI | E5: 4990 | F5: F | G5: Credito | H5: Comision Plataformas Delivery | I5: 797 | J5: 4193 | K5: 1.8.2 | L5: CC8
A6: 45328 | B6: 2024-02 | C6: Compra Nacional CLUB REPOSTERO SPA | E6: 2590 | F6: F | G6: Credito | H6: Ingredientes | I6: 414 | J6: 2176 | K6: 1.1.1 | L6: CC1
A7: 45328 | B7: 2024-02 | C7: Compra Nacional HIP LIDER BUENAVEN | E7: 210 | F7: F | G7: Credito | H7: Ingredientes | I7: 34 | J7: 176 | K7: 1.1.1 | L7: CC1
A8: 45328 | B8: 2024-02 | C8: Compra Nacional NP FLOW | E8: 99979 | F8: F | G8: Credito | H8: Equipamiento Local | I8: 15963 | J8: 84016 | K8: 1.3.10 | L8: CC3
A9: 45328 | B9: 2024-02 | C9: Compra Nacional LAPIZ LOPEZ | E9: 5960 | F9: F | G9: Credito | H9: Equipamiento Local | I9: 952 | J9: 5008 | K9: 1.3.10 | L9: CC3
A10: 45328 | B10: 2024-02 | C10: Compra Internacional FACEBK *5PT5J | E10: 31600 | F10: F | G10: Credito | H10: RRSS | I10: 5045 | J10: 26555 | K10: 1.6.1 | L10: CC6
A11: 45330 | B11: 2024-02 | C11: Compra Nacional NP ALVI TOBALABA O | E11: 55104 | F11: F | G11: Credito | H11: Ingredientes | I11: 8798 | J11: 46306 | K11: 1.1.1 | L11: CC1
A12: 45330 | B12: 2024-02 | C12: Compra Nacional NP ALVI TOBALABA O | E12: 36736 | F12: F | G12: Credito | H12: Ingredientes | I12: 5865 | J12: 30871 | K12: 1.1.1 | L12: CC1
A13: 45330 | B13: 2024-02 | C13: Compra Nacional MERPAGO*PAPADINSPA | E13: 20400 | F13: F | G13: Credito | H13: Ingredientes | I13: 3257 | J13: 17143 | K13: 1.1.1 | L13: CC1
... A817: 46112 | B817: 2026-03 | C817: Compra FACEBK *NAJMMJ9VJ | E817: 343624 | F817: F | G817: Credito | H817: RRSS | I817: 54864 | J817: 288760 | K817: 1.6.1 | L817: CC6
A818: 45323 | B818: 2024-02 | C818: Transf.Internet a 81.094.100-6 | D818: COOPERATIVA AGRICOLA Y LECHERA DE LA UNION LTDA. | E818: 321409 | F818: F | G818: Debito | H818: Ingredientes | I818: 51317 | J818: 270092 | K818: 1.1.1 | L818: CC1
A819: 45323 | B819: 2024-01 | C819: Transf.Internet a 19.567.111-7 | D819: Maria Jose Grez (sueldo) | E819: 2790 | F819: S | G819: Debito | H819: Sueldos con Contrato | I819: 0 | J819: 2790 | K819: 1.2.1 | L819: CC2
A820: 45323 | B820: 2024-01 | C820: Transf.Internet a 18.732.574-9 | D820: Sueldo | E820: 100000 | F820: S | G820: Debito | H820: Sueldos con Contrato | I820: 0 | J820: 100000 | K820: 1.2.1 | L820: CC2
A821: 45323 | B821: 2024-01 | C821: Transf.Internet a 21.093.602-5 | D821: Nataly Morales (sueldo) | E821: 325000 | F821: S | G821: Debito | H821: Sueldos con Contrato | I821: 0 | J821: 325000 | K821: 1.2.1 | L821: CC2
A822: 45323 | B822: 2024-02 | C822: Transf.Internet a 19.324.205-7 | D822: Catalina Cuevas (honorarios marketing) | E822: 400000 | F822: S | G822: Debito | H822: Honorarios | I822: 0 | J822: 400000 | K822: 1.2.2 | L822: CC2
A823: 45323 | B823: 2024-01 | C823: Transf.Internet a 19.567.111-7 | D823: Maria Jose Grez (sueldo) | E823: 400000 | F823: S | G823: Debito | H823: Sueldos con Contrato | I823: 0 | J823: 400000 | K823: 1.2.1 | L823: CC2
A824: 45323 | B824: 2024-01 | C824: Transf.Internet a 19.606.694-2 | D824: Josefina Landaeta (sueldo) | E824: 400000 | F824: S | G824: Debito | H824: Sueldos con Contrato | I824: 0 | J824: 400000 | K824: 1.2.1 | L824: CC2
A825: 45323 | B825: 2024-01 | C825: Transf.Internet a 19.606.694-2 | D825: Josefina Landaeta (sueldo) | E825: 400000 | F825: S | G825: Debito | H825: Sueldos con Contrato | I825: 0 | J825: 400000 | K825: 1.2.1 | L825: CC2
A826: 45323 | B826: 2024-01 | C826: Transf.Internet a 19.567.111-7 | D826: Maria Jose Grez (sueldo) | E826: 400000 | F826: S | G826: Debito | H826: Sueldos con Contrato | I826: 0 | J826: 400000 | K826: 1.2.1 | L826: CC2
A827: 45323 | B827: 2024-01 | C827: Transf.Internet a 17.083.572-7 | D827: Ignacia Grez (retiro duena) | E827: 400000 | F827: S | G827: Debito | H827: Sueldos con Contrato | I827: 0 | J827: 400000 | K827: 1.2.1 | L827: CC2
A828: 45323 | B828: 2024-02 | C828: Transf.Internet a 6.551.524-5 | D828: Despachos Horeca (6.551.524-5) | E828: 7880 | F828: S | G828: Debito | H828: Despachos B2B (Gaspar) | I828: 0 | J828: 7880 | K828: 1.7.1 | L828: CC7
A829: 45324 | B829: 2024-02 | C829: Transf.Internet a 78.383.730-7 | D829: AVICOLA Y COMERCIAL EL TOCO LTDA | E829: 59400 | F829: F | G829: Debito | H829: Ingredientes | I829: 9484 | J829: 49916 | K829: 1.1.1 | L829: CC1
... A847: 45338 | B847: 2024-02 | C847: Transf.Internet a 76.669.508-6 | D847: ENVIAME LATAM SPA | E847: 362422 | F847: F | G847: Debito | H847: Despachos B2B (Gaspar) | I847: 57866 | J847: 304556 | K847: 1.7.1 | L847: CC7
A848: 45344 | B848: 2024-02 | C848: Compra Nacional RAN SPA | E848: 1400 | F848: S | G848: Credito | I848: 0 | J848: 1400 | K848: 1.3.6 | L848: CC3
A849: 45344 | B849: 2024-02 | C849: Compra Nacional SUCURSAL APUMANQUE | E849: 16250 | F849: S | G849: Credito | I849: 0 | J849: 16250 | K849: 1.3.6 | L849: CC3
A850: 45345 | B850: 2024-01 | C850: Transf.Internet a 19.076.816-3 | D850: Sueldo | E850: 250000 | F850: S | G850: Debito | H850: Sueldos con Contrato | I850: 0 | J850: 250000 | K850: 1.2.1 | L850: CC2
A851: 45348 | B851: 2024-01 | C851: Transf.Internet a 21.572.942-7 | D851: Sueldo | E851: 200000 | F851: S | G851: Debito | H851: Sueldos con Contrato | I851: 0 | J851: 200000 | K851: 1.2.1 | L851: CC2
A852: 45349 | B852: 2024-02 | C852: Transf.Internet a 19.324.205-7 | D852: Catalina Cuevas (honorarios marketing) | E852: 11200 | F852: S | G852: Debito | H852: Honorarios | I852: 0 | J852: 11200 | K852: 1.2.2 | L852: CC2
A853: 45351 | B853: 2024-02 | C853: Transf.Internet a 81.094.100-6 | D853: COOPERATIVA AGRICOLA Y LECHERA DE LA UNION LTDA. | E853: 42969 | F853: F | G853: Debito | H853: Ingredientes | I853: 6861 | J853: 36108 | K853: 1.1.1 | L853: CC1
A854: 45351 | B854: 2024-02 | C854: Transf.Internet a 76.934.534-5 | D854: AT CONTADORES SERVICIOS PROFESIONALES LIMITADA | E854: 45000 | F854: F | G854: Debito | H854: Asesoria Contable | I854: 7185 | J854: 37815 | K854: 1.2.3 | L854: CC2
A855: 45351 | B855: 2024-01 | C855: Transf.Internet a 21.093.602-5 | D855: Nataly Morales (sueldo) | E855: 325000 | F855: S | G855: Debito | H855: Sueldos con Contrato | I855: 0 | J855: 325000 | K855: 1.2.1 | L855: CC2
A856: 45351 | B856: 2024-02 | C856: Transf.Internet a 19.324.205-7 | D856: Catalina Cuevas (honorarios marketing) | E856: 400000 | F856: S | G856: Debito | H856: Honorarios | I856: 0 | J856: 400000 | K856: 1.2.2 | L856: CC2
A857: 45351 | B857: 2024-01 | C857: Transf.Internet a 17.083.572-7 | D857: Ignacia Grez (retiro duena) | E857: 400000 | F857: S | G857: Debito | H857: Sueldos con Contrato | I857: 0 | J857: 400000 | K857: 1.2.1 | L857: CC2
A858: 45351 | B858: 2024-01 | C858: Transf.Internet a 19.606.694-2 | D858: Josefina Landaeta (sueldo) | E858: 800000 | F858: S | G858: Debito | H858: Sueldos con Contrato | I858: 0 | J858: 800000 | K858: 1.2.1 | L858: CC2
A859: 45351 | B859: 2024-01 | C859: Transf.Internet a 19.567.111-7 | D859: Maria Jose Grez (sueldo) | E859: 800000 | F859: S | G859: Debito | H859: Sueldos con Contrato | I859: 0 | J859: 800000 | K859: 1.2.1 | L859: CC2
A860: 45351 | B860: 2024-02 | C860: Transf.Internet a 76.860.819-9 | D860: AGENCIA DE PUBLICIDAD RORAIMA DIGITAL LIMITADA | E860: 17850 | F860: F | G860: Debito | H860: RRSS | I860: 2850 | J860: 15000 | K860: 1.6.1 | L860: CC6
A861: 45659 | B861: 2025-01 | C861: Transf.Internet a 77.931.120-1 | D861: Homs | E861: 41995 | F861: F | G861: Debito | H861: Packaging | I861: 6705 | J861: 35290 | K861: 1.1.2 | L861: CC1
... A1009: 45758 | B1009: 2025-04 | C1009: Transf.Internet a 78.996.660-5 | D1009: COLORPACK IMPRESORES LIMITADA | E1009: 1127525 | F1009: F | G1009: Debito | H1009: Packaging | I1009: 180025 | J1009: 947500 | K1009: 1.1.2 | L1009: CC1
A1010: 45758 | B1010: 2025-04 | C1010: Compra SALA VENTAS VITAC | E1010: 4460 | F1010: S | G1010: Credito | I1010: 0 | J1010: 4460 | K1010: 1.3.6 | L1010: CC3
A1011: 45758 | B1011: 2025-04 | C1011: Transf.Internet a 77.857.789-5 | D1011: FLAPP SPA | E1011: 876661 | F1011: F | G1011: Debito | H1011: Plataformas Digitales | I1011: 139971 | J1011: 736690 | K1011: 1.5.1 | L1011: CC5
A1012: 45758 | B1012: 2025-04 | C1012: Transf.Internet a 76.669.508-6 | D1012: ENVIAME LATAM SPA | E1012: 12376 | F1012: F | G1012: Debito | H1012: Despachos B2B (Gaspar) | I1012: 1976 | J1012: 10400 | K1012: 1.7.1 | L1012: CC7
A1013: 45758 | B1013: 2025-04 | C1013: Transf.Internet a 6.551.524-5 | D1013: Despachos Horeca (6.551.524-5) | E1013: 39186 | F1013: S | G1013: Debito | H1013: Despachos B2B (Gaspar) | I1013: 0 | J1013: 39186 | K1013: 1.7.1 | L1013: CC7
A1014: 45761 | B1014: 2025-04 | C1014: Transf.Internet a 84.736.800-4 | D1014: CHAVARRI Y HUGOT LTDA | E1014: 99450 | F1014: F | G1014: Debito | H1014: Ingredientes | I1014: 15879 | J1014: 83571 | K1014: 1.1.1 | L1014: CC1
A1015: 45761 | B1015: 2025-04 | C1015: Transf.Internet a 96.556.940-5 | D1015: PROVEEDORES INTEGRALES PRISA S A | E1015: 152618 | F1015: F | G1015: Debito | H1015: Limpieza y Aseo | I1015: 24368 | J1015: 128250 | K1015: 1.3.8 | L1015: CC3
A1016: 45761 | B1016: 2025-03 | C1016: Transf.Internet a 10.325.328-4 | D1016: Patricia Guijuelos (sueldo carrito) | E1016: 130000 | F1016: S | G1016: Debito | H1016: Sueldos Carro | I1016: 0 | J1016: 130000 | K1016: 1.4.5 | L1016: CC4
A1017: 45762 | B1017: 2025-04 | C1017: Transf.Internet a 78.383.730-7 | D1017: AVICOLA Y COMERCIAL EL TOCO LTDA | E1017: 75601 | F1017: F | G1017: Debito | H1017: Ingredientes | I1017: 12071 | J1017: 63530 | K1017: 1.1.1 | L1017: CC1
A1018: 45762 | B1018: 2025-04 | C1018: Transf.Internet a 78.383.730-7 | D1018: AVICOLA Y COMERCIAL EL TOCO LTDA | E1018: 75601 | F1018: F | G1018: Debito | H1018: Ingredientes | I1018: 12071 | J1018: 63530 | K1018: 1.1.1 | L1018: CC1
A1019: 45762 | B1019: 2025-04 | C1019: Transf.Internet a 78.383.730-7 | D1019: AVICOLA Y COMERCIAL EL TOCO LTDA | E1019: 75601 | F1019: F | G1019: Debito | H1019: Ingredientes | I1019: 12071 | J1019: 63530 | K1019: 1.1.1 | L1019: CC1
A1020: 45763 | B1020: 2025-04 | C1020: Transf.Internet a 96.775.020-4 | D1020: GREAT FOODS S.A. | E1020: 269014 | F1020: F | G1020: Debito | H1020: Ingredientes | I1020: 42952 | J1020: 226062 | K1020: 1.1.1 | L1020: CC1
A1021: 45763 | B1021: 2025-03 | C1021: Transf.Internet a 21.093.602-5 | D1021: Nataly Morales (sueldo) | E1021: 200000 | F1021: S | G1021: Debito | H1021: Sueldos con Contrato | I1021: 0 | J1021: 200000 | K1021: 1.2.1 | L1021: CC2
A1022: 45764 | B1022: 2025-04 | C1022: Transf.Internet a 76.339.600-2 | D1022: INVERSIONES PST LTDA | E1022: 69055 | F1022: F | G1022: Debito | H1022: Ingredientes | I1022: 11026 | J1022: 58029 | K1022: 1.1.1 | L1022: CC1
... A1064: 45783 | B1064: 2025-04 | C1064: Transf.Internet a 19.606.694-2 | D1064: Josefina Landaeta (sueldo) | E1064: 125000 | F1064: S | G1064: Debito | H1064: Sueldos con Contrato | I1064: 0 | J1064: 125000 | K1064: 1.2.1 | L1064: CC2
A1065: 45783 | B1065: 2025-05 | C1065: Transf.Internet a 76.439.798-3 | E1065: 92880 | F1065: S | G1065: Debito | I1065: 0 | J1065: 92880 | K1065: 1.3.6 | L1065: CC3
A1066: 45784 | B1066: 2025-05 | C1066: Transf.Internet a 78.383.730-7 | D1066: AVICOLA Y COMERCIAL EL TOCO LTDA | E1066: 75601 | F1066: F | G1066: Debito | H1066: Ingredientes | I1066: 12071 | J1066: 63530 | K1066: 1.1.1 | L1066: CC1
A1067: 45784 | B1067: 2025-05 | C1067: Transf.Internet a 78.383.730-7 | D1067: AVICOLA Y COMERCIAL EL TOCO LTDA | E1067: 75601 | F1067: F | G1067: Debito | H1067: Ingredientes | I1067: 12071 | J1067: 63530 | K1067: 1.1.1 | L1067: CC1
A1068: 45784 | B1068: 2025-05 | C1068: Transf.Internet a 84.736.800-4 | D1068: CHAVARRI Y HUGOT LTDA | E1068: 110240 | F1068: F | G1068: Debito | H1068: Ingredientes | I1068: 17601 | J1068: 92639 | K1068: 1.1.1 | L1068: CC1
A1069: 45784 | B1069: 2025-05 | C1069: Transf.Internet a 76.499.503-1 | D1069: PreGel Chile SPA | E1069: 228637 | F1069: F | G1069: Debito | H1069: Ingredientes | I1069: 36505 | J1069: 192132 | K1069: 1.1.1 | L1069: CC1
A1070: 45784 | B1070: 2025-05 | C1070: Transf.Internet a 81.094.100-6 | D1070: COOPERATIVA AGRICOLA Y LECHERA DE LA UNION LTDA. | E1070: 369876 | F1070: F | G1070: Debito | H1070: Ingredientes | I1070: 59056 | J1070: 310820 | K1070: 1.1.1 | L1070: CC1
A1071: 45784 | B1071: 2025-05 | C1071: Transf.Internet a 19.324.205-7 | D1071: Catalina Cuevas (honorarios marketing) | E1071: 3200 | F1071: S | G1071: Debito | H1071: Honorarios | I1071: 0 | J1071: 3200 | K1071: 1.2.2 | L1071: CC2
A1072: 45784 | B1072: 2025-05 | C1072: Transf.Internet a 19.324.205-7 | D1072: Catalina Cuevas (honorarios marketing) | E1072: 72904 | F1072: S | G1072: Debito | H1072: Honorarios | I1072: 0 | J1072: 72904 | K1072: 1.2.2 | L1072: CC2
A1073: 45785 | B1073: 2025-05 | C1073: Transf.Internet a 77.190.532-3 | D1073: STICKERS PRINT SPA | E1073: 11990 | F1073: F | G1073: Debito | H1073: Packaging | I1073: 1914 | J1073: 10076 | K1073: 1.1.2 | L1073: CC1
A1074: 45785 | B1074: 2025-04 | C1074: Transf.Internet a 21.593.197-8 | D1074: Sueldo | E1074: 34000 | F1074: S | G1074: Debito | H1074: Sueldos con Contrato | I1074: 0 | J1074: 34000 | K1074: 1.2.1 | L1074: CC2
A1075: 45789 | B1075: 2025-05 | C1075: Transf.Internet a 78.088.306-5 | D1075: BOZEN SPA | E1075: 46720 | F1075: F | G1075: Debito | H1075: Ingredientes | I1075: 7459 | J1075: 39261 | K1075: 1.1.1 | L1075: CC1
A1076: 45789 | B1076: 2025-05 | C1076: Transf.Internet a 96.556.940-5 | D1076: PROVEEDORES INTEGRALES PRISA S A | E1076: 122601 | F1076: F | G1076: Debito | H1076: Limpieza y Aseo | I1076: 19575 | J1076: 103026 | K1076: 1.3.8 | L1076: CC3
A1077: 45789 | B1077: 2025-05 | C1077: Transf.Internet a 5.279.758-6 | D1077: Luis Felipe Ibieta (sobreconsumos agua/luz/gas) | E1077: 826409 | F1077: S | G1077: Debito | H1077: Mantenciones | I1077: 0 | J1077: 826409 | K1077: 1.3.6 | L1077: CC3
... A1150: 45818 | B1150: 2025-06 | C1150: Transf.Internet a 96.556.940-5 | D1150: PROVEEDORES INTEGRALES PRISA S A | E1150: 103601 | F1150: F | G1150: Debito | H1150: Limpieza y Aseo | I1150: 16541 | J1150: 87060 | K1150: 1.3.8 | L1150: CC3
A1151: 45818 | B1151: 2025-06 | C1151: Compra SAM SPA | E1151: 3000 | F1151: S | G1151: Credito | I1151: 0 | J1151: 3000 | K1151: 1.3.6 | L1151: CC3
A1152: 45818 | B1152: 2025-06 | C1152: Transf.Internet a 77.857.789-5 | D1152: FLAPP SPA | E1152: 1142050 | F1152: F | G1152: Debito | H1152: Plataformas Digitales | I1152: 182344 | J1152: 959706 | K1152: 1.5.1 | L1152: CC5
A1153: 45818 | B1153: 2025-06 | C1153: Transf.Internet a 96.946.650-3 | D1153: CENTRO DE CONVENCIONES SANTIAGO S.A | E1153: 178500 | F1153: F | G1153: Debito | H1153: Ferias y Eventos | I1153: 28500 | J1153: 150000 | K1153: 1.6.3 | L1153: CC6
A1154: 45818 | B1154: 2025-06 | C1154: Transf.Internet a 6.551.524-5 | D1154: Despachos Horeca (6.551.524-5) | E1154: 42000 | F1154: S | G1154: Debito | H1154: Despachos B2B (Gaspar) | I1154: 0 | J1154: 42000 | K1154: 1.7.1 | L1154: CC7
A1155: 45819 | B1155: 2025-06 | C1155: Transf.Internet a 56.059.620-0 | D1155: GGCC/Arriendo oficina (56.059.620-0) | E1155: 248828 | F1155: F | G1155: Debito | H1155: Arriendo Local | I1155: 39729 | J1155: 209099 | K1155: 1.3.1 | L1155: CC3
A1156: 45819 | B1156: 2025-06 | C1156: Transf.Internet a 76.669.508-6 | D1156: ENVIAME LATAM SPA | E1156: 15470 | F1156: F | G1156: Debito | H1156: Despachos B2B (Gaspar) | I1156: 2470 | J1156: 13000 | K1156: 1.7.1 | L1156: CC7
A1157: 45821 | B1157: 2025-06 | C1157: Transf.Internet a 78.383.730-7 | D1157: AVICOLA Y COMERCIAL EL TOCO LTDA | E1157: 37800 | F1157: F | G1157: Debito | H1157: Ingredientes | I1157: 6035 | J1157: 31765 | K1157: 1.1.1 | L1157: CC1
A1158: 45821 | B1158: 2025-06 | C1158: Transf.Internet a 78.383.730-7 | D1158: AVICOLA Y COMERCIAL EL TOCO LTDA | E1158: 37800 | F1158: F | G1158: Debito | H1158: Ingredientes | I1158: 6035 | J1158: 31765 | K1158: 1.1.1 | L1158: CC1
A1159: 45821 | B1159: 2025-06 | C1159: Transf.Internet a 84.736.800-4 | D1159: CHAVARRI Y HUGOT LTDA | E1159: 110240 | F1159: F | G1159: Debito | H1159: Ingredientes | I1159: 17601 | J1159: 92639 | K1159: 1.1.1 | L1159: CC1
A1160: 45821 | B1160: 2025-05 | C1160: Transf.Internet a 18.022.436-K | D1160: Angeles Grez (sueldo) | E1160: 4580 | F1160: S | G1160: Debito | H1160: Sueldos con Contrato | I1160: 0 | J1160: 4580 | K1160: 1.2.1 | L1160: CC2
A1161: 45821 | B1161: 2025-05 | C1161: Transf.Internet a 21.093.602-5 | D1161: Nataly Morales (sueldo) | E1161: 200000 | F1161: S | G1161: Debito | H1161: Sueldos con Contrato | I1161: 0 | J1161: 200000 | K1161: 1.2.1 | L1161: CC2
A1162: 45824 | B1162: 2025-06 | C1162: Transf.Internet a 96.532.120-9 | D1162: LA OFERTA COMERCIAL LIMITADA | E1162: 164850 | F1162: F | G1162: Debito | H1162: Ingredientes | I1162: 26321 | J1162: 138529 | K1162: 1.1.1 | L1162: CC1
A1163: 45824 | B1163: 2025-05 | C1163: Transf.Internet a 22.042.791-9 | D1163: Sueldo | E1163: 42730 | F1163: S | G1163: Debito | H1163: Sueldos con Contrato | I1163: 0 | J1163: 42730 | K1163: 1.2.1 | L1163: CC2
... A1194: 45839 | B1194: 2025-06 | C1194: Transf.Internet a 19.567.111-7 | D1194: Maria Jose Grez (sueldo) | E1194: 1134330 | F1194: S | G1194: Debito | H1194: Sueldos con Contrato | I1194: 0 | J1194: 1134330 | K1194: 1.2.1 | L1194: CC2
A1195: 45839 | B1195: 2025-07 | C1195: 0762094746 Transf a IMP. Y COM. IN | E1195: 20393 | F1195: S | G1195: Debito | I1195: 0 | J1195: 20393 | K1195: 1.3.6 | L1195: CC3
A1196: 45839 | B1196: 2025-06 | C1196: Transf.Internet a 10.325.328-4 | D1196: Patricia Guijuelos (sueldo carrito) | E1196: 563922 | F1196: S | G1196: Debito | H1196: Sueldos Carro | I1196: 0 | J1196: 563922 | K1196: 1.4.5 | L1196: CC4
A1197: 45840 | B1197: 2025-06 | C1197: Transf.Internet a 20.830.554-9 | D1197: Sueldo personal (20.830.554-9) | E1197: 50000 | F1197: S | G1197: Debito | H1197: Sueldos con Contrato | I1197: 0 | J1197: 50000 | K1197: 1.2.1 | L1197: CC2
A1198: 45841 | B1198: 2025-07 | C1198: Transf.Internet a 78.088.306-5 | D1198: BOZEN SPA | E1198: 29009 | F1198: F | G1198: Debito | H1198: Ingredientes | I1198: 4632 | J1198: 24377 | K1198: 1.1.1 | L1198: CC1
A1199: 45841 | B1199: 2025-07 | C1199: Transf.Internet a 76.639.313-6 | D1199: CC NUTS SpA | E1199: 79900 | F1199: F | G1199: Debito | H1199: Ingredientes | I1199: 12757 | J1199: 67143 | K1199: 1.1.1 | L1199: CC1
A1200: 45841 | B1200: 2025-07 | C1200: Transf.Internet a 78.065.582-8 | D1200: CLAVE TRIBUTARIA CONTADORES LIMITADA | E1200: 65000 | F1200: F | G1200: Debito | H1200: Asesoria Contable | I1200: 10378 | J1200: 54622 | K1200: 1.2.3 | L1200: CC2
A1201: 45841 | B1201: 2025-07 | C1201: Transf.Internet a 76.996.332-4 | D1201: VST SPA | E1201: 70210 | F1201: F | G1201: Debito | H1201: Mantenciones | I1201: 11210 | J1201: 59000 | K1201: 1.3.6 | L1201: CC3
A1202: 45841 | B1202: 2025-07 | C1202: Transf.Internet a 76.903.312-2 | D1202: AGENCIA DE DISEÃ?O PLANK LIMITADA | E1202: 129000 | F1202: F | G1202: Debito | H1202: RRSS | I1202: 20597 | J1202: 108403 | K1202: 1.6.1 | L1202: CC6
A1203: 45842 | B1203: 2025-06 | C1203: Transf.Internet a 7.051.940-2 | D1203: Sueldo | E1203: 18000 | F1203: S | G1203: Debito | H1203: Sueldos con Contrato | I1203: 0 | J1203: 18000 | K1203: 1.2.1 | L1203: CC2
A1204: 45842 | B1204: 2025-07 | C1204: Transf.Internet a 5.279.758-6 | D1204: Luis Felipe Ibieta (sobreconsumos agua/luz/gas) | E1204: 916300 | F1204: S | G1204: Debito | H1204: Mantenciones | I1204: 0 | J1204: 916300 | K1204: 1.3.6 | L1204: CC3
A1205: 45845 | B1205: 2025-07 | C1205: Transf.Internet a 76.339.600-2 | D1205: INVERSIONES PST LTDA | E1205: 66570 | F1205: F | G1205: Debito | H1205: Ingredientes | I1205: 10629 | J1205: 55941 | K1205: 1.1.1 | L1205: CC1
A1206: 45845 | B1206: 2025-07 | C1206: Transf.Internet a 96.556.940-5 | D1206: PROVEEDORES INTEGRALES PRISA S A | E1206: 122015 | F1206: F | G1206: Debito | H1206: Limpieza y Aseo | I1206: 19481 | J1206: 102534 | K1206: 1.3.8 | L1206: CC3
A1207: 45845 | B1207: 2025-07 | C1207: Transf.Internet a 56.059.620-0 | D1207: GGCC/Arriendo oficina (56.059.620-0) | E1207: 246737 | F1207: F | G1207: Debito | H1207: Arriendo Local | I1207: 39395 | J1207: 207342 | K1207: 1.3.1 | L1207: CC3
... A1235: 45856 | B1235: 2025-07 | C1235: Transf.Internet a 76.285.343-4 | D1235: FRAILE CASTRUCCIO YUTE SPA | E1235: 38080 | F1235: F | G1235: Debito | H1235: Packaging | I1235: 6080 | J1235: 32000 | K1235: 1.1.2 | L1235: CC1
A1236: 45859 | B1236: 2025-07 | C1236: Compra SUCURSAL APUMANQU | E1236: 7990 | F1236: S | G1236: Credito | I1236: 0 | J1236: 7990 | K1236: 1.3.6 | L1236: CC3
A1237: 45860 | B1237: 2025-07 | C1237: Transf.Internet a 84.736.800-4 | D1237: CHAVARRI Y HUGOT LTDA | E1237: 92560 | F1237: F | G1237: Debito | H1237: Ingredientes | I1237: 14778 | J1237: 77782 | K1237: 1.1.1 | L1237: CC1
...

Sheet Resumen
A1: Mes Devengo | B1: CC1 Costos Producto | C1: CC2 Sueldos | D1: CC3 Infraestructura | E1: CC4 Carrito | F1: CC5 Plataformas Digitales | G1: CC6 Marketing | H1: CC7 Logistica | I1: CC8 Comisiones | J1: CC9 Impuestos | K1: TOTAL
A2: 2025-01 | B2: 3542555 | C2: 1601559 | D2: 1770166 | F2: 1270508 | G2: 509471 | H2: 87948 | I2: 4193 | J2: 33442 | K2: =+SUM(B2:J2) -> 8819842
A3: 2025-02 | C3: 8151421 | J3: 1055433 | K3: =+SUM(B3:J3) -> 9206854
A4: 2025-03 | B4: 2102400 | C4: 5416208 | D4: 1046705 | E4: 390000 | F4: 930769 | G4: 609405 | H4: 95154 | I4: 54420 | J4: 1684643 | K4: =+SUM(B4:J4) -> 12329704
A5: 2025-04 | B5: 5468426 | C5: 5180655 | D5: 2267053 | E5: 520000 | F5: 1289353 | G5: 241080 | H5: 91292 | I5: 19531 | J5: 2028841 | K5: =+SUM(B5:J5) -> 17106231
A6: 2025-05 | B6: 5975278 | C6: 5397366 | D6: 2207267 | E6: 1714271 | F6: 1123685 | G6: 1055463 | H6: 111775 | I6: 30158 | J6: 1781383 | K6: =+SUM(B6:J6) -> 19396646
A7: 2025-06 | B7: 6802920 | C7: 9673034 | D7: 2662253 | E7: 588922 | F7: 1513352 | G7: 741769 | H7: 140638 | I7: 22967 | J7: 1585026 | K7: =+SUM(B7:J7) -> 23730881
A8: 2025-07 | B8: 4501491 | C8: 3772466 | D8: 2780933 | E8: 25000 | F8: 1619437 | G8: 1143524 | H8: 155377 | I8: 44407 | J8: 1895184 | K8: =+SUM(B8:J8) -> 15937819
A9: 2025-08 | B9: 4124880 | C9: 6412311 | D9: 2621844 | E9: 645002 | F9: 1357282 | G9: 931670 | H9: 127385 | I9: 5979 | J9: 2347740 | K9: =+SUM(B9:J9) -> 18574093
A10: 2025-09 | B10: 4137176 | C10: 11662962 | D10: 2640613 | E10: 1006036 | F10: 1235007 | G10: 623561 | H10: 178648 | I10: 26828 | J10: 1936260 | K10: =+SUM(B10:J10) -> 23447091
A11: 2025-10 | B11: 4387607 | C11: 3998259 | D11: 57867500 | F11: 1649247 | G11: 758966 | H11: 98038 | I11: 31928 | J11: 1395392 | K11: =+SUM(B11:J11) -> 70186937
A12: 2025-11 | B12: 4365818 | C12: 6611057 | D12: 7065137 | E12: 545002 | F12: 1561367 | G12: 448323 | H12: 113459 | I12: 54812 | J12: 2034764 | K12: =+SUM(B12:J12) -> 22799739
A13: 2025-12 | B13: 5443210 | C13: 7162631 | D13: 6270337 | E13: 514794 | F13: 1168034 | G13: 2269081 | H13: 570128 | I13: 2492 | J13: 2278363 | K13: =+SUM(B13:J13) -> 25679070
A14: 2026-01 | B14: 5578871 | C14: 9849594 | D14: 5849410 | E14: 551261 | F14: 1833190 | G14: 827746 | H14: 559074 | J14: 2425979 | K14: =+SUM(B14:J14) -> 27475125
A15: 2026-02 | B15: 1287402 | C15: 8745073 | D15: 3652697 | E15: 605767 | F15: 871065 | G15: 719473 | H15: 467200 | J15: 2147617 | K15: =+SUM(B15:J15) -> 18496294
A16: 2026-03 | B16: 7592596 | C16: 853701 | D16: 3683962 | F16: 977940 | G16: 2081341 | H16: 593130 | J16: 1926212 | K16: =+SUM(B16:J16) -> 17708882
A17: TOTAL ANUAL | B17: =+SUM(B2:B16) -> 65310630 | C17: =+SUM(C2:C16) -> 94488297 | D17: =+SUM(D2:D16) -> 102385877 | E17: =+SUM(E2:E16) -> 7106055 | F17: =+SUM(F2:F16) -> 18400236 | G17: =+SUM(G2:G16) -> 12960873 | H17: =+SUM(H2:H16) -> 3389246 | I17: =+SUM(I2:I16) -> 297715 | J17: =+SUM(J2:J16) -> 26556279 | K17: =+SUM(B17:J17) -> 330895208

Sheet Pendientes
A1: Fecha Pago | B1: Mes Devengo | C1: Descripcion | D1: Monto Total | E1: Nombre DTE | F1: Nombre Cuenta | G1: Codigo | H1: CC
A2: 45323 | B2: 2024-02 | C2: Transf.Internet a 18.732.574-9 | D2: 100000 | G2: =+_xlfn.XLOOKUP(F2,Listas!$B:$B,Listas!$A:$A,0,0) -> 0 | H2: =+_xlfn.XLOOKUP(F2,Listas!$B:$B,Listas!$C:$C,0,0) -> 0
A3: 45323 | B3: 2024-02 | C3: Transf.Internet a 6.551.524-5 | D3: 7880 | G3: =+_xlfn.XLOOKUP(F3,Listas!$B:$B,Listas!$A:$A,0,0) -> 0 | H3: =+_xlfn.XLOOKUP(F3,Listas!$B:$B,Listas!$C:$C,0,0) -> 0
A4: 45324 | B4: 2024-02 | C4: Transf.Internet a 26.715.306-K | D4: 400000 | G4: =+_xlfn.XLOOKUP(F4,Listas!$B:$B,Listas!$A:$A,0,0) -> 0 | H4: =+_xlfn.XLOOKUP(F4,Listas!$B:$B,Listas!$C:$C,0,0) -> 0
A5: 45328 | B5: 2024-02 | C5: Transf.Internet a 14.680.015-7 | D5: 53550 | G5: =+_xlfn.XLOOKUP(F5,Listas!$B:$B,Listas!$A:$A,0,0) -> 0 | H5: =+_xlfn.XLOOKUP(F5,Listas!$B:$B,Listas!$C:$C,0,0) -> 0
A6: 45328 | B6: 2024-02 | C6: Compra Nacional LAPIZ LOPEZ | D6: 5960 | G6: =+_xlfn.XLOOKUP(F6,Listas!$B:$B,Listas!$A:$A,0,0) -> 0 | H6: =+_xlfn.XLOOKUP(F6,Listas!$B:$B,Listas!$C:$C,0,0) -> 0
A7: 45328 | B7: 2024-02 | C7: Compra Nacional NP FLOW | D7: 99979 | G7: =+_xlfn.XLOOKUP(F7,Listas!$B:$B,Listas!$A:$A,0,0) -> 0 | H7: =+_xlfn.XLOOKUP(F7,Listas!$B:$B,Listas!$C:$C,0,0) -> 0
A8: 45330 | B8: 2024-02 | C8: Compra Nacional NP ALVI TOBALABA O | D8: 36736 | G8: =+_xlfn.XLOOKUP(F8,Listas!$B:$B,Listas!$A:$A,0,0) -> 0 | H8: =+_xlfn.XLOOKUP(F8,Listas!$B:$B,Listas!$C:$C,0,0) -> 0
A9: 45330 | B9: 2024-02 | C9: Compra Nacional NP ALVI TOBALABA O | D9: 55104 | G9: =+_xlfn.XLOOKUP(F9,Listas!$B:$B,Listas!$A:$A,0,0) -> 0 | H9: =+_xlfn.XLOOKUP(F9,Listas!$B:$B,Listas!$C:$C,0,0) -> 0
A10: 45344 | B10: 2024-02 | C10: Compra Nacional RAN SPA | D10: 1400 | G10: =+_xlfn.XLOOKUP(F10,Listas!$B:$B,Listas!$A:$A,0,0) -> 0 | H10: =+_xlfn.XLOOKUP(F10,Listas!$B:$B,Listas!$C:$C,0,0) -> 0
A11: 45344 | B11: 2024-02 | C11: Compra Nacional SUCURSAL APUMANQUE | D11: 16250 | G11: =+_xlfn.XLOOKUP(F11,Listas!$B:$B,Listas!$A:$A,0,0) -> 0 | H11: =+_xlfn.XLOOKUP(F11,Listas!$B:$B,Listas!$C:$C,0,0) -> 0
A12: 45345 | B12: 2024-02 | C12: Transf.Internet a 19.076.816-3 | D12: 250000 | G12: =+_xlfn.XLOOKUP(F12,Listas!$B:$B,Listas!$A:$A,0,0) -> 0 | H12: =+_xlfn.XLOOKUP(F12,Listas!$B:$B,Listas!$C:$C,0,0) -> 0
A13: 45348 | B13: 2024-02 | C13: Transf.Internet a 21.572.942-7 | D13: 200000 | G13: =+_xlfn.XLOOKUP(F13,Listas!$B:$B,Listas!$A:$A,0,0) -> 0 | H13: =+_xlfn.XLOOKUP(F13,Listas!$B:$B,Listas!$C:$C,0,0) -> 0
... A22: 45659 | B22: 2025-01 | C22: Compra Inter. NP www.aliexpress.co | D22: 3776 | G22: =+_xlfn.XLOOKUP(F22,Listas!$B:$B,Listas!$A:$A,0,0) -> 0 | H22: =+_xlfn.XLOOKUP(F22,Listas!$B:$B,Listas!$C:$C,0,0) -> 0
A23: 45659 | B23: 2025-01 | C23: Transf.Internet a 77.931.120-1 | D23: 41995 | E23: DTE: Homs | G23: =+_xlfn.XLOOKUP(F23,Listas!$B:$B,Listas!$A:$A,0,0) -> 0 | H23: =+_xlfn.XLOOKUP(F23,Listas!$B:$B,Listas!$C:$C,0,0) -> 0
A24: 45663 | B24: 2025-01 | C24: Transf.Internet a 26.715.306-K | D24: 145000 | G24: =+_xlfn.XLOOKUP(F24,Listas!$B:$B,Listas!$A:$A,0,0) -> 0 | H24: =+_xlfn.XLOOKUP(F24,Listas!$B:$B,Listas!$C:$C,0,0) -> 0
A25: 45663 | B25: 2025-01 | C25: Compra Nacional MERPAGO*3PRODUCTOS | D25: 28380 | G25: =+_xlfn.XLOOKUP(F25,Listas!$B:$B,Listas!$A:$A,0,0) -> 0 | H25: =+_xlfn.XLOOKUP(F25,Listas!$B:$B,Listas!$C:$C,0,0) -> 0
A26: 45663 | B26: 2025-01 | C26: Transf.Internet a 26.715.306-K | D26: 540000 | G26: =+_xlfn.XLOOKUP(F26,Listas!$B:$B,Listas!$A:$A,0,0) -> 0 | H26: =+_xlfn.XLOOKUP(F26,Listas!$B:$B,Listas!$C:$C,0,0) -> 0
A27: 45666 | B27: 2025-01 | C27: Pago Recurrente VD APP-SORTEOS.COM | D27: 9221 | G27: =+_xlfn.XLOOKUP(F27,Listas!$B:$B,Listas!$A:$A,0,0) -> 0 | H27: =+_xlfn.XLOOKUP(F27,Listas!$B:$B,Listas!$C:$C,0,0) -> 0
A28: 45671 | B28: 2025-01 | C28: Compra Nacional NP FLOW | D28: 107656 | G28: =+_xlfn.XLOOKUP(F28,Listas!$B:$B,Listas!$A:$A,0,0) -> 0 | H28: =+_xlfn.XLOOKUP(F28,Listas!$B:$B,Listas!$C:$C,0,0) -> 0
A29: 45671 | B29: 2025-01 | C29: Transf.Internet a 6.551.524-5 | D29: 10940 | G29: =+_xlfn.XLOOKUP(F29,Listas!$B:$B,Listas!$A:$A,0,0) -> 0 | H29: =+_xlfn.XLOOKUP(F29,Listas!$B:$B,Listas!$C:$C,0,0) -> 0
A30: 45671 | B30: 2025-01 | C30: Compra Nacional MERPAGO*9PRODUCTOS | D30: 45654 | G30: =+_xlfn.XLOOKUP(F30,Listas!$B:$B,Listas!$A:$A,0,0) -> 0 | H30: =+_xlfn.XLOOKUP(F30,Listas!$B:$B,Listas!$C:$C,0,0) -> 0
A31: 45679 | B31: 2025-01 | C31: Compra Nacional THE CAKE CLUB | D31: 105160 | G31: =+_xlfn.XLOOKUP(F31,Listas!$B:$B,Listas!$A:$A,0,0) -> 0 | H31: =+_xlfn.XLOOKUP(F31,Listas!$B:$B,Listas!$C:$C,0,0) -> 0
A32: 45679 | B32: 2025-01 | C32: Transf.Internet a 6.551.524-5 | D32: 19606 | G32: =+_xlfn.XLOOKUP(F32,Listas!$B:$B,Listas!$A:$A,0,0) -> 0 | H32: =+_xlfn.XLOOKUP(F32,Listas!$B:$B,Listas!$C:$C,0,0) -> 0
A33: 45684 | B33: 2025-01 | C33: Transf.Internet a 6.551.524-5 | D33: 23154 | G33: =+_xlfn.XLOOKUP(F33,Listas!$B:$B,Listas!$A:$A,0,0) -> 0 | H33: =+_xlfn.XLOOKUP(F33,Listas!$B:$B,Listas!$C:$C,0,0) -> 0
A34: 45685 | B34: 2025-01 | C34: Compra Nacional NP FLOW | D34: 24900 | G34: =+_xlfn.XLOOKUP(F34,Listas!$B:$B,Listas!$A:$A,0,0) -> 0 | H34: =+_xlfn.XLOOKUP(F34,Listas!$B:$B,Listas!$C:$C,0,0) -> 0
A35: 45685 | B35: 2025-01 | C35: Compra Nacional MERPAGO*10PRODUCTO | D35: 58850 | G35: =+_xlfn.XLOOKUP(F35,Listas!$B:$B,Listas!$A:$A,0,0) -> 0 | H35: =+_xlfn.XLOOKUP(F35,Listas!$B:$B,Listas!$C:$C,0,0) -> 0
... A123: 45855 | B123: 2025-07 | C123: Transf.Internet a 22.809.808-6 | D123: 150000 | G123: =+_xlfn.XLOOKUP(F123,Listas!$B:$B,Listas!$A:$A,0,0) -> 0 | H123: =+_xlfn.XLOOKUP(F123,Listas!$B:$B,Listas!$C:$C,0,0) -> 0
A124: 45855 | B124: 2025-07 | C124: Transf.Internet a 77.931.120-1 | D124: 36146 | E124: DTE: Homs | G124: =+_xlfn.XLOOKUP(F124,Listas!$B:$B,Listas!$A:$A,0,0) -> 0 | H124: =+_xlfn.XLOOKUP(F124,Listas!$B:$B,Listas!$C:$C,0,0) -> 0
A125: 45856 | B125: 2025-07 | C125: Compra DP *FALABELLA | D125: 19970 | G125: =+_xlfn.XLOOKUP(F125,Listas!$B:$B,Listas!$A:$A,0,0) -> 0 | H125: =+_xlfn.XLOOKUP(F125,Listas!$B:$B,Listas!$C:$C,0,0) -> 0
A126: 45859 | B126: 2025-07 | C126: Compra SUCURSAL APUMANQU | D126: 7990 | G126: =+_xlfn.XLOOKUP(F126,Listas!$B:$B,Listas!$A:$A,0,0) -> 0 | H126: =+_xlfn.XLOOKUP(F126,Listas!$B:$B,Listas!$C:$C,0,0) -> 0
A127: 45861 | B127: 2025-07 | C127: Compra MERCADOPAGO *BYWA | D127: 2500 | G127: =+_xlfn.XLOOKUP(F127,Listas!$B:$B,Listas!$A:$A,0,0) -> 0 | H127: =+_xlfn.XLOOKUP(F127,Listas!$B:$B,Listas!$C:$C,0,0) -> 0
A128: 45863 | B128: 2025-07 | C128: Compra DP *FALABELLA | D128: 32740 | G128: =+_xlfn.XLOOKUP(F128,Listas!$B:$B,Listas!$A:$A,0,0) -> 0 | H128: =+_xlfn.XLOOKUP(F128,Listas!$B:$B,Listas!$C:$C,0,0) -> 0
A129: 45863 | B129: 2025-07 | C129: Compra DP *FALABELLA | D129: 32740 | G129: =+_xlfn.XLOOKUP(F129,Listas!$B:$B,Listas!$A:$A,0,0) -> 0 | H129: =+_xlfn.XLOOKUP(F129,Listas!$B:$B,Listas!$C:$C,0,0) -> 0
A130: 45863 | B130: 2025-07 | C130: 0065515245 Transf a Luis Felipe Gr | D130: 63000 | G130: =+_xlfn.XLOOKUP(F130,Listas!$B:$B,Listas!$A:$A,0,0) -> 0 | H130: =+_xlfn.XLOOKUP(F130,Listas!$B:$B,Listas!$C:$C,0,0) -> 0
A131: 45866 | B131: 2025-07 | C131: Compra SALA VENTAS VITAC | D131: 2680 | G131: =+_xlfn.XLOOKUP(F131,Listas!$B:$B,Listas!$A:$A,0,0) -> 0 | H131: =+_xlfn.XLOOKUP(F131,Listas!$B:$B,Listas!$C:$C,0,0) -> 0
A132: 45869 | B132: 2025-07 | C132: Transf.Internet a 20.830.554-9 | D132: 100000 | G132: =+_xlfn.XLOOKUP(F132,Listas!$B:$B,Listas!$A:$A,0,0) -> 0 | H132: =+_xlfn.XLOOKUP(F132,Listas!$B:$B,Listas!$C:$C,0,0) -> 0
A133: 45869 | B133: 2025-07 | C133: 0965569405 Transf a Proveedores in | D133: 143844 | G133: =+_xlfn.XLOOKUP(F133,Listas!$B:$B,Listas!$A:$A,0,0) -> 0 | H133: =+_xlfn.XLOOKUP(F133,Listas!$B:$B,Listas!$C:$C,0,0) -> 0
A134: 45869 | B134: 2025-07 | C134: Transf.Internet a 22.809.808-6 | D134: 363000 | G134: =+_xlfn.XLOOKUP(F134,Listas!$B:$B,Listas!$A:$A,0,0) -> 0 | H134: =+_xlfn.XLOOKUP(F134,Listas!$B:$B,Listas!$C:$C,0,0) -> 0
A135: 45869 | B135: 2025-07 | C135: 0765020417 Transf a MUNDO ETIQUETA | D135: 55942 | G135: =+_xlfn.XLOOKUP(F135,Listas!$B:$B,Listas!$A:$A,0,0) -> 0 | H135: =+_xlfn.XLOOKUP(F135,Listas!$B:$B,Listas!$C:$C,0,0) -> 0
A136: 45869 | B136: 2025-07 | C136: 0847368004 Transf a CHAVARRY Y HUG | D136: 85670 | G136: =+_xlfn.XLOOKUP(F136,Listas!$B:$B,Listas!$A:$A,0,0) -> 0 | H136: =+_xlfn.XLOOKUP(F136,Listas!$B:$B,Listas!$C:$C,0,0) -> 0
... A139: 45877 | B139: 2025-08 | C139: Transf.Internet a 7.051.940-2 | D139: 18000 | G139: =+_xlfn.XLOOKUP(F139,Listas!$B:$B,Listas!$A:$A,0,0) -> 0 | H139: =+_xlfn.XLOOKUP(F139,Listas!$B:$B,Listas!$C:$C,0,0) -> 0
A140: 45877 | B140: 2025-08 | C140: Transf.Internet a 77.230.502-8 | D140: 25490 | E140: DTE: COMERCIAL GUTIERREZ AGUILAR SPA | G140: =+_xlfn.XLOOKUP(F140,Listas!$B:$B,Listas!$A:$A,0,0) -> 0 | H140: =+_xlfn.XLOOKUP(F140,Listas!$B:$B,Listas!$C:$C,0,0) -> 0
A141: 45880 | B141: 2025-08 | C141: Transf.Internet a 56.059.620-0 | D141: 252631 | G141: =+_xlfn.XLOOKUP(F141,Listas!$B:$B,Listas!$A:$A,0,0) -> 0 | H141: =+_xlfn.XLOOKUP(F141,Listas!$B:$B,Listas!$C:$C,0,0) -> 0
A142: 45883 | B142: 2025-08 | C142: Transf.Internet a 6.551.524-5 | D142: 58000 | G142: =+_xlfn.XLOOKUP(F142,Listas!$B:$B,Listas!$A:$A,0,0) -> 0 | H142: =+_xlfn.XLOOKUP(F142,Listas!$B:$B,Listas!$C:$C,0,0) -> 0
A143: 45895 | B143: 2025-08 | C143: Compra VIGAHOME SPA | D143: 2000 | G143: =+_xlfn.XLOOKUP(F143,Listas!$B:$B,Listas!$A:$A,0,0) -> 0 | H143: =+_xlfn.XLOOKUP(F143,Listas!$B:$B,Listas!$C:$C,0,0) -> 0
A144: 45895 | B144: 2025-08 | C144: Compra EXPRESS VITACURA | D144: 30055 | G144: =+_xlfn.XLOOKUP(F144,Listas!$B:$B,Listas!$A:$A,0,0) -> 0 | H144: =+_xlfn.XLOOKUP(F144,Listas!$B:$B,Listas!$C:$C,0,0) -> 0
A145: 45896 | B145: 2025-08 | C145: Compra IHELP VITACURA | D145: 10000 | G145: =+_xlfn.XLOOKUP(F145,Listas!$B:$B,Listas!$A:$A,0,0) -> 0 | H145: =+_xlfn.XLOOKUP(F145,Listas!$B:$B,Listas!$C:$C,0,0) -> 0
A146: 45897 | B146: 2025-08 | C146: Transf.Internet a 6.551.524-5 | D146: 3000 | G146: =+_xlfn.XLOOKUP(F146,Listas!$B:$B,Listas!$A:$A,0,0) -> 0 | H146: =+_xlfn.XLOOKUP(F146,Listas!$B:$B,Listas!$C:$C,0,0) -> 0
A147: 45897 | B147: 2025-08 | C147: Transf.Internet a 26.715.306-K | D147: 340000 | G147: =+_xlfn.XLOOKUP(F147,Listas!$B:$B,Listas!$A:$A,0,0) -> 0 | H147: =+_xlfn.XLOOKUP(F147,Listas!$B:$B,Listas!$C:$C,0,0) -> 0
A148: 45897 | B148: 2025-08 | C148: Transf.Internet a 6.551.524-5 | D148: 9000 | G148: =+_xlfn.XLOOKUP(F148,Listas!$B:$B,Listas!$A:$A,0,0) -> 0 | H148: =+_xlfn.XLOOKUP(F148,Listas!$B:$B,Listas!$C:$C,0,0) -> 0
A149: 45901 | B149: 2025-09 | C149: Transf.Internet a 20.998.405-9 | D149: 146975 | G149: =+_xlfn.XLOOKUP(F149,Listas!$B:$B,Listas!$A:$A,0,0) -> 0 | H149: =+_xlfn.XLOOKUP(F149,Listas!$B:$B,Listas!$C:$C,0,0) -> 0
A150: 45901 | B150: 2025-09 | C150: Transf.Internet a 20.830.554-9 | D150: 299735 | G150: =+_xlfn.XLOOKUP(F150,Listas!$B:$B,Listas!$A:$A,0,0) -> 0 | H150: =+_xlfn.XLOOKUP(F150,Listas!$B:$B,Listas!$C:$C,0,0) -> 0
A151: 45901 | B151: 2025-09 | C151: Transf.Internet a 22.809.808-6 | D151: 513000 | G151: =+_xlfn.XLOOKUP(F151,Listas!$B:$B,Listas!$A:$A,0,0) -> 0 | H151: =+_xlfn.XLOOKUP(F151,Listas!$B:$B,Listas!$C:$C,0,0) -> 0
A152: 45902 | B152: 2025-09 | C152: Transf.Internet a 7.051.940-2 | D152: 18000 | G152: =+_xlfn.XLOOKUP(F152,Listas!$B:$B,Listas!$A:$A,0,0) -> 0 | H152: =+_xlfn.XLOOKUP(F152,Listas!$B:$B,Listas!$C:$C,0,0) -> 0
... A201: 45986 | B201: 2025-11 | C201: Compra MP *MAGENTAGLASSC | D201: 10800 | G201: =+_xlfn.XLOOKUP(F201,Listas!$B:$B,Listas!$A:$A,0,0) -> 0 | H201: =+_xlfn.XLOOKUP(F201,Listas!$B:$B,Listas!$C:$C,0,0) -> 0
A202: 45986 | B202: 2025-11 | C202: Transf.Internet a 77.230.502-8 | D202: 25490 | E202: DTE: COMERCIAL GUTIERREZ AGUILAR SPA | G202: =+_xlfn.XLOOKUP(F202,Listas!$B:$B,Listas!$A:$A,0,0) -> 0 | H202: =+_xlfn.XLOOKUP(F202,Listas!$B:$B,Listas!$C:$C,0,0) -> 0
A203: 45988 | B203: 2025-11 | C203: Compra MP *MICOCACOLA | D203: 60020 | G203: =+_xlfn.XLOOKUP(F203,Listas!$B:$B,Listas!$A:$A,0,0) -> 0 | H203: =+_xlfn.XLOOKUP(F203,Listas!$B:$B,Listas!$C:$C,0,0) -> 0
A204: 45993 | B204: 2025-12 | C204: Transf.Internet a 21.920.200-8 | D204: 100000 | G204: =+_xlfn.XLOOKUP(F204,Listas!$B:$B,Listas!$A:$A,0,0) -> 0 | H204: =+_xlfn.XLOOKUP(F204,Listas!$B:$B,Listas!$C:$C,0,0) -> 0
A205: 45993 | B205: 2025-12 | C205: Compra DPS CHILE | D205: 161878 | G205: =+_xlfn.XLOOKUP(F205,Listas!$B:$B,Listas!$A:$A,0,0) -> 0 | H205: =+_xlfn.XLOOKUP(F205,Listas!$B:$B,Listas!$C:$C,0,0) -> 0
A206: 45993 | B206: 2025-12 | C206: Transf.Internet a 18.866.000-2 | D206: 22042 | G206: =+_xlfn.XLOOKUP(F206,Listas!$B:$B,Listas!$A:$A,0,0) -> 0 | H206: =+_xlfn.XLOOKUP(F206,Listas!$B:$B,Listas!$C:$C,0,0) -> 0
A207: 45993 | B207: 2025-12 | C207: Transf.Internet a 20.830.554-9 | D207: 402295 | G207: =+_xlfn.XLOOKUP(F207,Listas!$B:$B,Listas!$A:$A,0,0) -> 0 | H207: =+_xlfn.XLOOKUP(F207,Listas!$B:$B,Listas!$C:$C,0,0) -> 0
A208: 45993 | B208: 2025-12 | C208: Transf.Internet a 18.866.000-2 | D208: 450366 | G208: =+_xlfn.XLOOKUP(F208,Listas!$B:$B,Listas!$A:$A,0,0) -> 0 | H208: =+_xlfn.XLOOKUP(F208,Listas!$B:$B,Listas!$C:$C,0,0) -> 0
A209: 45993 | B209: 2025-12 | C209: Transf.Internet a 27.417.959-7 | D209: 575167 | G209: =+_xlfn.XLOOKUP(F209,Listas!$B:$B,Listas!$A:$A,0,0) -> 0 | H209: =+_xlfn.XLOOKUP(F209,Listas!$B:$B,Listas!$C:$C,0,0) -> 0
A210: 45993 | B210: 2025-12 | C210: Transf.Internet a 77.341.096-8 | D210: 75000 | E210: DTE: MULTISERVICIO S S SPA | G210: =+_xlfn.XLOOKUP(F210,Listas!$B:$B,Listas!$A:$A,0,0) -> 0 | H210: =+_xlfn.XLOOKUP(F210,Listas!$B:$B,Listas!$C:$C,0,0) -> 0
A211: 45995 | B211: 2025-12 | C211: Compra HARRY PLOTTER | D211: 22600 | G211: =+_xlfn.XLOOKUP(F211,Listas!$B:$B,Listas!$A:$A,0,0) -> 0 | H211: =+_xlfn.XLOOKUP(F211,Listas!$B:$B,Listas!$C:$C,0,0) -> 0
A212: 46001 | B212: 2025-12 | C212: Transf.Internet a 77.707.763-5 | D212: 50000 | E212: DTE: INVERSIONES MAS SPA | G212: =+_xlfn.XLOOKUP(F212,Listas!$B:$B,Listas!$A:$A,0,0) -> 0 | H212: =+_xlfn.XLOOKUP(F212,Listas!$B:$B,Listas!$C:$C,0,0) -> 0
A213: 46008 | B213: 2025-12 | C213: Compra STEWARD WEB | D213: 27962 | G213: =+_xlfn.XLOOKUP(F213,Listas!$B:$B,Listas!$A:$A,0,0) -> 0 | H213: =+_xlfn.XLOOKUP(F213,Listas!$B:$B,Listas!$C:$C,0,0) -> 0
A214: 46008 | B214: 2025-12 | C214: Compra KS*NIKE | D214: 56440 | G214: =+_xlfn.XLOOKUP(F214,Listas!$B:$B,Listas!$A:$A,0,0) -> 0 | H214: =+_xlfn.XLOOKUP(F214,Listas!$B:$B,Listas!$C:$C,0,0) -> 0
A215: 46009 | B215: 2025-12 | C215: Compra AGUAS CORDILLERA | D215: 21410 | G215: =+_xlfn.XLOOKUP(F215,Listas!$B:$B,Listas!$A:$A,0,0) -> 0 | H215: =+_xlfn.XLOOKUP(F215,Listas!$B:$B,Listas!$C:$C,0,0) -> 0
A216: 46010 | B216: 2025-12 | C216: Transf.Internet a 25.777.006-0 | D216: 214500 | G216: =+_xlfn.XLOOKUP(F216,Listas!$B:$B,Listas!$A:$A,0,0) -> 0 | H216: =+_xlfn.XLOOKUP(F216,Listas!$B:$B,Listas!$C:$C,0,0) -> 0
A217: 46013 | B217: 2025-12 | C217: Transf.Internet a 17.628.639-3 | D217: 3600 | G217: =+_xlfn.XLOOKUP(F217,Listas!$B:$B,Listas!$A:$A,0,0) -> 0 | H217: =+_xlfn.XLOOKUP(F217,Listas!$B:$B,Listas!$C:$C,0,0) -> 0
A218: 46021 | B218: 2025-12 | C218: Compra DPS CHILE | D218: 73114 | G218: =+_xlfn.XLOOKUP(F218,Listas!$B:$B,Listas!$A:$A,0,0) -> 0 | H218: =+_xlfn.XLOOKUP(F218,Listas!$B:$B,Listas!$C:$C,0,0) -> 0
A219: 46024 | B219: 2026-01 | C219: Transf.Internet a 21.920.200-8 | D219: 100000 | G219: =+_xlfn.XLOOKUP(F219,Listas!$B:$B,Listas!$A:$A,0,0) -> 0 | H219: =+_xlfn.XLOOKUP(F219,Listas!$B:$B,Listas!$C:$C,0,0) -> 0
A220: 46024 | B220: 2026-01 | C220: Transf.Internet a 21.081.516-3 | D220: 100000 | G220: =+_xlfn.XLOOKUP(F220,Listas!$B:$B,Listas!$A:$A,0,0) -> 0 | H220: =+_xlfn.XLOOKUP(F220,Listas!$B:$B,Listas!$C:$C,0,0) -> 0
A221: 46024 | B221: 2026-01 | C221: Transf.Internet a 21.081.516-3 | D221: 100000 | G221: =+_xlfn.XLOOKUP(F221,Listas!$B:$B,Listas!$A:$A,0,0) -> 0 | H221: =+_xlfn.XLOOKUP(F221,Listas!$B:$B,Listas!$C:$C,0,0) -> 0
A222: 46024 | B222: 2026-01 | C222: Transf.Internet a 18.866.000-2 | D222: 200000 | G222: =+_xlfn.XLOOKUP(F222,Listas!$B:$B,Listas!$A:$A,0,0) -> 0 | H222: =+_xlfn.XLOOKUP(F222,Listas!$B:$B,Listas!$C:$C,0,0) -> 0
A223: 46024 | B223: 2026-01 | C223: Transf.Internet a 21.920.200-8 | D223: 25000 | G223: =+_xlfn.XLOOKUP(F223,Listas!$B:$B,Listas!$A:$A,0,0) -> 0 | H223: =+_xlfn.XLOOKUP(F223,Listas!$B:$B,Listas!$C:$C,0,0) -> 0
A224: 46024 | B224: 2026-01 | C224: Transf.Internet a 20.550.382-k | D224: 35000 | G224: =+_xlfn.XLOOKUP(F224,Listas!$B:$B,Listas!$A:$A,0,0) -> 0 | H224: =+_xlfn.XLOOKUP(F224,Listas!$B:$B,Listas!$C:$C,0,0) -> 0
... A242: 46037 | B242: 2026-01 | C242: Compra DP *IKEA.COM | D242: 64450 | G242: =+_xlfn.XLOOKUP(F242,Listas!$B:$B,Listas!$A:$A,0,0) -> 0 | H242: =+_xlfn.XLOOKUP(F242,Listas!$B:$B,Listas!$C:$C,0,0) -> 0
A243: 46037 | B243: 2026-01 | C243: Transf.Internet a 96.794.400-9 | D243: 743750 | E243: DTE: COMERCIALIZADORA Y CONSTRUCTORA MACUL S A | G243: =+_xlfn.XLOOKUP(F243,Listas!$B:$B,Listas!$A:$A,0,0) -> 0 | H243: =+_xlfn.XLOOKUP(F243,Listas!$B:$B,Listas!$C:$C,0,0) -> 0
A244: 46038 | B244: 2026-01 | C244: Compra PLAZA LAS CONDES | D244: 1850 | G244: =+_xlfn.XLOOKUP(F244,Listas!$B:$B,Listas!$A:$A,0,0) -> 0 | H244: =+_xlfn.XLOOKUP(F244,Listas!$B:$B,Listas!$C:$C,0,0) -> 0
A245: 46038 | B245: 2026-01 | C245: Compra M LAS CONDES TESO | D245: 69751 | G245: =+_xlfn.XLOOKUP(F245,Listas!$B:$B,Listas!$A:$A,0,0) -> 0 | H245: =+_xlfn.XLOOKUP(F245,Listas!$B:$B,Listas!$C:$C,0,0) -> 0
A246: 46038 | B246: 2026-01 | C246: Cargo Mercado Capitales | D246: 72885 | G246: =+_xlfn.XLOOKUP(F246,Listas!$B:$B,Listas!$A:$A,0,0) -> 0 | H246: =+_xlfn.XLOOKUP(F246,Listas!$B:$B,Listas!$C:$C,0,0) -> 0
A247: 46041 | B247: 2026-01 | C247: Compra MULTISERVICE | D247: 37400 | G247: =+_xlfn.XLOOKUP(F247,Listas!$B:$B,Listas!$A:$A,0,0) -> 0 | H247: =+_xlfn.XLOOKUP(F247,Listas!$B:$B,Listas!$C:$C,0,0) -> 0
A248: 46042 | B248: 2026-01 | C248: Compra COPYEXPRESS | D248: 13599 | G248: =+_xlfn.XLOOKUP(F248,Listas!$B:$B,Listas!$A:$A,0,0) -> 0 | H248: =+_xlfn.XLOOKUP(F248,Listas!$B:$B,Listas!$C:$C,0,0) -> 0
A249: 46042 | B249: 2026-01 | C249: Transf.Internet a 18.831.462-7 | D249: 300000 | G249: =+_xlfn.XLOOKUP(F249,Listas!$B:$B,Listas!$A:$A,0,0) -> 0 | H249: =+_xlfn.XLOOKUP(F249,Listas!$B:$B,Listas!$C:$C,0,0) -> 0
A250: 46042 | B250: 2026-01 | C250: Compra M LAS CONDES TESO | D250: 63217 | G250: =+_xlfn.XLOOKUP(F250,Listas!$B:$B,Listas!$A:$A,0,0) -> 0 | H250: =+_xlfn.XLOOKUP(F250,Listas!$B:$B,Listas!$C:$C,0,0) -> 0
A251: 46043 | B251: 2026-01 | C251: Transf.Internet a 28.508.344-3 | D251: 214500 | G251: =+_xlfn.XLOOKUP(F251,Listas!$B:$B,Listas!$A:$A,0,0) -> 0 | H251: =+_xlfn.XLOOKUP(F251,Listas!$B:$B,Listas!$C:$C,0,0) -> 0
A252: 46043 | B252: 2026-01 | C252: Transf.Internet a 17.598.442-9 | D252: 25380 | G252: =+_xlfn.XLOOKUP(F252,Listas!$B:$B,Listas!$A:$A,0,0) -> 0 | H252: =+_xlfn.XLOOKUP(F252,Listas!$B:$B,Listas!$C:$C,0,0) -> 0
A253: 46044 | B253: 2026-01 | C253: Compra IKEA OPEN KENNEDY | D253: 19990 | G253: =+_xlfn.XLOOKUP(F253,Listas!$B:$B,Listas!$A:$A,0,0) -> 0 | H253: =+_xlfn.XLOOKUP(F253,Listas!$B:$B,Listas!$C:$C,0,0) -> 0
A254: 46044 | B254: 2026-01 | C254: Compra VIDA PARQUE | D254: 4800 | G254: =+_xlfn.XLOOKUP(F254,Listas!$B:$B,Listas!$A:$A,0,0) -> 0 | H254: =+_xlfn.XLOOKUP(F254,Listas!$B:$B,Listas!$C:$C,0,0) -> 0
A255: 46055 | B255: 2026-02 | C255: Transf.Internet a 20.550.382-k | D255: 100000 | G255: =+_xlfn.XLOOKUP(F255,Listas!$B:$B,Listas!$A:$A,0,0) -> 0 | H255: =+_xlfn.XLOOKUP(F255,Listas!$B:$B,Listas!$C:$C,0,0) -> 0
... A263: 46056 | B263: 2026-02 | C263: Transf.Internet a 21.575.375-1 | D263: 25650 | G263: =+_xlfn.XLOOKUP(F263,Listas!$B:$B,Listas!$A:$A,0,0) -> 0 | H263: =+_xlfn.XLOOKUP(F263,Listas!$B:$B,Listas!$C:$C,0,0) -> 0
A264: 46057 | B264: 2026-02 | C264: Transf.Internet a 96.794.400-9 | D264: 743750 | E264: DTE: COMERCIALIZADORA Y CONSTRUCTORA MACUL S A | G264: =+_xlfn.XLOOKUP(F264,Listas!$B:$B,Listas!$A:$A,0,0) -> 0 | H264: =+_xlfn.XLOOKUP(F264,Listas!$B:$B,Listas!$C:$C,0,0) -> 0
A265: 46063 | B265: 2026-02 | C265: Pago Automático T. de Crédito | D265: 5000 | G265: =+_xlfn.XLOOKUP(F265,Listas!$B:$B,Listas!$A:$A,0,0) -> 0 | H265: =+_xlfn.XLOOKUP(F265,Listas!$B:$B,Listas!$C:$C,0,0) -> 0
A266: 46073 | B266: 2026-02 | C266: Compra NEWTREE | D266: 4170 | G266: =+_xlfn.XLOOKUP(F266,Listas!$B:$B,Listas!$A:$A,0,0) -> 0 | H266: =+_xlfn.XLOOKUP(F266,Listas!$B:$B,Listas!$C:$C,0,0) -> 0
A267: 46078 | B267: 2026-02 | C267: Compra DP *FALABELLA | D267: 15930 | G267: =+_xlfn.XLOOKUP(F267,Listas!$B:$B,Listas!$A:$A,0,0) -> 0 | H267: =+_xlfn.XLOOKUP(F267,Listas!$B:$B,Listas!$C:$C,0,0) -> 0
A268: 46078 | B268: 2026-02 | C268: Transf.Internet a 78.107.847-6 | D268: 45839 | G268: =+_xlfn.XLOOKUP(F268,Listas!$B:$B,Listas!$A:$A,0,0) -> 0 | H268: =+_xlfn.XLOOKUP(F268,Listas!$B:$B,Listas!$C:$C,0,0) -> 0
A269: 46079 | B269: 2026-02 | C269: Compra MERCADOPAGO *ADAB | D269: 39024 | G269: =+_xlfn.XLOOKUP(F269,Listas!$B:$B,Listas!$A:$A,0,0) -> 0 | H269: =+_xlfn.XLOOKUP(F269,Listas!$B:$B,Listas!$C:$C,0,0) -> 0
...

Sheet Listas
A1: Codigo | B1: Nombre | C1: CC
A2: 1.1.1 | B2: Ingredientes | C2: CC1
A3: 1.1.2 | B3: Packaging | C3: CC1
A4: 1.1.3 | B4: Equipamiento de Cocina | C4: CC1
A5: 1.2.1 | B5: Sueldos con Contrato | C5: CC2
A6: 1.2.2 | B6: Honorarios | C6: CC2
A7: 1.2.3 | B7: Asesoria Contable | C7: CC2
A8: 1.2.4 | B8: Uniformes Personal | C8: CC2
A9: 1.2.5 | B9: Prestamos Personal | C9: CC2
A10: 1.3.1 | B10: Arriendo Local | C10: CC3
A11: 1.3.2 | B11: Agua | C11: CC3
A12: 1.3.3 | B12: Luz | C12: CC3
... A40: 1.9.5 | B40: Gastos Bancarios | C40: CC9
A42: 1.8.3 | B42: Plataformas Digitales (Comision)
A43: CC9 | B43: Impuestos
A44: 1.9.1 | B44: IVA Neto (F29)
A45: 1.9.2 | B45: Provision Impuesto a la Renta
A46: 1.9.3 | B46: Impuesto a la Renta
A47: 1.9.4 | B47: Patente Comercial
A48: 1.9.5 | B48: Gastos Bancarios
