Workbook

Sheet 1. INGRESOS
A1: Fecha | B1: Mes Devengo | C1: Cliente | D1: Descripcion | E1: Monto Total | F1: Tipo Doc | G1: IVA | H1: Monto Neto | I1: Cuenta | J1: Nombre Cuenta | K1: Canal
A2: 45658 | B2: 2025-01 | C2: Rebeca Uribe Fridman | D2: CANELÉ TRADICIONAL | E2: 23790 | F2: B | G2: 3798 | H2: 19992 | I2: 3.2 | J2: Ventas Personas (B2C) | K2: CH2
A3: 45659 | B3: 2025-01 | C3: GALVEZ Y HEUSSER SPA | D3: HORECA CATERING | E3: 71035 | F3: F | G3: 11342 | H3: 59693 | I3: 3.1 | J3: Ventas HoReCa | K3: CH1
A4: 45659 | B4: 2025-01 | C4: HUERTO SUR LIMITADA | D4: HORECA CAFETERIA | E4: 89589 | F4: F | G4: 14304 | H4: 75285 | I4: 3.1 | J4: Ventas HoReCa | K4: CH1
A5: 45659 | B5: 2025-01 | C5: Sin cliente | D5: CANELÉ TRADICIONAL | E5: 11120 | F5: B | G5: 1775 | H5: 9345 | I5: 3.2 | J5: Ventas Personas (B2C) | K5: CH2
A6: 45659 | B6: 2025-01 | C6: CAFÉ UNDER SPA | D6: HORECA CAFETERIA | E6: 63990 | F6: F | G6: 10217 | H6: 53773 | I6: 3.1 | J6: Ventas HoReCa | K6: CH1
A7: 45659 | B7: 2025-01 | C7: Carolina Rivera | D7: PACKS GOURMET | E7: 24786 | F7: B | G7: 3957 | H7: 20829 | I7: 3.2 | J7: Ventas Personas (B2C) | K7: CH2
A8: 45659 | B8: 2025-01 | C8: Santa María spa | D8: HORECA CAFETERIA | E8: 178711 | F8: F | G8: 28534 | H8: 150177 | I8: 3.1 | J8: Ventas HoReCa | K8: CH1
A9: 45659 | B9: 2025-01 | C9: Nicole Stefanic | D9: CANELE SIN AZUCAR | E9: 28289 | F9: B | G9: 4517 | H9: 23772 | I9: 3.2 | J9: Ventas Personas (B2C) | K9: CH2
A10: 45659 | B10: 2025-01 | C10: Candelaria Mackay | D10: PACKS GOURMET | E10: 21705 | F10: B | G10: 3466 | H10: 18239 | I10: 3.2 | J10: Ventas Personas (B2C) | K10: CH2
A11: 45659 | B11: 2025-01 | C11: Sin cliente | D11: CANELÉ TRADICIONAL | E11: 13900 | F11: B | G11: 2219 | H11: 11681 | I11: 3.2 | J11: Ventas Personas (B2C) | K11: CH2
A12: 45660 | B12: 2025-01 | C12: Belén Pérez Silva | D12: CANELÉ TRADICIONAL | E12: 17890 | F12: B | G12: 2856 | H12: 15034 | I12: 3.2 | J12: Ventas Personas (B2C) | K12: CH2
A13: 45660 | B13: 2025-01 | C13: Antonio Maino | D13: CANELÉ TRADICIONAL | E13: 17890 | F13: B | G13: 2856 | H13: 15034 | I13: 3.2 | J13: Ventas Personas (B2C) | K13: CH2
... A7248: 46157 | B7248: 2026-05 | C7248: BLUE OAK COFFE SPA | D7248: HORECA CAFETERIA | E7248: 77564 | F7248: F | G7248: 12384 | H7248: 65180 | I7248: 3.1 | J7248: Ventas HoReCa | K7248: CH1

Sheet 2. EGRESOS
A1: Fecha Pago | B1: Mes Devengo | C1: Descripcion | D1: Proveedor | E1: Monto Total | F1: Tipo Doc | G1: Forma Pago | H1: Nombre Cuenta | I1: IVA | J1: Monto Neto | K1: Cuenta | L1: CC
A2: 46113 | B2: 2026-03 | C2: Sueldo 22.520.465-9 - Carolina Gutierrez | E2: 1127159 | G2: Debito | H2: Sueldos con Contrato | I2: =IF(F2="F",ROUND(E2*0.19/1.19,0),0) | J2: =IF(E2="","",E2-I2) | K2: =+_xlfn.XLOOKUP(Tabla1[[#This Row],[Nombre Cuenta]],PLAN_CUENTAS!$B$2:$B$100,PLAN_CUENTAS!$A$2:$A$100,0,0) | L2: =+_xlfn.XLOOKUP(Tabla1[[#This Row],[Nombre Cuenta]],PLAN_CUENTAS!$B$2:$B$100,PLAN_CUENTAS!$C$2:$C$100,0,0)
A3: 46113 | B3: 2026-03 | C3: Sueldo 22.520.465-9 - Carolina Gutierrez | E3: 825400 | G3: Debito | H3: Sueldos con Contrato | I3: =IF(F3="F",ROUND(E3*0.19/1.19,0),0) | J3: =IF(E3="","",E3-I3) | K3: =+_xlfn.XLOOKUP(Tabla1[[#This Row],[Nombre Cuenta]],PLAN_CUENTAS!$B$2:$B$100,PLAN_CUENTAS!$A$2:$A$100,0,0) | L3: =+_xlfn.XLOOKUP(Tabla1[[#This Row],[Nombre Cuenta]],PLAN_CUENTAS!$B$2:$B$100,PLAN_CUENTAS!$C$2:$C$100,0,0)
A4: 46113 | B4: 2026-03 | C4: Sueldo 17.083.572-7 - M Ignacia Grez | E4: 800000 | G4: Debito | H4: Sueldos con Contrato | I4: =IF(F4="F",ROUND(E4*0.19/1.19,0),0) | J4: =IF(E4="","",E4-I4) | K4: =+_xlfn.XLOOKUP(Tabla1[[#This Row],[Nombre Cuenta]],PLAN_CUENTAS!$B$2:$B$100,PLAN_CUENTAS!$A$2:$A$100,0,0) | L4: =+_xlfn.XLOOKUP(Tabla1[[#This Row],[Nombre Cuenta]],PLAN_CUENTAS!$B$2:$B$100,PLAN_CUENTAS!$C$2:$C$100,0,0)
A5: 46113 | B5: 2026-03 | C5: Sueldo 19.324.205-7 - Catalina Cuevas | E5: 700000 | G5: Debito | H5: Honorarios | I5: =IF(F5="F",ROUND(E5*0.19/1.19,0),0) | J5: =IF(E5="","",E5-I5) | K5: =+_xlfn.XLOOKUP(Tabla1[[#This Row],[Nombre Cuenta]],PLAN_CUENTAS!$B$2:$B$100,PLAN_CUENTAS!$A$2:$A$100,0,0) | L5: =+_xlfn.XLOOKUP(Tabla1[[#This Row],[Nombre Cuenta]],PLAN_CUENTAS!$B$2:$B$100,PLAN_CUENTAS!$C$2:$C$100,0,0)
A6: 46113 | B6: 2026-03 | C6: Sueldo 21.093.602-5 - Nataly Morales | E6: 682252 | G6: Debito | H6: Sueldos con Contrato | I6: =IF(F6="F",ROUND(E6*0.19/1.19,0),0) | J6: =IF(E6="","",E6-I6) | K6: =+_xlfn.XLOOKUP(Tabla1[[#This Row],[Nombre Cuenta]],PLAN_CUENTAS!$B$2:$B$100,PLAN_CUENTAS!$A$2:$A$100,0,0) | L6: =+_xlfn.XLOOKUP(Tabla1[[#This Row],[Nombre Cuenta]],PLAN_CUENTAS!$B$2:$B$100,PLAN_CUENTAS!$C$2:$C$100,0,0)
A7: 46113 | B7: 2026-03 | C7: Sueldo 18.866.000-2 - Camila Aguilera | E7: 627742 | G7: Debito | H7: Sueldos con Contrato | I7: =IF(F7="F",ROUND(E7*0.19/1.19,0),0) | J7: =IF(E7="","",E7-I7) | K7: =+_xlfn.XLOOKUP(Tabla1[[#This Row],[Nombre Cuenta]],PLAN_CUENTAS!$B$2:$B$100,PLAN_CUENTAS!$A$2:$A$100,0,0) | L7: =+_xlfn.XLOOKUP(Tabla1[[#This Row],[Nombre Cuenta]],PLAN_CUENTAS!$B$2:$B$100,PLAN_CUENTAS!$C$2:$C$100,0,0)
A8: 46113 | B8: 2026-03 | C8: Sueldo 10.325.328-4 - Patricia Guijuelos | E8: 551261 | G8: Debito | H8: Sueldos con Contrato | I8: =IF(F8="F",ROUND(E8*0.19/1.19,0),0) | J8: =IF(E8="","",E8-I8) | K8: =+_xlfn.XLOOKUP(Tabla1[[#This Row],[Nombre Cuenta]],PLAN_CUENTAS!$B$2:$B$100,PLAN_CUENTAS!$A$2:$A$100,0,0) | L8: =+_xlfn.XLOOKUP(Tabla1[[#This Row],[Nombre Cuenta]],PLAN_CUENTAS!$B$2:$B$100,PLAN_CUENTAS!$C$2:$C$100,0,0)
A9: 46113 | B9: 2026-03 | C9: Sueldo 20.550.382-k - Veronica Alvarez | E9: 456803 | G9: Debito | H9: Honorarios | I9: =IF(F9="F",ROUND(E9*0.19/1.19,0),0) | J9: =IF(E9="","",E9-I9) | K9: =+_xlfn.XLOOKUP(Tabla1[[#This Row],[Nombre Cuenta]],PLAN_CUENTAS!$B$2:$B$100,PLAN_CUENTAS!$A$2:$A$100,0,0) | L9: =+_xlfn.XLOOKUP(Tabla1[[#This Row],[Nombre Cuenta]],PLAN_CUENTAS!$B$2:$B$100,PLAN_CUENTAS!$C$2:$C$100,0,0)
A10: 46113 | B10: 2026-03 | C10: Sueldo 18.831.462-7 - Katherine Chamorro | E10: 236667 | G10: Debito | H10: Honorarios | I10: =IF(F10="F",ROUND(E10*0.19/1.19,0),0) | J10: =IF(E10="","",E10-I10) | K10: =+_xlfn.XLOOKUP(Tabla1[[#This Row],[Nombre Cuenta]],PLAN_CUENTAS!$B$2:$B$100,PLAN_CUENTAS!$A$2:$A$100,0,0) | L10: =+_xlfn.XLOOKUP(Tabla1[[#This Row],[Nombre Cuenta]],PLAN_CUENTAS!$B$2:$B$100,PLAN_CUENTAS!$C$2:$C$100,0,0)
A11: 46113 | B11: 2026-03 | C11: Sueldo 21.920.200-8 - Catalina Arriagada | E11: 213750 | G11: Debito | H11: Honorarios | I11: =IF(F11="F",ROUND(E11*0.19/1.19,0),0) | J11: =IF(E11="","",E11-I11) | K11: =+_xlfn.XLOOKUP(Tabla1[[#This Row],[Nombre Cuenta]],PLAN_CUENTAS!$B$2:$B$100,PLAN_CUENTAS!$A$2:$A$100,0,0) | L11: =+_xlfn.XLOOKUP(Tabla1[[#This Row],[Nombre Cuenta]],PLAN_CUENTAS!$B$2:$B$100,PLAN_CUENTAS!$C$2:$C$100,0,0)
A12: 46113 | B12: 2026-03 | C12: Sueldo 21.832.228-K - Emilia Bravo | E12: 177975 | G12: Debito | H12: Honorarios | I12: =IF(F12="F",ROUND(E12*0.19/1.19,0),0) | J12: =IF(E12="","",E12-I12) | K12: =+_xlfn.XLOOKUP(Tabla1[[#This Row],[Nombre Cuenta]],PLAN_CUENTAS!$B$2:$B$100,PLAN_CUENTAS!$A$2:$A$100,0,0) | L12: =+_xlfn.XLOOKUP(Tabla1[[#This Row],[Nombre Cuenta]],PLAN_CUENTAS!$B$2:$B$100,PLAN_CUENTAS!$C$2:$C$100,0,0)
A13: 46113 | B13: 2026-03 | C13: Sueldo 21.380.644-0 - Elizabeth Caceres | E13: 146718 | G13: Debito | H13: Honorarios | I13: =IF(F13="F",ROUND(E13*0.19/1.19,0),0) | J13: =IF(E13="","",E13-I13) | K13: =+_xlfn.XLOOKUP(Tabla1[[#This Row],[Nombre Cuenta]],PLAN_CUENTAS!$B$2:$B$100,PLAN_CUENTAS!$A$2:$A$100,0,0) | L13: =+_xlfn.XLOOKUP(Tabla1[[#This Row],[Nombre Cuenta]],PLAN_CUENTAS!$B$2:$B$100,PLAN_CUENTAS!$C$2:$C$100,0,0)
A14: 46113 | B14: 2026-04 | C14: Mensualidad Plataforma Bsale | D14: Bsale Chile S.A | E14: 137494 | F14: F | G14: Debito | H14: Plataformas Digitales | I14: =IF(F14="F",ROUND(E14*0.19/1.19,0),0) | J14: =IF(E14="","",E14-I14) | K14: =+_xlfn.XLOOKUP(Tabla1[[#This Row],[Nombre Cuenta]],PLAN_CUENTAS!$B$2:$B$100,PLAN_CUENTAS!$A$2:$A$100,0,0) | L14: =+_xlfn.XLOOKUP(Tabla1[[#This Row],[Nombre Cuenta]],PLAN_CUENTAS!$B$2:$B$100,PLAN_CUENTAS!$C$2:$C$100,0,0)
A15: 46113 | B15: 2026-04 | C15: Google Workspace (7 correos) | D15: Google Workspace | E15: 111702 | F15: F | G15: Debito | H15: Plataformas Digitales | I15: =IF(F15="F",ROUND(E15*0.19/1.19,0),0) | J15: =IF(E15="","",E15-I15) | K15: =+_xlfn.XLOOKUP(Tabla1[[#This Row],[Nombre Cuenta]],PLAN_CUENTAS!$B$2:$B$100,PLAN_CUENTAS!$A$2:$A$100,0,0) | L15: =+_xlfn.XLOOKUP(Tabla1[[#This Row],[Nombre Cuenta]],PLAN_CUENTAS!$B$2:$B$100,PLAN_CUENTAS!$C$2:$C$100,0,0)
A16: 46113 | B16: 2026-03 | C16: Sueldo - 21.575.375-1 - Martina Jorquera | E16: 100000 | G16: Debito | H16: Honorarios | I16: =IF(F16="F",ROUND(E16*0.19/1.19,0),0) | J16: =IF(E16="","",E16-I16) | K16: =+_xlfn.XLOOKUP(Tabla1[[#This Row],[Nombre Cuenta]],PLAN_CUENTAS!$B$2:$B$100,PLAN_CUENTAS!$A$2:$A$100,0,0) | L16: =+_xlfn.XLOOKUP(Tabla1[[#This Row],[Nombre Cuenta]],PLAN_CUENTAS!$B$2:$B$100,PLAN_CUENTAS!$C$2:$C$100,0,0)
A17: 46113 | B17: 2026-04 | C17: Transf.Internet a 76.803.503-2 | D17: Sticker Shop | E17: 99853 | F17: S | G17: Debito | H17: Packaging | I17: =IF(F17="F",ROUND(E17*0.19/1.19,0),0) | J17: =IF(E17="","",E17-I17) | K17: =+_xlfn.XLOOKUP(Tabla1[[#This Row],[Nombre Cuenta]],PLAN_CUENTAS!$B$2:$B$100,PLAN_CUENTAS!$A$2:$A$100,0,0) | L17: =+_xlfn.XLOOKUP(Tabla1[[#This Row],[Nombre Cuenta]],PLAN_CUENTAS!$B$2:$B$100,PLAN_CUENTAS!$C$2:$C$100,0,0)
A18: 46113 | B18: 2026-04 | C18: Transf.Internet a 77.190.532-3 | D18: Sticker Print | E18: 64260 | F18: F | G18: Debito | H18: Packaging | I18: =IF(F18="F",ROUND(E18*0.19/1.19,0),0) | J18: =IF(E18="","",E18-I18) | K18: =+_xlfn.XLOOKUP(Tabla1[[#This Row],[Nombre Cuenta]],PLAN_CUENTAS!$B$2:$B$100,PLAN_CUENTAS!$A$2:$A$100,0,0) | L18: =+_xlfn.XLOOKUP(Tabla1[[#This Row],[Nombre Cuenta]],PLAN_CUENTAS!$B$2:$B$100,PLAN_CUENTAS!$C$2:$C$100,0,0)
A19: 46113 | B19: 2026-04 | C19: Compra TOKU *VERISURE | D19: Verisure | E19: 59265 | F19: F | G19: Debito | H19: Seguridad | I19: =IF(F19="F",ROUND(E19*0.19/1.19,0),0) | J19: =IF(E19="","",E19-I19) | K19: =+_xlfn.XLOOKUP(Tabla1[[#This Row],[Nombre Cuenta]],PLAN_CUENTAS!$B$2:$B$100,PLAN_CUENTAS!$A$2:$A$100,0,0) | L19: =+_xlfn.XLOOKUP(Tabla1[[#This Row],[Nombre Cuenta]],PLAN_CUENTAS!$B$2:$B$100,PLAN_CUENTAS!$C$2:$C$100,0,0)
A20: 46113 | B20: 2026-04 | C20: Estampado Camisa Despachador B2B | D20: VINCULO EXPERIENCE SPA | E20: 7599 | F20: F | G20: Debito | H20: Uniformes Personal | I20: =IF(F20="F",ROUND(E20*0.19/1.19,0),0) | J20: =IF(E20="","",E20-I20) | K20: =+_xlfn.XLOOKUP(Tabla1[[#This Row],[Nombre Cuenta]],PLAN_CUENTAS!$B$2:$B$100,PLAN_CUENTAS!$A$2:$A$100,0,0) | L20: =+_xlfn.XLOOKUP(Tabla1[[#This Row],[Nombre Cuenta]],PLAN_CUENTAS!$B$2:$B$100,PLAN_CUENTAS!$C$2:$C$100,0,0)
A21: 46113 | B21: 2026-04 | C21: Transf.Internet a 77.512.163-7 | D21: Ecourier | E21: 3332 | F21: F | G21: Debito | H21: Despachos B2C | I21: =IF(F21="F",ROUND(E21*0.19/1.19,0),0) | J21: =IF(E21="","",E21-I21) | K21: =+_xlfn.XLOOKUP(Tabla1[[#This Row],[Nombre Cuenta]],PLAN_CUENTAS!$B$2:$B$100,PLAN_CUENTAS!$A$2:$A$100,0,0) | L21: =+_xlfn.XLOOKUP(Tabla1[[#This Row],[Nombre Cuenta]],PLAN_CUENTAS!$B$2:$B$100,PLAN_CUENTAS!$C$2:$C$100,0,0)
A22: 46113 | B22: 2026-04 | C22: Compra MP *CABIFY2614VSC | D22: Cabify | E22: 2679 | F22: F | G22: Debito | H22: Transporte Personas (Empleados) | I22: =IF(F22="F",ROUND(E22*0.19/1.19,0),0) | J22: =IF(E22="","",E22-I22) | K22: =+_xlfn.XLOOKUP(Tabla1[[#This Row],[Nombre Cuenta]],PLAN_CUENTAS!$B$2:$B$100,PLAN_CUENTAS!$A$2:$A$100,0,0) | L22: =+_xlfn.XLOOKUP(Tabla1[[#This Row],[Nombre Cuenta]],PLAN_CUENTAS!$B$2:$B$100,PLAN_CUENTAS!$C$2:$C$100,0,0)
A23: 46113 | B23: 2026-04 | C23: Compra MP *CABIFY2614NSZ | D23: Cabify | E23: 2660 | F23: F | G23: Debito | H23: Transporte Personas (Empleados) | I23: =IF(F23="F",ROUND(E23*0.19/1.19,0),0) | J23: =IF(E23="","",E23-I23) | K23: =+_xlfn.XLOOKUP(Tabla1[[#This Row],[Nombre Cuenta]],PLAN_CUENTAS!$B$2:$B$100,PLAN_CUENTAS!$A$2:$A$100,0,0) | L23: =+_xlfn.XLOOKUP(Tabla1[[#This Row],[Nombre Cuenta]],PLAN_CUENTAS!$B$2:$B$100,PLAN_CUENTAS!$C$2:$C$100,0,0)
A24: 46114 | B24: 2026-04 | C24: Transf.Internet a 15.411.174-3 | D24: TECNOLOGIA VERDE SPA | E24: 70000 | F24: F | G24: Debito | H24: Despachos B2B (Gaspar) | I24: =IF(F24="F",ROUND(E24*0.19/1.19,0),0) | J24: =IF(E24="","",E24-I24) | K24: =+_xlfn.XLOOKUP(Tabla1[[#This Row],[Nombre Cuenta]],PLAN_CUENTAS!$B$2:$B$100,PLAN_CUENTAS!$A$2:$A$100,0,0) | L24: =+_xlfn.XLOOKUP(Tabla1[[#This Row],[Nombre Cuenta]],PLAN_CUENTAS!$B$2:$B$100,PLAN_CUENTAS!$C$2:$C$100,0,0)
A25: 46114 | B25: 2026-05 | C25: 76.839.579-9 - Tarjetas PPT 50% del total | D25: SERVICIOS DIGITALES E IMPRESIÓN OSEG SPA | E25: 60150 | F25: F | G25: Debito | H25: Packaging | I25: =IF(F25="F",ROUND(E25*0.19/1.19,0),0) | J25: =IF(E25="","",E25-I25) | K25: =+_xlfn.XLOOKUP(Tabla1[[#This Row],[Nombre Cuenta]],PLAN_CUENTAS!$B$2:$B$100,PLAN_CUENTAS!$A$2:$A$100,0,0) | L25: =+_xlfn.XLOOKUP(Tabla1[[#This Row],[Nombre Cuenta]],PLAN_CUENTAS!$B$2:$B$100,PLAN_CUENTAS!$C$2:$C$100,0,0)
A26: 46114 | B26: 2026-04 | C26: Vajilla faltante terraza | D26: LIDER | E26: 37790 | F26: F | G26: Debito | H26: Equipamiento Local | I26: =IF(F26="F",ROUND(E26*0.19/1.19,0),0) | J26: =IF(E26="","",E26-I26) | K26: =+_xlfn.XLOOKUP(Tabla1[[#This Row],[Nombre Cuenta]],PLAN_CUENTAS!$B$2:$B$100,PLAN_CUENTAS!$A$2:$A$100,0,0) | L26: =+_xlfn.XLOOKUP(Tabla1[[#This Row],[Nombre Cuenta]],PLAN_CUENTAS!$B$2:$B$100,PLAN_CUENTAS!$C$2:$C$100,0,0)
A27: 46114 | B27: 2026-04 | C27: Compra OPENAI *CHATGPT S | D27: CHATGPT | E27: 18825 | G27: Debito | H27: Plataformas Digitales | I27: =IF(F27="F",ROUND(E27*0.19/1.19,0),0) | J27: =IF(E27="","",E27-I27) | K27: =+_xlfn.XLOOKUP(Tabla1[[#This Row],[Nombre Cuenta]],PLAN_CUENTAS!$B$2:$B$100,PLAN_CUENTAS!$A$2:$A$100,0,0) | L27: =+_xlfn.XLOOKUP(Tabla1[[#This Row],[Nombre Cuenta]],PLAN_CUENTAS!$B$2:$B$100,PLAN_CUENTAS!$C$2:$C$100,0,0)
A28: 46114 | B28: 2026-04 | C28: Compra MP *CABIFY2614X8T | D28: Cabify | E28: 2846 | F28: F | G28: Debito | H28: Transporte Personas (Empleados) | I28: =IF(F28="F",ROUND(E28*0.19/1.19,0),0) | J28: =IF(E28="","",E28-I28) | K28: =+_xlfn.XLOOKUP(Tabla1[[#This Row],[Nombre Cuenta]],PLAN_CUENTAS!$B$2:$B$100,PLAN_CUENTAS!$A$2:$A$100,0,0) | L28: =+_xlfn.XLOOKUP(Tabla1[[#This Row],[Nombre Cuenta]],PLAN_CUENTAS!$B$2:$B$100,PLAN_CUENTAS!$C$2:$C$100,0,0)
A29: 46114 | B29: 2026-04 | C29: Compra MP *CABIFY2614OE3 | D29: Cabify | E29: 2846 | F29: F | G29: Debito | H29: Transporte Personas (Empleados) | I29: =IF(F29="F",ROUND(E29*0.19/1.19,0),0) | J29: =IF(E29="","",E29-I29) | K29: =+_xlfn.XLOOKUP(Tabla1[[#This Row],[Nombre Cuenta]],PLAN_CUENTAS!$B$2:$B$100,PLAN_CUENTAS!$A$2:$A$100,0,0) | L29: =+_xlfn.XLOOKUP(Tabla1[[#This Row],[Nombre Cuenta]],PLAN_CUENTAS!$B$2:$B$100,PLAN_CUENTAS!$C$2:$C$100,0,0)
A30: 46118 | B30: 2026-04 | C30: 17.403.946-1 - Arriendo Local | D30: Florencia Castro | E30: 3386546 | G30: Debito | H30: Arriendo Local | I30: =IF(F30="F",ROUND(E30*0.19/1.19,0),0) | J30: =IF(E30="","",E30-I30) | K30: =+_xlfn.XLOOKUP(Tabla1[[#This Row],[Nombre Cuenta]],PLAN_CUENTAS!$B$2:$B$100,PLAN_CUENTAS!$A$2:$A$100,0,0) | L30: =+_xlfn.XLOOKUP(Tabla1[[#This Row],[Nombre Cuenta]],PLAN_CUENTAS!$B$2:$B$100,PLAN_CUENTAS!$C$2:$C$100,0,0)
A31: 46118 | B31: 2026-04 | C31: 18.831.462-7 - Katherine Chamorro - Moto | E31: 1200000 | G31: Debito | H31: Prestamos Personal | I31: =IF(F31="F",ROUND(E31*0.19/1.19,0),0) | J31: =IF(E31="","",E31-I31) | K31: =+_xlfn.XLOOKUP(Tabla1[[#This Row],[Nombre Cuenta]],PLAN_CUENTAS!$B$2:$B$100,PLAN_CUENTAS!$A$2:$A$100,0,0) | L31: =+_xlfn.XLOOKUP(Tabla1[[#This Row],[Nombre Cuenta]],PLAN_CUENTAS!$B$2:$B$100,PLAN_CUENTAS!$C$2:$C$100,0,0)
A32: 46118 | B32: 2026-03 | C32: 77.305.867-9 - Gaspar | D32: SERVICIOS INTEGRALES DAGA SPA | E32: 707967 | F32: F | G32: Debito | H32: Despachos B2B (Gaspar) | I32: =IF(F32="F",ROUND(E32*0.19/1.19,0),0) | J32: =IF(E32="","",E32-I32) | K32: =+_xlfn.XLOOKUP(Tabla1[[#This Row],[Nombre Cuenta]],PLAN_CUENTAS!$B$2:$B$100,PLAN_CUENTAS!$A$2:$A$100,0,0) | L32: =+_xlfn.XLOOKUP(Tabla1[[#This Row],[Nombre Cuenta]],PLAN_CUENTAS!$B$2:$B$100,PLAN_CUENTAS!$C$2:$C$100,0,0)
A33: 46118 | B33: 2026-03 | C33: 76.041.249-K - Martin Iturrieta | D33: MARKETING ADVERTISING AND SALES | E33: 702100 | F33: F | G33: Debito | H33: Produccion Audiovisual | I33: =IF(F33="F",ROUND(E33*0.19/1.19,0),0) | J33: =IF(E33="","",E33-I33) | K33: =+_xlfn.XLOOKUP(Tabla1[[#This Row],[Nombre Cuenta]],PLAN_CUENTAS!$B$2:$B$100,PLAN_CUENTAS!$A$2:$A$100,0,0) | L33: =+_xlfn.XLOOKUP(Tabla1[[#This Row],[Nombre Cuenta]],PLAN_CUENTAS!$B$2:$B$100,PLAN_CUENTAS!$C$2:$C$100,0,0)
A34: 46118 | B34: 2026-04 | C34: Transf.Internet a 77.298.762-5 | D34: TECNOLOGIA VERDE SPA | E34: 107100 | F34: F | G34: Debito | H34: Despachos B2B (Gaspar) | I34: =IF(F34="F",ROUND(E34*0.19/1.19,0),0) | J34: =IF(E34="","",E34-I34) | K34: =+_xlfn.XLOOKUP(Tabla1[[#This Row],[Nombre Cuenta]],PLAN_CUENTAS!$B$2:$B$100,PLAN_CUENTAS!$A$2:$A$100,0,0) | L34: =+_xlfn.XLOOKUP(Tabla1[[#This Row],[Nombre Cuenta]],PLAN_CUENTAS!$B$2:$B$100,PLAN_CUENTAS!$C$2:$C$100,0,0)
A35: 46118 | B35: 2026-03 | C35: 77.305.867-9 - Gaspar (Iva chofer niños ignacia) | D35: SERVICIOS INTEGRALES DAGA SPA | E35: 95200 | F35: F | G35: Debito | H35: Despachos B2B (Gaspar) | I35: =IF(F35="F",ROUND(E35*0.19/1.19,0),0) | J35: =IF(E35="","",E35-I35) | K35: =+_xlfn.XLOOKUP(Tabla1[[#This Row],[Nombre Cuenta]],PLAN_CUENTAS!$B$2:$B$100,PLAN_CUENTAS!$A$2:$A$100,0,0) | L35: =+_xlfn.XLOOKUP(Tabla1[[#This Row],[Nombre Cuenta]],PLAN_CUENTAS!$B$2:$B$100,PLAN_CUENTAS!$C$2:$C$100,0,0)
A36: 46118 | B36: 2026-04 | C36: Compra MP *EKIPOTELCL | D36: Ekipotel | E36: 43503 | F36: F | G36: Debito | H36: Ferias y Eventos | I36: =IF(F36="F",ROUND(E36*0.19/1.19,0),0) | J36: =IF(E36="","",E36-I36) | K36: =+_xlfn.XLOOKUP(Tabla1[[#This Row],[Nombre Cuenta]],PLAN_CUENTAS!$B$2:$B$100,PLAN_CUENTAS!$A$2:$A$100,0,0) | L36: =+_xlfn.XLOOKUP(Tabla1[[#This Row],[Nombre Cuenta]],PLAN_CUENTAS!$B$2:$B$100,PLAN_CUENTAS!$C$2:$C$100,0,0)
A37: 46118 | B37: 2026-04 | C37: Compra PADDLE.NET* APPCH | D37: CHATGPT | E37: 18861 | G37: Debito | H37: Plataformas Digitales | I37: =IF(F37="F",ROUND(E37*0.19/1.19,0),0) | J37: =IF(E37="","",E37-I37) | K37: =+_xlfn.XLOOKUP(Tabla1[[#This Row],[Nombre Cuenta]],PLAN_CUENTAS!$B$2:$B$100,PLAN_CUENTAS!$A$2:$A$100,0,0) | L37: =+_xlfn.XLOOKUP(Tabla1[[#This Row],[Nombre Cuenta]],PLAN_CUENTAS!$B$2:$B$100,PLAN_CUENTAS!$C$2:$C$100,0,0)
A38: 46118 | B38: 2026-04 | C38: Compra CABIFY | D38: Cabify | E38: 4107 | F38: F | G38: Debito | H38: Transporte Personas (Empleados) | I38: =IF(F38="F",ROUND(E38*0.19/1.19,0),0) | J38: =IF(E38="","",E38-I38) | K38: =+_xlfn.XLOOKUP(Tabla1[[#This Row],[Nombre Cuenta]],PLAN_CUENTAS!$B$2:$B$100,PLAN_CUENTAS!$A$2:$A$100,0,0) | L38: =+_xlfn.XLOOKUP(Tabla1[[#This Row],[Nombre Cuenta]],PLAN_CUENTAS!$B$2:$B$100,PLAN_CUENTAS!$C$2:$C$100,0,0)
A39: 46119 | B39: 2026-04 | C39: Pago Cuota Crédito N° 420051171054 | D39: Banco Santander | E39: 1926881 | G39: Debito | H39: Gastos Bancarios | I39: =IF(F39="F",ROUND(E39*0.19/1.19,0),0) | J39: =IF(E39="","",E39-I39) | K39: =+_xlfn.XLOOKUP(Tabla1[[#This Row],[Nombre Cuenta]],PLAN_CUENTAS!$B$2:$B$100,PLAN_CUENTAS!$A$2:$A$100,0,0) | L39: =+_xlfn.XLOOKUP(Tabla1[[#This Row],[Nombre Cuenta]],PLAN_CUENTAS!$B$2:$B$100,PLAN_CUENTAS!$C$2:$C$100,0,0)
A40: 46119 | B40: 2026-04 | C40: Amortización Periódica LCA N° 0020 | D40: Banco Santander | E40: 631740 | G40: Debito | H40: Gastos Bancarios | I40: =IF(F40="F",ROUND(E40*0.19/1.19,0),0) | J40: =IF(E40="","",E40-I40) | K40: =+_xlfn.XLOOKUP(Tabla1[[#This Row],[Nombre Cuenta]],PLAN_CUENTAS!$B$2:$B$100,PLAN_CUENTAS!$A$2:$A$100,0,0) | L40: =+_xlfn.XLOOKUP(Tabla1[[#This Row],[Nombre Cuenta]],PLAN_CUENTAS!$B$2:$B$100,PLAN_CUENTAS!$C$2:$C$100,0,0)
A41: 46119 | B41: 2026-04 | C41: Capsulas Orafio y Vertuo - Cafeteria | D41: Nespresso | E41: 228875 | F41: F | G41: Debito | H41: Ingredientes | I41: =IF(F41="F",ROUND(E41*0.19/1.19,0),0) | J41: =IF(E41="","",E41-I41) | K41: =+_xlfn.XLOOKUP(Tabla1[[#This Row],[Nombre Cuenta]],PLAN_CUENTAS!$B$2:$B$100,PLAN_CUENTAS!$A$2:$A$100,0,0) | L41: =+_xlfn.XLOOKUP(Tabla1[[#This Row],[Nombre Cuenta]],PLAN_CUENTAS!$B$2:$B$100,PLAN_CUENTAS!$C$2:$C$100,0,0)
A42: 46119 | B42: 2026-04 | C42: 78.065.582-8 - Asesoria Contable | D42: Clave Contadores | E42: 110000 | F42: F | G42: Debito | H42: Asesoria Contable | I42: =IF(F42="F",ROUND(E42*0.19/1.19,0),0) | J42: =IF(E42="","",E42-I42) | K42: =+_xlfn.XLOOKUP(Tabla1[[#This Row],[Nombre Cuenta]],PLAN_CUENTAS!$B$2:$B$100,PLAN_CUENTAS!$A$2:$A$100,0,0) | L42: =+_xlfn.XLOOKUP(Tabla1[[#This Row],[Nombre Cuenta]],PLAN_CUENTAS!$B$2:$B$100,PLAN_CUENTAS!$C$2:$C$100,0,0)
A43: 46119 | B43: 2026-04 | C43: 4 Canastos Feria Ñam | D43: Falabella | E43: 40970 | F43: F | G43: Debito | H43: Ferias y Eventos | I43: =IF(F43="F",ROUND(E43*0.19/1.19,0),0) | J43: =IF(E43="","",E43-I43) | K43: =+_xlfn.XLOOKUP(Tabla1[[#This Row],[Nombre Cuenta]],PLAN_CUENTAS!$B$2:$B$100,PLAN_CUENTAS!$A$2:$A$100,0,0) | L43: =+_xlfn.XLOOKUP(Tabla1[[#This Row],[Nombre Cuenta]],PLAN_CUENTAS!$B$2:$B$100,PLAN_CUENTAS!$C$2:$C$100,0,0)
A44: 46119 | B44: 2026-04 | C44: Compra CABIFY | D44: Cabify | E44: 4123 | F44: F | G44: Debito | H44: Transporte Personas (Empleados) | I44: =IF(F44="F",ROUND(E44*0.19/1.19,0),0) | J44: =IF(E44="","",E44-I44) | K44: =+_xlfn.XLOOKUP(Tabla1[[#This Row],[Nombre Cuenta]],PLAN_CUENTAS!$B$2:$B$100,PLAN_CUENTAS!$A$2:$A$100,0,0) | L44: =+_xlfn.XLOOKUP(Tabla1[[#This Row],[Nombre Cuenta]],PLAN_CUENTAS!$B$2:$B$100,PLAN_CUENTAS!$C$2:$C$100,0,0)
A45: 46120 | B45: 2026-04 | C45: 88.566.900-K - Bolsas Blancas Grandes y Chicas | D45: Edipac | E45: 205194 | F45: F | G45: Debito | H45: Packaging | I45: =IF(F45="F",ROUND(E45*0.19/1.19,0),0) | J45: =IF(E45="","",E45-I45) | K45: =+_xlfn.XLOOKUP(Tabla1[[#This Row],[Nombre Cuenta]],PLAN_CUENTAS!$B$2:$B$100,PLAN_CUENTAS!$A$2:$A$100,0,0) | L45: =+_xlfn.XLOOKUP(Tabla1[[#This Row],[Nombre Cuenta]],PLAN_CUENTAS!$B$2:$B$100,PLAN_CUENTAS!$C$2:$C$100,0,0)
A46: 46120 | B46: 2026-04 | C46: 17.403.946-1 - Arriendo Local | D46: Florencia Castro | E46: 199208 | G46: Debito | H46: Arriendo Local | I46: =IF(F46="F",ROUND(E46*0.19/1.19,0),0) | J46: =IF(E46="","",E46-I46) | K46: =+_xlfn.XLOOKUP(Tabla1[[#This Row],[Nombre Cuenta]],PLAN_CUENTAS!$B$2:$B$100,PLAN_CUENTAS!$A$2:$A$100,0,0) | L46: =+_xlfn.XLOOKUP(Tabla1[[#This Row],[Nombre Cuenta]],PLAN_CUENTAS!$B$2:$B$100,PLAN_CUENTAS!$C$2:$C$100,0,0)
A47: 46120 | B47: 2026-04 | C47: 76.706.900-6 - Nuez Partida | D47: Pepitas de Oro | E47: 47005 | F47: F | G47: Debito | H47: Ingredientes | I47: =IF(F47="F",ROUND(E47*0.19/1.19,0),0) | J47: =IF(E47="","",E47-I47) | K47: =+_xlfn.XLOOKUP(Tabla1[[#This Row],[Nombre Cuenta]],PLAN_CUENTAS!$B$2:$B$100,PLAN_CUENTAS!$A$2:$A$100,0,0) | L47: =+_xlfn.XLOOKUP(Tabla1[[#This Row],[Nombre Cuenta]],PLAN_CUENTAS!$B$2:$B$100,PLAN_CUENTAS!$C$2:$C$100,0,0)
A48: 46120 | B48: 2026-04 | C48: 76.554.985-k - Firma Aprobado Ignacia | D48: Timbre mio | E48: 39490 | F48: F | G48: Debito | H48: Equipamiento Local | I48: =IF(F48="F",ROUND(E48*0.19/1.19,0),0) | J48: =IF(E48="","",E48-I48) | K48: =+_xlfn.XLOOKUP(Tabla1[[#This Row],[Nombre Cuenta]],PLAN_CUENTAS!$B$2:$B$100,PLAN_CUENTAS!$A$2:$A$100,0,0) | L48: =+_xlfn.XLOOKUP(Tabla1[[#This Row],[Nombre Cuenta]],PLAN_CUENTAS!$B$2:$B$100,PLAN_CUENTAS!$C$2:$C$100,0,0)
A49: 46121 | B49: 2026-03 | C49: PAGO EN LINEA PREVIRED | D49: Previred | E49: 1721239 | G49: Debito | H49: Sueldos con Contrato | I49: =IF(F49="F",ROUND(E49*0.19/1.19,0),0) | J49: =IF(E49="","",E49-I49) | K49: =+_xlfn.XLOOKUP(Tabla1[[#This Row],[Nombre Cuenta]],PLAN_CUENTAS!$B$2:$B$100,PLAN_CUENTAS!$A$2:$A$100,0,0) | L49: =+_xlfn.XLOOKUP(Tabla1[[#This Row],[Nombre Cuenta]],PLAN_CUENTAS!$B$2:$B$100,PLAN_CUENTAS!$C$2:$C$100,0,0)
A50: 46121 | B50: 2026-04 | C50: 16.716.491-9 - 70% enchufes terraza | D50: Raul Velasquez | E50: 385000 | F50: F | G50: Debito | H50: Equipamiento Local | I50: =IF(F50="F",ROUND(E50*0.19/1.19,0),0) | J50: =IF(E50="","",E50-I50) | K50: =+_xlfn.XLOOKUP(Tabla1[[#This Row],[Nombre Cuenta]],PLAN_CUENTAS!$B$2:$B$100,PLAN_CUENTAS!$A$2:$A$100,0,0) | L50: =+_xlfn.XLOOKUP(Tabla1[[#This Row],[Nombre Cuenta]],PLAN_CUENTAS!$B$2:$B$100,PLAN_CUENTAS!$C$2:$C$100,0,0)
A51: 46121 | B51: 2026-04 | C51: 78.065.582-8 - Asesoria Contable | D51: Clave Contadores | E51: 220000 | F51: F | G51: Debito | H51: Asesoria Contable | I51: =IF(F51="F",ROUND(E51*0.19/1.19,0),0) | J51: =IF(E51="","",E51-I51) | K51: =+_xlfn.XLOOKUP(Tabla1[[#This Row],[Nombre Cuenta]],PLAN_CUENTAS!$B$2:$B$100,PLAN_CUENTAS!$A$2:$A$100,0,0) | L51: =+_xlfn.XLOOKUP(Tabla1[[#This Row],[Nombre Cuenta]],PLAN_CUENTAS!$B$2:$B$100,PLAN_CUENTAS!$C$2:$C$100,0,0)
A52: 46121 | B52: 2026-04 | C52: 84.736.800-4 - Ron y Coñac | D52: Chavarry Y Hugot | E52: 137800 | F52: F | G52: Debito | H52: Ingredientes | I52: =IF(F52="F",ROUND(E52*0.19/1.19,0),0) | J52: =IF(E52="","",E52-I52) | K52: =+_xlfn.XLOOKUP(Tabla1[[#This Row],[Nombre Cuenta]],PLAN_CUENTAS!$B$2:$B$100,PLAN_CUENTAS!$A$2:$A$100,0,0) | L52: =+_xlfn.XLOOKUP(Tabla1[[#This Row],[Nombre Cuenta]],PLAN_CUENTAS!$B$2:$B$100,PLAN_CUENTAS!$C$2:$C$100,0,0)
A53: 46121 | B53: 2026-03 | C53: Compra AGUAS ANDINAS | D53: Aguas Andinas | E53: 39640 | F53: F | G53: Debito | H53: Agua | I53: =IF(F53="F",ROUND(E53*0.19/1.19,0),0) | J53: =IF(E53="","",E53-I53) | K53: =+_xlfn.XLOOKUP(Tabla1[[#This Row],[Nombre Cuenta]],PLAN_CUENTAS!$B$2:$B$100,PLAN_CUENTAS!$A$2:$A$100,0,0) | L53: =+_xlfn.XLOOKUP(Tabla1[[#This Row],[Nombre Cuenta]],PLAN_CUENTAS!$B$2:$B$100,PLAN_CUENTAS!$C$2:$C$100,0,0)
A54: 46121 | B54: 2026-04 | C54: Procesadora | D54: Falabella | E54: 30980 | F54: F | G54: Debito | H54: Equipamiento de Cocina | I54: =IF(F54="F",ROUND(E54*0.19/1.19,0),0) | J54: =IF(E54="","",E54-I54) | K54: =+_xlfn.XLOOKUP(Tabla1[[#This Row],[Nombre Cuenta]],PLAN_CUENTAS!$B$2:$B$100,PLAN_CUENTAS!$A$2:$A$100,0,0) | L54: =+_xlfn.XLOOKUP(Tabla1[[#This Row],[Nombre Cuenta]],PLAN_CUENTAS!$B$2:$B$100,PLAN_CUENTAS!$C$2:$C$100,0,0)
A55: 46121 | B55: 2026-04 | C55: Tarjetas de presentacion personalizadas Saint Laurent | D55: Alo Print | E55: 23240 | F55: F | G55: Debito | H55: Packaging | I55: =IF(F55="F",ROUND(E55*0.19/1.19,0),0) | J55: =IF(E55="","",E55-I55) | K55: =+_xlfn.XLOOKUP(Tabla1[[#This Row],[Nombre Cuenta]],PLAN_CUENTAS!$B$2:$B$100,PLAN_CUENTAS!$A$2:$A$100,0,0) | L55: =+_xlfn.XLOOKUP(Tabla1[[#This Row],[Nombre Cuenta]],PLAN_CUENTAS!$B$2:$B$100,PLAN_CUENTAS!$C$2:$C$100,0,0)
A56: 46121 | B56: 2026-04 | C56: Traslado fernando y Cata Ñam al local | D56: Cabify | E56: 6777 | F56: F | G56: Debito | H56: Transporte Personas (Empleados) | I56: =IF(F56="F",ROUND(E56*0.19/1.19,0),0) | J56: =IF(E56="","",E56-I56) | K56: =+_xlfn.XLOOKUP(Tabla1[[#This Row],[Nombre Cuenta]],PLAN_CUENTAS!$B$2:$B$100,PLAN_CUENTAS!$A$2:$A$100,0,0) | L56: =+_xlfn.XLOOKUP(Tabla1[[#This Row],[Nombre Cuenta]],PLAN_CUENTAS!$B$2:$B$100,PLAN_CUENTAS!$C$2:$C$100,0,0)
A57: 46125 | B57: 2026-03 | C57: Compra FACEBK *4X6S4MVVJ | D57: Facebook Ads | E57: 198123 | F57: S | G57: Debito | H57: RRSS | I57: =IF(F57="F",ROUND(E57*0.19/1.19,0),0) | J57: =IF(E57="","",E57-I57) | K57: =+_xlfn.XLOOKUP(Tabla1[[#This Row],[Nombre Cuenta]],PLAN_CUENTAS!$B$2:$B$100,PLAN_CUENTAS!$A$2:$A$100,0,0) | L57: =+_xlfn.XLOOKUP(Tabla1[[#This Row],[Nombre Cuenta]],PLAN_CUENTAS!$B$2:$B$100,PLAN_CUENTAS!$C$2:$C$100,0,0)
A58: 46125 | B58: 2026-04 | C58: Huevos primera blanco | D58: LIDER | E58: 71910 | F58: F | G58: Debito | H58: Ingredientes | I58: =IF(F58="F",ROUND(E58*0.19/1.19,0),0) | J58: =IF(E58="","",E58-I58) | K58: =+_xlfn.XLOOKUP(Tabla1[[#This Row],[Nombre Cuenta]],PLAN_CUENTAS!$B$2:$B$100,PLAN_CUENTAS!$A$2:$A$100,0,0) | L58: =+_xlfn.XLOOKUP(Tabla1[[#This Row],[Nombre Cuenta]],PLAN_CUENTAS!$B$2:$B$100,PLAN_CUENTAS!$C$2:$C$100,0,0)
A59: 46125 | B59: 2026-04 | C59: Huevos primera blanco | D59: LIDER | E59: 31960 | F59: F | G59: Debito | H59: Ingredientes | I59: =IF(F59="F",ROUND(E59*0.19/1.19,0),0) | J59: =IF(E59="","",E59-I59) | K59: =+_xlfn.XLOOKUP(Tabla1[[#This Row],[Nombre Cuenta]],PLAN_CUENTAS!$B$2:$B$100,PLAN_CUENTAS!$A$2:$A$100,0,0) | L59: =+_xlfn.XLOOKUP(Tabla1[[#This Row],[Nombre Cuenta]],PLAN_CUENTAS!$B$2:$B$100,PLAN_CUENTAS!$C$2:$C$100,0,0)
A60: 46125 | B60: 2026-04 | C60: Traslado Ñam | D60: Cabify | E60: 7437 | F60: F | G60: Debito | H60: Transporte Personas (Empleados) | I60: =IF(F60="F",ROUND(E60*0.19/1.19,0),0) | J60: =IF(E60="","",E60-I60) | K60: =+_xlfn.XLOOKUP(Tabla1[[#This Row],[Nombre Cuenta]],PLAN_CUENTAS!$B$2:$B$100,PLAN_CUENTAS!$A$2:$A$100,0,0) | L60: =+_xlfn.XLOOKUP(Tabla1[[#This Row],[Nombre Cuenta]],PLAN_CUENTAS!$B$2:$B$100,PLAN_CUENTAS!$C$2:$C$100,0,0)
A61: 46125 | B61: 2026-04 | C61: Traslado Ñam | D61: Cabify | E61: 6649 | F61: F | G61: Debito | H61: Transporte Personas (Empleados) | I61: =IF(F61="F",ROUND(E61*0.19/1.19,0),0) | J61: =IF(E61="","",E61-I61) | K61: =+_xlfn.XLOOKUP(Tabla1[[#This Row],[Nombre Cuenta]],PLAN_CUENTAS!$B$2:$B$100,PLAN_CUENTAS!$A$2:$A$100,0,0) | L61: =+_xlfn.XLOOKUP(Tabla1[[#This Row],[Nombre Cuenta]],PLAN_CUENTAS!$B$2:$B$100,PLAN_CUENTAS!$C$2:$C$100,0,0)
... A76: 46126 | B76: 2026-04 | C76: 77.934.110-0 - Nutella Balde 6 kilos | D76: Alca Chile | E76: 80301 | F76: F | G76: Debito | H76: Ingredientes | I76: =IF(F76="F",ROUND(E76*0.19/1.19,0),0) | J76: =IF(E76="","",E76-I76) | K76: =+_xlfn.XLOOKUP(Tabla1[[#This Row],[Nombre Cuenta]],PLAN_CUENTAS!$B$2:$B$100,PLAN_CUENTAS!$A$2:$A$100,0,0) | L76: =+_xlfn.XLOOKUP(Tabla1[[#This Row],[Nombre Cuenta]],PLAN_CUENTAS!$B$2:$B$100,PLAN_CUENTAS!$C$2:$C$100,0,0)
A77: 46126 | B77: 2026-04 | C77: Sueldo - 21.920.200-8 Cata Arriagada Adelanto | E77: 50000 | G77: Debito | H77: Honorarios | I77: =IF(F77="F",ROUND(E77*0.19/1.19,0),0) | J77: =IF(E77="","",E77-I77) | K77: =+_xlfn.XLOOKUP(Tabla1[[#This Row],[Nombre Cuenta]],PLAN_CUENTAS!$B$2:$B$100,PLAN_CUENTAS!$A$2:$A$100,0,0) | L77: =+_xlfn.XLOOKUP(Tabla1[[#This Row],[Nombre Cuenta]],PLAN_CUENTAS!$B$2:$B$100,PLAN_CUENTAS!$C$2:$C$100,0,0)
A78: 46126 | B78: 2026-04 | C78: Compra OPENAI *CHATGPT S | D78: CHATGPT | E78: 22007 | G78: Debito | H78: Plataformas Digitales | I78: =IF(F78="F",ROUND(E78*0.19/1.19,0),0) | J78: =IF(E78="","",E78-I78) | K78: =+_xlfn.XLOOKUP(Tabla1[[#This Row],[Nombre Cuenta]],PLAN_CUENTAS!$B$2:$B$100,PLAN_CUENTAS!$A$2:$A$100,0,0) | L78: =+_xlfn.XLOOKUP(Tabla1[[#This Row],[Nombre Cuenta]],PLAN_CUENTAS!$B$2:$B$100,PLAN_CUENTAS!$C$2:$C$100,0,0)
A79: 46126 | B79: 2026-04 | C79: 18.831.462-7 - Almuerzo Ñam Kathy | E79: 12000 | F79: S | G79: Debito | H79: Ferias y Eventos | I79: =IF(F79="F",ROUND(E79*0.19/1.19,0),0) | J79: =IF(E79="","",E79-I79) | K79: =+_xlfn.XLOOKUP(Tabla1[[#This Row],[Nombre Cuenta]],PLAN_CUENTAS!$B$2:$B$100,PLAN_CUENTAS!$A$2:$A$100,0,0) | L79: =+_xlfn.XLOOKUP(Tabla1[[#This Row],[Nombre Cuenta]],PLAN_CUENTAS!$B$2:$B$100,PLAN_CUENTAS!$C$2:$C$100,0,0)
A80: 46127 | B80: 2026-04 | C80: 77.361.009-6 - Azucar Granulada | D80: El Pistacho Spa | E80: 107100 | F80: F | G80: Debito | H80: Ingredientes | I80: =IF(F80="F",ROUND(E80*0.19/1.19,0),0) | J80: =IF(E80="","",E80-I80) | K80: =+_xlfn.XLOOKUP(Tabla1[[#This Row],[Nombre Cuenta]],PLAN_CUENTAS!$B$2:$B$100,PLAN_CUENTAS!$A$2:$A$100,0,0) | L80: =+_xlfn.XLOOKUP(Tabla1[[#This Row],[Nombre Cuenta]],PLAN_CUENTAS!$B$2:$B$100,PLAN_CUENTAS!$C$2:$C$100,0,0)
A81: 46127 | B81: 2026-04 | C81: 76.467.151-1 - Jugos Bless Naranja y Pepino | D81: Bless | E81: 34558 | F81: F | G81: Debito | H81: Ingredientes | I81: =IF(F81="F",ROUND(E81*0.19/1.19,0),0) | J81: =IF(E81="","",E81-I81) | K81: =+_xlfn.XLOOKUP(Tabla1[[#This Row],[Nombre Cuenta]],PLAN_CUENTAS!$B$2:$B$100,PLAN_CUENTAS!$A$2:$A$100,0,0) | L81: =+_xlfn.XLOOKUP(Tabla1[[#This Row],[Nombre Cuenta]],PLAN_CUENTAS!$B$2:$B$100,PLAN_CUENTAS!$C$2:$C$100,0,0)
A82: 46128 | B82: 2026-04 | C82: 76.474.307-5 - Carrito Parque Araucano 1 de 3 | D82: HG CONSTRUCTORA SPA | E82: 1616667 | F82: F | G82: Debito | H82: Inversión Carro | I82: =IF(F82="F",ROUND(E82*0.19/1.19,0),0) | J82: =IF(E82="","",E82-I82) | K82: =+_xlfn.XLOOKUP(Tabla1[[#This Row],[Nombre Cuenta]],PLAN_CUENTAS!$B$2:$B$100,PLAN_CUENTAS!$A$2:$A$100,0,0) | L82: =+_xlfn.XLOOKUP(Tabla1[[#This Row],[Nombre Cuenta]],PLAN_CUENTAS!$B$2:$B$100,PLAN_CUENTAS!$C$2:$C$100,0,0)
A83: 46128 | B83: 2026-04 | C83: Sueldo 21.093.602-5 - Nataly Morales (Adelanto) | E83: 300000 | G83: Debito | H83: Sueldos con Contrato | I83: =IF(F83="F",ROUND(E83*0.19/1.19,0),0) | J83: =IF(E83="","",E83-I83) | K83: =+_xlfn.XLOOKUP(Tabla1[[#This Row],[Nombre Cuenta]],PLAN_CUENTAS!$B$2:$B$100,PLAN_CUENTAS!$A$2:$A$100,0,0) | L83: =+_xlfn.XLOOKUP(Tabla1[[#This Row],[Nombre Cuenta]],PLAN_CUENTAS!$B$2:$B$100,PLAN_CUENTAS!$C$2:$C$100,0,0)
A84: 46128 | B84: 2026-04 | C84: Ñam 21.575.375-1 - Martina Jorquera | E84: 75000 | G84: Debito | H84: Honorarios | I84: =IF(F84="F",ROUND(E84*0.19/1.19,0),0) | J84: =IF(E84="","",E84-I84) | K84: =+_xlfn.XLOOKUP(Tabla1[[#This Row],[Nombre Cuenta]],PLAN_CUENTAS!$B$2:$B$100,PLAN_CUENTAS!$A$2:$A$100,0,0) | L84: =+_xlfn.XLOOKUP(Tabla1[[#This Row],[Nombre Cuenta]],PLAN_CUENTAS!$B$2:$B$100,PLAN_CUENTAS!$C$2:$C$100,0,0)
A85: 46128 | B85: 2026-04 | C85: Ñam 21.780.804-9 - Isidora Rodriguez | E85: 75000 | G85: Debito | H85: Honorarios | I85: =IF(F85="F",ROUND(E85*0.19/1.19,0),0) | J85: =IF(E85="","",E85-I85) | K85: =+_xlfn.XLOOKUP(Tabla1[[#This Row],[Nombre Cuenta]],PLAN_CUENTAS!$B$2:$B$100,PLAN_CUENTAS!$A$2:$A$100,0,0) | L85: =+_xlfn.XLOOKUP(Tabla1[[#This Row],[Nombre Cuenta]],PLAN_CUENTAS!$B$2:$B$100,PLAN_CUENTAS!$C$2:$C$100,0,0)
A86: 46128 | B86: 2026-04 | C86: Ñam 21.380.644-0 - Elizabeth Caceres | E86: 75000 | G86: Debito | H86: Honorarios | I86: =IF(F86="F",ROUND(E86*0.19/1.19,0),0) | J86: =IF(E86="","",E86-I86) | K86: =+_xlfn.XLOOKUP(Tabla1[[#This Row],[Nombre Cuenta]],PLAN_CUENTAS!$B$2:$B$100,PLAN_CUENTAS!$A$2:$A$100,0,0) | L86: =+_xlfn.XLOOKUP(Tabla1[[#This Row],[Nombre Cuenta]],PLAN_CUENTAS!$B$2:$B$100,PLAN_CUENTAS!$C$2:$C$100,0,0)
A87: 46128 | B87: 2026-04 | C87: Ñam 21.572.942-7 - Almendra Angelini | E87: 50000 | G87: Debito | H87: Honorarios | I87: =IF(F87="F",ROUND(E87*0.19/1.19,0),0) | J87: =IF(E87="","",E87-I87) | K87: =+_xlfn.XLOOKUP(Tabla1[[#This Row],[Nombre Cuenta]],PLAN_CUENTAS!$B$2:$B$100,PLAN_CUENTAS!$A$2:$A$100,0,0) | L87: =+_xlfn.XLOOKUP(Tabla1[[#This Row],[Nombre Cuenta]],PLAN_CUENTAS!$B$2:$B$100,PLAN_CUENTAS!$C$2:$C$100,0,0)
A88: 46128 | B88: 2026-04 | C88: Bolsas de basura 3 tamaños | D88: Mercadolibre | E88: 30200 | F88: F | G88: Debito | H88: Equipamiento de Cocina | I88: =IF(F88="F",ROUND(E88*0.19/1.19,0),0) | J88: =IF(E88="","",E88-I88) | K88: =+_xlfn.XLOOKUP(Tabla1[[#This Row],[Nombre Cuenta]],PLAN_CUENTAS!$B$2:$B$100,PLAN_CUENTAS!$A$2:$A$100,0,0) | L88: =+_xlfn.XLOOKUP(Tabla1[[#This Row],[Nombre Cuenta]],PLAN_CUENTAS!$B$2:$B$100,PLAN_CUENTAS!$C$2:$C$100,0,0)
A89: 46128 | B89: 2026-04 | C89: 10.325.328-4 - Patricia Guijuelos | E89: 26484 | G89: Debito | H89: Honorarios | I89: =IF(F89="F",ROUND(E89*0.19/1.19,0),0) | J89: =IF(E89="","",E89-I89) | K89: =+_xlfn.XLOOKUP(Tabla1[[#This Row],[Nombre Cuenta]],PLAN_CUENTAS!$B$2:$B$100,PLAN_CUENTAS!$A$2:$A$100,0,0) | L89: =+_xlfn.XLOOKUP(Tabla1[[#This Row],[Nombre Cuenta]],PLAN_CUENTAS!$B$2:$B$100,PLAN_CUENTAS!$C$2:$C$100,0,0)
A90: 46128 | B90: 2026-04 | C90: Ñam 20.550.382-k - Veronica Alvarez | E90: 25000 | G90: Debito | H90: Honorarios | I90: =IF(F90="F",ROUND(E90*0.19/1.19,0),0) | J90: =IF(E90="","",E90-I90) | K90: =+_xlfn.XLOOKUP(Tabla1[[#This Row],[Nombre Cuenta]],PLAN_CUENTAS!$B$2:$B$100,PLAN_CUENTAS!$A$2:$A$100,0,0) | L90: =+_xlfn.XLOOKUP(Tabla1[[#This Row],[Nombre Cuenta]],PLAN_CUENTAS!$B$2:$B$100,PLAN_CUENTAS!$C$2:$C$100,0,0)
A91: 46128 | B91: 2026-04 | C91: Ñam 21.093.602-5 - Nataly Morales | E91: 25000 | G91: Debito | H91: Honorarios | I91: =IF(F91="F",ROUND(E91*0.19/1.19,0),0) | J91: =IF(E91="","",E91-I91) | K91: =+_xlfn.XLOOKUP(Tabla1[[#This Row],[Nombre Cuenta]],PLAN_CUENTAS!$B$2:$B$100,PLAN_CUENTAS!$A$2:$A$100,0,0) | L91: =+_xlfn.XLOOKUP(Tabla1[[#This Row],[Nombre Cuenta]],PLAN_CUENTAS!$B$2:$B$100,PLAN_CUENTAS!$C$2:$C$100,0,0)
A92: 46128 | B92: 2026-04 | C92: Ñam 18.866.000-2 - Camila Aguilera | E92: 25000 | G92: Debito | H92: Honorarios | I92: =IF(F92="F",ROUND(E92*0.19/1.19,0),0) | J92: =IF(E92="","",E92-I92) | K92: =+_xlfn.XLOOKUP(Tabla1[[#This Row],[Nombre Cuenta]],PLAN_CUENTAS!$B$2:$B$100,PLAN_CUENTAS!$A$2:$A$100,0,0) | L92: =+_xlfn.XLOOKUP(Tabla1[[#This Row],[Nombre Cuenta]],PLAN_CUENTAS!$B$2:$B$100,PLAN_CUENTAS!$C$2:$C$100,0,0)
A93: 46128 | B93: 2026-04 | C93: Compra OPENAI *CHATGPT S | D93: CHATGPT | E93: 18190 | G93: Debito | H93: Plataformas Digitales | I93: =IF(F93="F",ROUND(E93*0.19/1.19,0),0) | J93: =IF(E93="","",E93-I93) | K93: =+_xlfn.XLOOKUP(Tabla1[[#This Row],[Nombre Cuenta]],PLAN_CUENTAS!$B$2:$B$100,PLAN_CUENTAS!$A$2:$A$100,0,0) | L93: =+_xlfn.XLOOKUP(Tabla1[[#This Row],[Nombre Cuenta]],PLAN_CUENTAS!$B$2:$B$100,PLAN_CUENTAS!$C$2:$C$100,0,0)
A94: 46129 | B94: 2026-04 | C94: Compra Shopify* 51721300 | D94: Shopify | E94: 146887 | G94: Debito | H94: Plataformas Digitales | I94: =IF(F94="F",ROUND(E94*0.19/1.19,0),0) | J94: =IF(E94="","",E94-I94) | K94: =+_xlfn.XLOOKUP(Tabla1[[#This Row],[Nombre Cuenta]],PLAN_CUENTAS!$B$2:$B$100,PLAN_CUENTAS!$A$2:$A$100,0,0) | L94: =+_xlfn.XLOOKUP(Tabla1[[#This Row],[Nombre Cuenta]],PLAN_CUENTAS!$B$2:$B$100,PLAN_CUENTAS!$C$2:$C$100,0,0)
A95: 46129 | B95: 2026-03 | C95: PAC Telefonica 00000141814606 - Hogar | D95: Movistar | E95: 18237 | F95: F | G95: Debito | H95: Telecomunicaciones | I95: =IF(F95="F",ROUND(E95*0.19/1.19,0),0) | J95: =IF(E95="","",E95-I95) | K95: =+_xlfn.XLOOKUP(Tabla1[[#This Row],[Nombre Cuenta]],PLAN_CUENTAS!$B$2:$B$100,PLAN_CUENTAS!$A$2:$A$100,0,0) | L95: =+_xlfn.XLOOKUP(Tabla1[[#This Row],[Nombre Cuenta]],PLAN_CUENTAS!$B$2:$B$100,PLAN_CUENTAS!$C$2:$C$100,0,0)
A96: 46129 | B96: 2026-03 | C96: PAC Movistar 00000141816185 - Celular | D96: Movistar | E96: 17265 | F96: F | G96: Debito | H96: Telecomunicaciones | I96: =IF(F96="F",ROUND(E96*0.19/1.19,0),0) | J96: =IF(E96="","",E96-I96) | K96: =+_xlfn.XLOOKUP(Tabla1[[#This Row],[Nombre Cuenta]],PLAN_CUENTAS!$B$2:$B$100,PLAN_CUENTAS!$A$2:$A$100,0,0) | L96: =+_xlfn.XLOOKUP(Tabla1[[#This Row],[Nombre Cuenta]],PLAN_CUENTAS!$B$2:$B$100,PLAN_CUENTAS!$C$2:$C$100,0,0)
A97: 46132 | B97: 2026-03 | C97: PAGO EN LINEA S.I.I. | D97: SII | E97: 1589542 | G97: Debito | H97: IVA Neto (F29) | I97: =IF(F97="F",ROUND(E97*0.19/1.19,0),0) | J97: =IF(E97="","",E97-I97) | K97: =+_xlfn.XLOOKUP(Tabla1[[#This Row],[Nombre Cuenta]],PLAN_CUENTAS!$B$2:$B$100,PLAN_CUENTAS!$A$2:$A$100,0,0) | L97: =+_xlfn.XLOOKUP(Tabla1[[#This Row],[Nombre Cuenta]],PLAN_CUENTAS!$B$2:$B$100,PLAN_CUENTAS!$C$2:$C$100,0,0)
A98: 46132 | B98: 2026-04 | C98: 16.716.491-9 - Carrito Parque Araucano 30% | D98: Raul Velasquez | E98: 345660 | F98: F | G98: Debito | H98: Inversión Carro | I98: =IF(F98="F",ROUND(E98*0.19/1.19,0),0) | J98: =IF(E98="","",E98-I98) | K98: =+_xlfn.XLOOKUP(Tabla1[[#This Row],[Nombre Cuenta]],PLAN_CUENTAS!$B$2:$B$100,PLAN_CUENTAS!$A$2:$A$100,0,0) | L98: =+_xlfn.XLOOKUP(Tabla1[[#This Row],[Nombre Cuenta]],PLAN_CUENTAS!$B$2:$B$100,PLAN_CUENTAS!$C$2:$C$100,0,0)
A99: 46132 | B99: 2026-04 | C99: 26.070.601-2 - Movilizacion Carrito | D99: ARCOS HUARHUA YLDIFONSO | E99: 210000 | F99: S | G99: Debito | H99: Ferias y Eventos | I99: =IF(F99="F",ROUND(E99*0.19/1.19,0),0) | J99: =IF(E99="","",E99-I99) | K99: =+_xlfn.XLOOKUP(Tabla1[[#This Row],[Nombre Cuenta]],PLAN_CUENTAS!$B$2:$B$100,PLAN_CUENTAS!$A$2:$A$100,0,0) | L99: =+_xlfn.XLOOKUP(Tabla1[[#This Row],[Nombre Cuenta]],PLAN_CUENTAS!$B$2:$B$100,PLAN_CUENTAS!$C$2:$C$100,0,0)
A100: 46132 | B100: 2026-04 | C100: 84.736.800-4 - Ron y Coñac | D100: Chavarry Y Hugot | E100: 137800 | F100: F | G100: Debito | H100: Ingredientes | I100: =IF(F100="F",ROUND(E100*0.19/1.19,0),0) | J100: =IF(E100="","",E100-I100) | K100: =+_xlfn.XLOOKUP(Tabla1[[#This Row],[Nombre Cuenta]],PLAN_CUENTAS!$B$2:$B$100,PLAN_CUENTAS!$A$2:$A$100,0,0) | L100: =+_xlfn.XLOOKUP(Tabla1[[#This Row],[Nombre Cuenta]],PLAN_CUENTAS!$B$2:$B$100,PLAN_CUENTAS!$C$2:$C$100,0,0)
A101: 46132 | B101: 2026-04 | C101: 77.371.782-6 - Chocolates Caravella | D101: Sugar Kindom | E101: 76898 | F101: F | G101: Debito | H101: Ingredientes | I101: =IF(F101="F",ROUND(E101*0.19/1.19,0),0) | J101: =IF(E101="","",E101-I101) | K101: =+_xlfn.XLOOKUP(Tabla1[[#This Row],[Nombre Cuenta]],PLAN_CUENTAS!$B$2:$B$100,PLAN_CUENTAS!$A$2:$A$100,0,0) | L101: =+_xlfn.XLOOKUP(Tabla1[[#This Row],[Nombre Cuenta]],PLAN_CUENTAS!$B$2:$B$100,PLAN_CUENTAS!$C$2:$C$100,0,0)
A102: 46132 | B102: 2026-04 | C102: 77.190.532-3 - Stickers Transparantes y Logo | D102: Sticker Print | E102: 36140 | F102: F | G102: Debito | H102: Packaging | I102: =IF(F102="F",ROUND(E102*0.19/1.19,0),0) | J102: =IF(E102="","",E102-I102) | K102: =+_xlfn.XLOOKUP(Tabla1[[#This Row],[Nombre Cuenta]],PLAN_CUENTAS!$B$2:$B$100,PLAN_CUENTAS!$A$2:$A$100,0,0) | L102: =+_xlfn.XLOOKUP(Tabla1[[#This Row],[Nombre Cuenta]],PLAN_CUENTAS!$B$2:$B$100,PLAN_CUENTAS!$C$2:$C$100,0,0)
A103: 46132 | B103: 2026-03 | C103: 78.088.306-5 - Aquaoven 2 en 1 liquido horno | D103: Bozenlight | E103: 34771 | F103: F | G103: Debito | H103: Limpieza y Aseo | I103: =IF(F103="F",ROUND(E103*0.19/1.19,0),0) | J103: =IF(E103="","",E103-I103) | K103: =+_xlfn.XLOOKUP(Tabla1[[#This Row],[Nombre Cuenta]],PLAN_CUENTAS!$B$2:$B$100,PLAN_CUENTAS!$A$2:$A$100,0,0) | L103: =+_xlfn.XLOOKUP(Tabla1[[#This Row],[Nombre Cuenta]],PLAN_CUENTAS!$B$2:$B$100,PLAN_CUENTAS!$C$2:$C$100,0,0)
A104: 46132 | B104: 2026-04 | C104: 76.740.421-2 - Kombuchas lima berries | D104: Dr. Kombu | E104: 33106 | F104: F | G104: Debito | H104: Ingredientes | I104: =IF(F104="F",ROUND(E104*0.19/1.19,0),0) | J104: =IF(E104="","",E104-I104) | K104: =+_xlfn.XLOOKUP(Tabla1[[#This Row],[Nombre Cuenta]],PLAN_CUENTAS!$B$2:$B$100,PLAN_CUENTAS!$A$2:$A$100,0,0) | L104: =+_xlfn.XLOOKUP(Tabla1[[#This Row],[Nombre Cuenta]],PLAN_CUENTAS!$B$2:$B$100,PLAN_CUENTAS!$C$2:$C$100,0,0)
A105: 46133 | B105: 2026-04 | C105: 19.567.111-7 - Reembolso Pago Enel | D105: Enel | E105: 176047 | F105: F | G105: Debito | H105: Luz | I105: =IF(F105="F",ROUND(E105*0.19/1.19,0),0) | J105: =IF(E105="","",E105-I105) | K105: =+_xlfn.XLOOKUP(Tabla1[[#This Row],[Nombre Cuenta]],PLAN_CUENTAS!$B$2:$B$100,PLAN_CUENTAS!$A$2:$A$100,0,0) | L105: =+_xlfn.XLOOKUP(Tabla1[[#This Row],[Nombre Cuenta]],PLAN_CUENTAS!$B$2:$B$100,PLAN_CUENTAS!$C$2:$C$100,0,0)
A106: 46133 | B106: 2026-04 | C106: 76.209.474-6 - Uniformes | D106: CTA WORK | E106: 80282 | F106: F | G106: Debito | H106: Equipamiento de Cocina | I106: =IF(F106="F",ROUND(E106*0.19/1.19,0),0) | J106: =IF(E106="","",E106-I106) | K106: =+_xlfn.XLOOKUP(Tabla1[[#This Row],[Nombre Cuenta]],PLAN_CUENTAS!$B$2:$B$100,PLAN_CUENTAS!$A$2:$A$100,0,0) | L106: =+_xlfn.XLOOKUP(Tabla1[[#This Row],[Nombre Cuenta]],PLAN_CUENTAS!$B$2:$B$100,PLAN_CUENTAS!$C$2:$C$100,0,0)
A107: 46133 | B107: 2026-03 | C107: PAGO EN LINEA CHILEXPRESS | D107: Chilexpress | E107: 40798 | F107: F | G107: Debito | H107: Despachos B2C | I107: =IF(F107="F",ROUND(E107*0.19/1.19,0),0) | J107: =IF(E107="","",E107-I107) | K107: =+_xlfn.XLOOKUP(Tabla1[[#This Row],[Nombre Cuenta]],PLAN_CUENTAS!$B$2:$B$100,PLAN_CUENTAS!$A$2:$A$100,0,0) | L107: =+_xlfn.XLOOKUP(Tabla1[[#This Row],[Nombre Cuenta]],PLAN_CUENTAS!$B$2:$B$100,PLAN_CUENTAS!$C$2:$C$100,0,0)
A108: 46134 | B108: 2026-04 | C108: Compra FACEBK *GTW84ND6P | D108: Facebook Ads | E108: 314430 | G108: Debito | H108: RRSS | I108: =IF(F108="F",ROUND(E108*0.19/1.19,0),0) | J108: =IF(E108="","",E108-I108) | K108: =+_xlfn.XLOOKUP(Tabla1[[#This Row],[Nombre Cuenta]],PLAN_CUENTAS!$B$2:$B$100,PLAN_CUENTAS!$A$2:$A$100,0,0) | L108: =+_xlfn.XLOOKUP(Tabla1[[#This Row],[Nombre Cuenta]],PLAN_CUENTAS!$B$2:$B$100,PLAN_CUENTAS!$C$2:$C$100,0,0)
A109: 46134 | B109: 2026-03 | C109: 78.383.730-7 - Huevos Primera Blanca Granel | D109: Cintazul | E109: 288004 | F109: F | G109: Debito | H109: Ingredientes | I109: =IF(F109="F",ROUND(E109*0.19/1.19,0),0) | J109: =IF(E109="","",E109-I109) | K109: =+_xlfn.XLOOKUP(Tabla1[[#This Row],[Nombre Cuenta]],PLAN_CUENTAS!$B$2:$B$100,PLAN_CUENTAS!$A$2:$A$100,0,0) | L109: =+_xlfn.XLOOKUP(Tabla1[[#This Row],[Nombre Cuenta]],PLAN_CUENTAS!$B$2:$B$100,PLAN_CUENTAS!$C$2:$C$100,0,0)
A110: 46134 | B110: 2026-04 | C110: 78.383.730-7 - Huevos Primera Blanca Granel | D110: Cintazul | E110: 237605 | F110: F | G110: Debito | H110: Ingredientes | I110: =IF(F110="F",ROUND(E110*0.19/1.19,0),0) | J110: =IF(E110="","",E110-I110) | K110: =+_xlfn.XLOOKUP(Tabla1[[#This Row],[Nombre Cuenta]],PLAN_CUENTAS!$B$2:$B$100,PLAN_CUENTAS!$A$2:$A$100,0,0) | L110: =+_xlfn.XLOOKUP(Tabla1[[#This Row],[Nombre Cuenta]],PLAN_CUENTAS!$B$2:$B$100,PLAN_CUENTAS!$C$2:$C$100,0,0)
A111: 46134 | B111: 2026-04 | C111: 78.383.730-7 - Huevos Primera Blanca Granel | D111: Cintazul | E111: 158399 | F111: F | G111: Debito | H111: Ingredientes | I111: =IF(F111="F",ROUND(E111*0.19/1.19,0),0) | J111: =IF(E111="","",E111-I111) | K111: =+_xlfn.XLOOKUP(Tabla1[[#This Row],[Nombre Cuenta]],PLAN_CUENTAS!$B$2:$B$100,PLAN_CUENTAS!$A$2:$A$100,0,0) | L111: =+_xlfn.XLOOKUP(Tabla1[[#This Row],[Nombre Cuenta]],PLAN_CUENTAS!$B$2:$B$100,PLAN_CUENTAS!$C$2:$C$100,0,0)
A112: 46134 | B112: 2026-04 | C112: 76.099.732-3 - Leche Vegetal | D112: Orasi | E112: 102387 | F112: F | G112: Debito | H112: Ingredientes | I112: =IF(F112="F",ROUND(E112*0.19/1.19,0),0) | J112: =IF(E112="","",E112-I112) | K112: =+_xlfn.XLOOKUP(Tabla1[[#This Row],[Nombre Cuenta]],PLAN_CUENTAS!$B$2:$B$100,PLAN_CUENTAS!$A$2:$A$100,0,0) | L112: =+_xlfn.XLOOKUP(Tabla1[[#This Row],[Nombre Cuenta]],PLAN_CUENTAS!$B$2:$B$100,PLAN_CUENTAS!$C$2:$C$100,0,0)
A113: 46134 | B113: 2026-04 | C113: 76.737.642-1 - Forros Carrito | D113: Importadora y Comercializadora lecaros | E113: 52900 | F113: F | G113: Debito | H113: Inversión Carro | I113: =IF(F113="F",ROUND(E113*0.19/1.19,0),0) | J113: =IF(E113="","",E113-I113) | K113: =+_xlfn.XLOOKUP(Tabla1[[#This Row],[Nombre Cuenta]],PLAN_CUENTAS!$B$2:$B$100,PLAN_CUENTAS!$A$2:$A$100,0,0) | L113: =+_xlfn.XLOOKUP(Tabla1[[#This Row],[Nombre Cuenta]],PLAN_CUENTAS!$B$2:$B$100,PLAN_CUENTAS!$C$2:$C$100,0,0)
A114: 46135 | B114: 2026-04 | C114: 9.659.773-8 - Vidrio Carrito | D114: José Hernandez | E114: 52900 | F114: F | G114: Debito | H114: Mantención Carro | I114: =IF(F114="F",ROUND(E114*0.19/1.19,0),0) | J114: =IF(E114="","",E114-I114) | K114: =+_xlfn.XLOOKUP(Tabla1[[#This Row],[Nombre Cuenta]],PLAN_CUENTAS!$B$2:$B$100,PLAN_CUENTAS!$A$2:$A$100,0,0) | L114: =+_xlfn.XLOOKUP(Tabla1[[#This Row],[Nombre Cuenta]],PLAN_CUENTAS!$B$2:$B$100,PLAN_CUENTAS!$C$2:$C$100,0,0)
...

Sheet 3. Flujo de Caja
C1: RESUMEN MENSUAL — FAIT PAR MARIE | Plan de Cuentas 2025-2026
C2: Basado en Mes Devengo (no fecha de pago). Ingresos y costos en Monto Neto sin IVA.
A3: N | B3: CC / Cuenta | C3: 2025-01 | D3: 2025-02 | E3: 2025-03 | F3: 2025-04 | G3: 2025-05 | H3: 2025-06 | I3: 2025-07 | J3: 2025-08 | K3: 2025-09 | L3: 2025-10 | M3: 2025-11 | N3: 2025-12 | O3: 2026-01 | P3: 2026-02 | Q3: 2026-03 | R3: 2026-04 | S3: 2026-05 | T3: 2026-06 | U3: 2026-07 | V3: 2026-08 | W3: 2026-09 | X3: 2026-10 | Y3: 2026-11 | Z3: 2026-12
A4: INGRESOS
A5: 2.1 | B5: Ventas HoReCa | C5: =SUMIFS('1. INGRESOS'!$E:$E,'1. INGRESOS'!$I:$I,$A5,'1. INGRESOS'!$B:$B,C$3) | D5: =SUMIFS('1. INGRESOS'!$E:$E,'1. INGRESOS'!$I:$I,$A5,'1. INGRESOS'!$B:$B,D$3) | E5: =SUMIFS('1. INGRESOS'!$E:$E,'1. INGRESOS'!$I:$I,$A5,'1. INGRESOS'!$B:$B,E$3) | F5: =SUMIFS('1. INGRESOS'!$E:$E,'1. INGRESOS'!$I:$I,$A5,'1. INGRESOS'!$B:$B,F$3) | G5: =SUMIFS('1. INGRESOS'!$E:$E,'1. INGRESOS'!$I:$I,$A5,'1. INGRESOS'!$B:$B,G$3) | H5: =SUMIFS('1. INGRESOS'!$E:$E,'1. INGRESOS'!$I:$I,$A5,'1. INGRESOS'!$B:$B,H$3) | I5: =SUMIFS('1. INGRESOS'!$E:$E,'1. INGRESOS'!$I:$I,$A5,'1. INGRESOS'!$B:$B,I$3) | J5: =SUMIFS('1. INGRESOS'!$E:$E,'1. INGRESOS'!$I:$I,$A5,'1. INGRESOS'!$B:$B,J$3) | ... Z5: =SUMIFS('1. INGRESOS'!$E:$E,'1. INGRESOS'!$I:$I,$A5,'1. INGRESOS'!$B:$B,Z$3)
A6: 2.2 | B6: Ventas Personas (B2C) | C6: =SUMIFS('1. INGRESOS'!$E:$E,'1. INGRESOS'!$I:$I,$A6,'1. INGRESOS'!$B:$B,C$3) | D6: =SUMIFS('1. INGRESOS'!$E:$E,'1. INGRESOS'!$I:$I,$A6,'1. INGRESOS'!$B:$B,D$3) | E6: =SUMIFS('1. INGRESOS'!$E:$E,'1. INGRESOS'!$I:$I,$A6,'1. INGRESOS'!$B:$B,E$3) | F6: =SUMIFS('1. INGRESOS'!$E:$E,'1. INGRESOS'!$I:$I,$A6,'1. INGRESOS'!$B:$B,F$3) | G6: =SUMIFS('1. INGRESOS'!$E:$E,'1. INGRESOS'!$I:$I,$A6,'1. INGRESOS'!$B:$B,G$3) | H6: =SUMIFS('1. INGRESOS'!$E:$E,'1. INGRESOS'!$I:$I,$A6,'1. INGRESOS'!$B:$B,H$3) | I6: =SUMIFS('1. INGRESOS'!$E:$E,'1. INGRESOS'!$I:$I,$A6,'1. INGRESOS'!$B:$B,I$3) | J6: =SUMIFS('1. INGRESOS'!$E:$E,'1. INGRESOS'!$I:$I,$A6,'1. INGRESOS'!$B:$B,J$3) | ... Z6: =SUMIFS('1. INGRESOS'!$E:$E,'1. INGRESOS'!$I:$I,$A6,'1. INGRESOS'!$B:$B,Z$3)
A7: 2.3 | B7: Ventas Carrito | C7: =SUMIFS('1. INGRESOS'!$E:$E,'1. INGRESOS'!$I:$I,$A7,'1. INGRESOS'!$B:$B,C$3) | D7: =SUMIFS('1. INGRESOS'!$E:$E,'1. INGRESOS'!$I:$I,$A7,'1. INGRESOS'!$B:$B,D$3) | E7: =SUMIFS('1. INGRESOS'!$E:$E,'1. INGRESOS'!$I:$I,$A7,'1. INGRESOS'!$B:$B,E$3) | F7: =SUMIFS('1. INGRESOS'!$E:$E,'1. INGRESOS'!$I:$I,$A7,'1. INGRESOS'!$B:$B,F$3) | G7: =SUMIFS('1. INGRESOS'!$E:$E,'1. INGRESOS'!$I:$I,$A7,'1. INGRESOS'!$B:$B,G$3) | H7: =SUMIFS('1. INGRESOS'!$E:$E,'1. INGRESOS'!$I:$I,$A7,'1. INGRESOS'!$B:$B,H$3) | I7: =SUMIFS('1. INGRESOS'!$E:$E,'1. INGRESOS'!$I:$I,$A7,'1. INGRESOS'!$B:$B,I$3) | J7: =SUMIFS('1. INGRESOS'!$E:$E,'1. INGRESOS'!$I:$I,$A7,'1. INGRESOS'!$B:$B,J$3) | ... Z7: =SUMIFS('1. INGRESOS'!$E:$E,'1. INGRESOS'!$I:$I,$A7,'1. INGRESOS'!$B:$B,Z$3)
A8: 2.4 | B8: Ventas Ferias | C8: =SUMIFS('1. INGRESOS'!$E:$E,'1. INGRESOS'!$I:$I,$A8,'1. INGRESOS'!$B:$B,C$3) | D8: =SUMIFS('1. INGRESOS'!$E:$E,'1. INGRESOS'!$I:$I,$A8,'1. INGRESOS'!$B:$B,D$3) | E8: =SUMIFS('1. INGRESOS'!$E:$E,'1. INGRESOS'!$I:$I,$A8,'1. INGRESOS'!$B:$B,E$3) | F8: =SUMIFS('1. INGRESOS'!$E:$E,'1. INGRESOS'!$I:$I,$A8,'1. INGRESOS'!$B:$B,F$3) | G8: =SUMIFS('1. INGRESOS'!$E:$E,'1. INGRESOS'!$I:$I,$A8,'1. INGRESOS'!$B:$B,G$3) | H8: =SUMIFS('1. INGRESOS'!$E:$E,'1. INGRESOS'!$I:$I,$A8,'1. INGRESOS'!$B:$B,H$3) | I8: =SUMIFS('1. INGRESOS'!$E:$E,'1. INGRESOS'!$I:$I,$A8,'1. INGRESOS'!$B:$B,I$3) | J8: =SUMIFS('1. INGRESOS'!$E:$E,'1. INGRESOS'!$I:$I,$A8,'1. INGRESOS'!$B:$B,J$3) | ... Z8: =SUMIFS('1. INGRESOS'!$E:$E,'1. INGRESOS'!$I:$I,$A8,'1. INGRESOS'!$B:$B,Z$3)
A9: 2.5 | B9: Ventas Delivery Apps | C9: =SUMIFS('1. INGRESOS'!$E:$E,'1. INGRESOS'!$I:$I,$A9,'1. INGRESOS'!$B:$B,C$3) | D9: =SUMIFS('1. INGRESOS'!$E:$E,'1. INGRESOS'!$I:$I,$A9,'1. INGRESOS'!$B:$B,D$3) | E9: =SUMIFS('1. INGRESOS'!$E:$E,'1. INGRESOS'!$I:$I,$A9,'1. INGRESOS'!$B:$B,E$3) | F9: =SUMIFS('1. INGRESOS'!$E:$E,'1. INGRESOS'!$I:$I,$A9,'1. INGRESOS'!$B:$B,F$3) | G9: =SUMIFS('1. INGRESOS'!$E:$E,'1. INGRESOS'!$I:$I,$A9,'1. INGRESOS'!$B:$B,G$3) | H9: =SUMIFS('1. INGRESOS'!$E:$E,'1. INGRESOS'!$I:$I,$A9,'1. INGRESOS'!$B:$B,H$3) | I9: =SUMIFS('1. INGRESOS'!$E:$E,'1. INGRESOS'!$I:$I,$A9,'1. INGRESOS'!$B:$B,I$3) | J9: =SUMIFS('1. INGRESOS'!$E:$E,'1. INGRESOS'!$I:$I,$A9,'1. INGRESOS'!$B:$B,J$3) | ... Z9: =SUMIFS('1. INGRESOS'!$E:$E,'1. INGRESOS'!$I:$I,$A9,'1. INGRESOS'!$B:$B,Z$3)
A10: 2.6 | B10: Otros Ingresos | C10: =SUMIFS('1. INGRESOS'!$E:$E,'1. INGRESOS'!$I:$I,$A10,'1. INGRESOS'!$B:$B,C$3) | D10: =SUMIFS('1. INGRESOS'!$E:$E,'1. INGRESOS'!$I:$I,$A10,'1. INGRESOS'!$B:$B,D$3) | E10: =SUMIFS('1. INGRESOS'!$E:$E,'1. INGRESOS'!$I:$I,$A10,'1. INGRESOS'!$B:$B,E$3) | F10: =SUMIFS('1. INGRESOS'!$E:$E,'1. INGRESOS'!$I:$I,$A10,'1. INGRESOS'!$B:$B,F$3) | G10: =SUMIFS('1. INGRESOS'!$E:$E,'1. INGRESOS'!$I:$I,$A10,'1. INGRESOS'!$B:$B,G$3) | H10: =SUMIFS('1. INGRESOS'!$E:$E,'1. INGRESOS'!$I:$I,$A10,'1. INGRESOS'!$B:$B,H$3) | I10: =SUMIFS('1. INGRESOS'!$E:$E,'1. INGRESOS'!$I:$I,$A10,'1. INGRESOS'!$B:$B,I$3) | J10: =SUMIFS('1. INGRESOS'!$E:$E,'1. INGRESOS'!$I:$I,$A10,'1. INGRESOS'!$B:$B,J$3) | ... Z10: =SUMIFS('1. INGRESOS'!$E:$E,'1. INGRESOS'!$I:$I,$A10,'1. INGRESOS'!$B:$B,Z$3)
A11: 2.7 | B11: Descuentos y devoluciones | C11: =SUMIFS('1. INGRESOS'!$E:$E,'1. INGRESOS'!$I:$I,$A11,'1. INGRESOS'!$B:$B,C$3) | D11: =SUMIFS('1. INGRESOS'!$E:$E,'1. INGRESOS'!$I:$I,$A11,'1. INGRESOS'!$B:$B,D$3) | E11: =SUMIFS('1. INGRESOS'!$E:$E,'1. INGRESOS'!$I:$I,$A11,'1. INGRESOS'!$B:$B,E$3) | F11: =SUMIFS('1. INGRESOS'!$E:$E,'1. INGRESOS'!$I:$I,$A11,'1. INGRESOS'!$B:$B,F$3) | G11: =SUMIFS('1. INGRESOS'!$E:$E,'1. INGRESOS'!$I:$I,$A11,'1. INGRESOS'!$B:$B,G$3) | H11: =SUMIFS('1. INGRESOS'!$E:$E,'1. INGRESOS'!$I:$I,$A11,'1. INGRESOS'!$B:$B,H$3) | I11: =SUMIFS('1. INGRESOS'!$E:$E,'1. INGRESOS'!$I:$I,$A11,'1. INGRESOS'!$B:$B,I$3) | J11: =SUMIFS('1. INGRESOS'!$E:$E,'1. INGRESOS'!$I:$I,$A11,'1. INGRESOS'!$B:$B,J$3) | ... Z11: =SUMIFS('1. INGRESOS'!$E:$E,'1. INGRESOS'!$I:$I,$A11,'1. INGRESOS'!$B:$B,Z$3)
A12: TOTAL INGRESOS | C12: =SUM(C5:C10) | D12: =SUM(D5:D10) | E12: =SUM(E5:E10) | F12: =SUM(F5:F10) | G12: =SUM(G5:G10) | H12: =SUM(H5:H10) | I12: =SUM(I5:I10) | J12: =SUM(J5:J10) | ... Z12: =SUM(Z5:Z10)
A14: CC1 | B14: Costos de Producto | C14: =+SUBTOTAL(9,C15:C17) | D14: =+SUBTOTAL(9,D15:D17) | E14: =+SUBTOTAL(9,E15:E17) | F14: =+SUBTOTAL(9,F15:F17) | G14: =+SUBTOTAL(9,G15:G17) | H14: =+SUBTOTAL(9,H15:H17) | I14: =+SUBTOTAL(9,I15:I17) | J14: =+SUBTOTAL(9,J15:J17) | ... Z14: =+SUBTOTAL(9,Z15:Z17)
A15: 1.1.1 | B15: Ingredientes | C15: =SUMIFS('2. EGRESOS'!$E:$E,'2. EGRESOS'!$K:$K,$A15,'2. EGRESOS'!$B:$B,C$3) | D15: =SUMIFS('2. EGRESOS'!$E:$E,'2. EGRESOS'!$K:$K,$A15,'2. EGRESOS'!$B:$B,D$3) | E15: =SUMIFS('2. EGRESOS'!$E:$E,'2. EGRESOS'!$K:$K,$A15,'2. EGRESOS'!$B:$B,E$3) | F15: =SUMIFS('2. EGRESOS'!$E:$E,'2. EGRESOS'!$K:$K,$A15,'2. EGRESOS'!$B:$B,F$3) | G15: =SUMIFS('2. EGRESOS'!$E:$E,'2. EGRESOS'!$K:$K,$A15,'2. EGRESOS'!$B:$B,G$3) | H15: =SUMIFS('2. EGRESOS'!$E:$E,'2. EGRESOS'!$K:$K,$A15,'2. EGRESOS'!$B:$B,H$3) | I15: =SUMIFS('2. EGRESOS'!$E:$E,'2. EGRESOS'!$K:$K,$A15,'2. EGRESOS'!$B:$B,I$3) | J15: =SUMIFS('2. EGRESOS'!$E:$E,'2. EGRESOS'!$K:$K,$A15,'2. EGRESOS'!$B:$B,J$3) | ... Z15: =SUMIFS('2. EGRESOS'!$E:$E,'2. EGRESOS'!$K:$K,$A15,'2. EGRESOS'!$B:$B,Z$3)
A16: 1.1.2 | B16: Packaging | C16: =SUMIFS('2. EGRESOS'!$E:$E,'2. EGRESOS'!$K:$K,$A16,'2. EGRESOS'!$B:$B,C$3) | D16: =SUMIFS('2. EGRESOS'!$E:$E,'2. EGRESOS'!$K:$K,$A16,'2. EGRESOS'!$B:$B,D$3) | E16: =SUMIFS('2. EGRESOS'!$E:$E,'2. EGRESOS'!$K:$K,$A16,'2. EGRESOS'!$B:$B,E$3) | F16: =SUMIFS('2. EGRESOS'!$E:$E,'2. EGRESOS'!$K:$K,$A16,'2. EGRESOS'!$B:$B,F$3) | G16: =SUMIFS('2. EGRESOS'!$E:$E,'2. EGRESOS'!$K:$K,$A16,'2. EGRESOS'!$B:$B,G$3) | H16: =SUMIFS('2. EGRESOS'!$E:$E,'2. EGRESOS'!$K:$K,$A16,'2. EGRESOS'!$B:$B,H$3) | I16: =SUMIFS('2. EGRESOS'!$E:$E,'2. EGRESOS'!$K:$K,$A16,'2. EGRESOS'!$B:$B,I$3) | J16: =SUMIFS('2. EGRESOS'!$E:$E,'2. EGRESOS'!$K:$K,$A16,'2. EGRESOS'!$B:$B,J$3) | ... Z16: =SUMIFS('2. EGRESOS'!$E:$E,'2. EGRESOS'!$K:$K,$A16,'2. EGRESOS'!$B:$B,Z$3)
A17: 1.1.3 | B17: Equipamiento de cocina | C17: =SUMIFS('2. EGRESOS'!$E:$E,'2. EGRESOS'!$K:$K,$A17,'2. EGRESOS'!$B:$B,C$3) | D17: =SUMIFS('2. EGRESOS'!$E:$E,'2. EGRESOS'!$K:$K,$A17,'2. EGRESOS'!$B:$B,D$3) | E17: =SUMIFS('2. EGRESOS'!$E:$E,'2. EGRESOS'!$K:$K,$A17,'2. EGRESOS'!$B:$B,E$3) | F17: =SUMIFS('2. EGRESOS'!$E:$E,'2. EGRESOS'!$K:$K,$A17,'2. EGRESOS'!$B:$B,F$3) | G17: =SUMIFS('2. EGRESOS'!$E:$E,'2. EGRESOS'!$K:$K,$A17,'2. EGRESOS'!$B:$B,G$3) | H17: =SUMIFS('2. EGRESOS'!$E:$E,'2. EGRESOS'!$K:$K,$A17,'2. EGRESOS'!$B:$B,H$3) | I17: =SUMIFS('2. EGRESOS'!$E:$E,'2. EGRESOS'!$K:$K,$A17,'2. EGRESOS'!$B:$B,I$3) | J17: =SUMIFS('2. EGRESOS'!$E:$E,'2. EGRESOS'!$K:$K,$A17,'2. EGRESOS'!$B:$B,J$3) | ... Z17: =SUMIFS('2. EGRESOS'!$E:$E,'2. EGRESOS'!$K:$K,$A17,'2. EGRESOS'!$B:$B,Z$3)
A18: CC2 | B18: Sueldos y RRHH | C18: =+SUBTOTAL(9,C19:C23) | D18: =+SUBTOTAL(9,D19:D23) | E18: =+SUBTOTAL(9,E19:E23) | F18: =+SUBTOTAL(9,F19:F23) | G18: =+SUBTOTAL(9,G19:G23) | H18: =+SUBTOTAL(9,H19:H23) | I18: =+SUBTOTAL(9,I19:I23) | J18: =+SUBTOTAL(9,J19:J23) | ... Z18: =+SUBTOTAL(9,Z19:Z23)
A19: 1.2.1 | B19: Sueldos con Contrato | C19: =SUMIFS('2. EGRESOS'!$E:$E,'2. EGRESOS'!$K:$K,$A19,'2. EGRESOS'!$B:$B,C$3) | D19: =SUMIFS('2. EGRESOS'!$E:$E,'2. EGRESOS'!$K:$K,$A19,'2. EGRESOS'!$B:$B,D$3) | E19: =SUMIFS('2. EGRESOS'!$E:$E,'2. EGRESOS'!$K:$K,$A19,'2. EGRESOS'!$B:$B,E$3) | F19: =SUMIFS('2. EGRESOS'!$E:$E,'2. EGRESOS'!$K:$K,$A19,'2. EGRESOS'!$B:$B,F$3) | G19: =SUMIFS('2. EGRESOS'!$E:$E,'2. EGRESOS'!$K:$K,$A19,'2. EGRESOS'!$B:$B,G$3) | H19: =SUMIFS('2. EGRESOS'!$E:$E,'2. EGRESOS'!$K:$K,$A19,'2. EGRESOS'!$B:$B,H$3) | I19: =SUMIFS('2. EGRESOS'!$E:$E,'2. EGRESOS'!$K:$K,$A19,'2. EGRESOS'!$B:$B,I$3) | J19: =SUMIFS('2. EGRESOS'!$E:$E,'2. EGRESOS'!$K:$K,$A19,'2. EGRESOS'!$B:$B,J$3) | ... Z19: =SUMIFS('2. EGRESOS'!$E:$E,'2. EGRESOS'!$K:$K,$A19,'2. EGRESOS'!$B:$B,Z$3)
A20: 1.2.2 | B20: Honorarios | C20: =SUMIFS('2. EGRESOS'!$E:$E,'2. EGRESOS'!$K:$K,$A20,'2. EGRESOS'!$B:$B,C$3) | D20: =SUMIFS('2. EGRESOS'!$E:$E,'2. EGRESOS'!$K:$K,$A20,'2. EGRESOS'!$B:$B,D$3) | E20: =SUMIFS('2. EGRESOS'!$E:$E,'2. EGRESOS'!$K:$K,$A20,'2. EGRESOS'!$B:$B,E$3) | F20: =SUMIFS('2. EGRESOS'!$E:$E,'2. EGRESOS'!$K:$K,$A20,'2. EGRESOS'!$B:$B,F$3) | G20: =SUMIFS('2. EGRESOS'!$E:$E,'2. EGRESOS'!$K:$K,$A20,'2. EGRESOS'!$B:$B,G$3) | H20: =SUMIFS('2. EGRESOS'!$E:$E,'2. EGRESOS'!$K:$K,$A20,'2. EGRESOS'!$B:$B,H$3) | I20: =SUMIFS('2. EGRESOS'!$E:$E,'2. EGRESOS'!$K:$K,$A20,'2. EGRESOS'!$B:$B,I$3) | J20: =SUMIFS('2. EGRESOS'!$E:$E,'2. EGRESOS'!$K:$K,$A20,'2. EGRESOS'!$B:$B,J$3) | ... Z20: =SUMIFS('2. EGRESOS'!$E:$E,'2. EGRESOS'!$K:$K,$A20,'2. EGRESOS'!$B:$B,Z$3)
A21: 1.2.3 | B21: Asesoria Contable | C21: =SUMIFS('2. EGRESOS'!$E:$E,'2. EGRESOS'!$K:$K,$A21,'2. EGRESOS'!$B:$B,C$3) | D21: =SUMIFS('2. EGRESOS'!$E:$E,'2. EGRESOS'!$K:$K,$A21,'2. EGRESOS'!$B:$B,D$3) | E21: =SUMIFS('2. EGRESOS'!$E:$E,'2. EGRESOS'!$K:$K,$A21,'2. EGRESOS'!$B:$B,E$3) | F21: =SUMIFS('2. EGRESOS'!$E:$E,'2. EGRESOS'!$K:$K,$A21,'2. EGRESOS'!$B:$B,F$3) | G21: =SUMIFS('2. EGRESOS'!$E:$E,'2. EGRESOS'!$K:$K,$A21,'2. EGRESOS'!$B:$B,G$3) | H21: =SUMIFS('2. EGRESOS'!$E:$E,'2. EGRESOS'!$K:$K,$A21,'2. EGRESOS'!$B:$B,H$3) | I21: =SUMIFS('2. EGRESOS'!$E:$E,'2. EGRESOS'!$K:$K,$A21,'2. EGRESOS'!$B:$B,I$3) | J21: =SUMIFS('2. EGRESOS'!$E:$E,'2. EGRESOS'!$K:$K,$A21,'2. EGRESOS'!$B:$B,J$3) | ... Z21: =SUMIFS('2. EGRESOS'!$E:$E,'2. EGRESOS'!$K:$K,$A21,'2. EGRESOS'!$B:$B,Z$3)
A22: 1.2.4 | B22: Uniformes Personal | C22: =SUMIFS('2. EGRESOS'!$E:$E,'2. EGRESOS'!$K:$K,$A22,'2. EGRESOS'!$B:$B,C$3) | D22: =SUMIFS('2. EGRESOS'!$E:$E,'2. EGRESOS'!$K:$K,$A22,'2. EGRESOS'!$B:$B,D$3) | E22: =SUMIFS('2. EGRESOS'!$E:$E,'2. EGRESOS'!$K:$K,$A22,'2. EGRESOS'!$B:$B,E$3) | F22: =SUMIFS('2. EGRESOS'!$E:$E,'2. EGRESOS'!$K:$K,$A22,'2. EGRESOS'!$B:$B,F$3) | G22: =SUMIFS('2. EGRESOS'!$E:$E,'2. EGRESOS'!$K:$K,$A22,'2. EGRESOS'!$B:$B,G$3) | H22: =SUMIFS('2. EGRESOS'!$E:$E,'2. EGRESOS'!$K:$K,$A22,'2. EGRESOS'!$B:$B,H$3) | I22: =SUMIFS('2. EGRESOS'!$E:$E,'2. EGRESOS'!$K:$K,$A22,'2. EGRESOS'!$B:$B,I$3) | J22: =SUMIFS('2. EGRESOS'!$E:$E,'2. EGRESOS'!$K:$K,$A22,'2. EGRESOS'!$B:$B,J$3) | ... Z22: =SUMIFS('2. EGRESOS'!$E:$E,'2. EGRESOS'!$K:$K,$A22,'2. EGRESOS'!$B:$B,Z$3)
A23: 1.2.5 | B23: Prestamos Personal | C23: =SUMIFS('2. EGRESOS'!$E:$E,'2. EGRESOS'!$K:$K,$A23,'2. EGRESOS'!$B:$B,C$3) | D23: =SUMIFS('2. EGRESOS'!$E:$E,'2. EGRESOS'!$K:$K,$A23,'2. EGRESOS'!$B:$B,D$3) | E23: =SUMIFS('2. EGRESOS'!$E:$E,'2. EGRESOS'!$K:$K,$A23,'2. EGRESOS'!$B:$B,E$3) | F23: =SUMIFS('2. EGRESOS'!$E:$E,'2. EGRESOS'!$K:$K,$A23,'2. EGRESOS'!$B:$B,F$3) | G23: =SUMIFS('2. EGRESOS'!$E:$E,'2. EGRESOS'!$K:$K,$A23,'2. EGRESOS'!$B:$B,G$3) | H23: =SUMIFS('2. EGRESOS'!$E:$E,'2. EGRESOS'!$K:$K,$A23,'2. EGRESOS'!$B:$B,H$3) | I23: =SUMIFS('2. EGRESOS'!$E:$E,'2. EGRESOS'!$K:$K,$A23,'2. EGRESOS'!$B:$B,I$3) | J23: =SUMIFS('2. EGRESOS'!$E:$E,'2. EGRESOS'!$K:$K,$A23,'2. EGRESOS'!$B:$B,J$3) | ... Z23: =SUMIFS('2. EGRESOS'!$E:$E,'2. EGRESOS'!$K:$K,$A23,'2. EGRESOS'!$B:$B,Z$3)
A24: CC3 | B24: Infraestructura | C24: =+SUBTOTAL(9,C25:C34) | D24: =+SUBTOTAL(9,D25:D34) | E24: =+SUBTOTAL(9,E25:E34) | F24: =+SUBTOTAL(9,F25:F34) | G24: =+SUBTOTAL(9,G25:G34) | H24: =+SUBTOTAL(9,H25:H34) | I24: =+SUBTOTAL(9,I25:I34) | J24: =+SUBTOTAL(9,J25:J34) | ... Z24: =+SUBTOTAL(9,Z25:Z34)
A25: 1.3.1 | B25: Arriendo Local | C25: =SUMIFS('2. EGRESOS'!$E:$E,'2. EGRESOS'!$K:$K,$A25,'2. EGRESOS'!$B:$B,C$3) | D25: =SUMIFS('2. EGRESOS'!$E:$E,'2. EGRESOS'!$K:$K,$A25,'2. EGRESOS'!$B:$B,D$3) | E25: =SUMIFS('2. EGRESOS'!$E:$E,'2. EGRESOS'!$K:$K,$A25,'2. EGRESOS'!$B:$B,E$3) | F25: =SUMIFS('2. EGRESOS'!$E:$E,'2. EGRESOS'!$K:$K,$A25,'2. EGRESOS'!$B:$B,F$3) | G25: =SUMIFS('2. EGRESOS'!$E:$E,'2. EGRESOS'!$K:$K,$A25,'2. EGRESOS'!$B:$B,G$3) | H25: =SUMIFS('2. EGRESOS'!$E:$E,'2. EGRESOS'!$K:$K,$A25,'2. EGRESOS'!$B:$B,H$3) | I25: =SUMIFS('2. EGRESOS'!$E:$E,'2. EGRESOS'!$K:$K,$A25,'2. EGRESOS'!$B:$B,I$3) | J25: =SUMIFS('2. EGRESOS'!$E:$E,'2. EGRESOS'!$K:$K,$A25,'2. EGRESOS'!$B:$B,J$3) | ... Z25: =SUMIFS('2. EGRESOS'!$E:$E,'2. EGRESOS'!$K:$K,$A25,'2. EGRESOS'!$B:$B,Z$3)
A26: 1.3.2 | B26: Agua | C26: =SUMIFS('2. EGRESOS'!$E:$E,'2. EGRESOS'!$K:$K,$A26,'2. EGRESOS'!$B:$B,C$3) | D26: =SUMIFS('2. EGRESOS'!$E:$E,'2. EGRESOS'!$K:$K,$A26,'2. EGRESOS'!$B:$B,D$3) | E26: =SUMIFS('2. EGRESOS'!$E:$E,'2. EGRESOS'!$K:$K,$A26,'2. EGRESOS'!$B:$B,E$3) | F26: =SUMIFS('2. EGRESOS'!$E:$E,'2. EGRESOS'!$K:$K,$A26,'2. EGRESOS'!$B:$B,F$3) | G26: =SUMIFS('2. EGRESOS'!$E:$E,'2. EGRESOS'!$K:$K,$A26,'2. EGRESOS'!$B:$B,G$3) | H26: =SUMIFS('2. EGRESOS'!$E:$E,'2. EGRESOS'!$K:$K,$A26,'2. EGRESOS'!$B:$B,H$3) | I26: =SUMIFS('2. EGRESOS'!$E:$E,'2. EGRESOS'!$K:$K,$A26,'2. EGRESOS'!$B:$B,I$3) | J26: =SUMIFS('2. EGRESOS'!$E:$E,'2. EGRESOS'!$K:$K,$A26,'2. EGRESOS'!$B:$B,J$3) | ... Z26: =SUMIFS('2. EGRESOS'!$E:$E,'2. EGRESOS'!$K:$K,$A26,'2. EGRESOS'!$B:$B,Z$3)
A27: 1.3.3 | B27: Luz | C27: =SUMIFS('2. EGRESOS'!$E:$E,'2. EGRESOS'!$K:$K,$A27,'2. EGRESOS'!$B:$B,C$3) | D27: =SUMIFS('2. EGRESOS'!$E:$E,'2. EGRESOS'!$K:$K,$A27,'2. EGRESOS'!$B:$B,D$3) | E27: =SUMIFS('2. EGRESOS'!$E:$E,'2. EGRESOS'!$K:$K,$A27,'2. EGRESOS'!$B:$B,E$3) | F27: =SUMIFS('2. EGRESOS'!$E:$E,'2. EGRESOS'!$K:$K,$A27,'2. EGRESOS'!$B:$B,F$3) | G27: =SUMIFS('2. EGRESOS'!$E:$E,'2. EGRESOS'!$K:$K,$A27,'2. EGRESOS'!$B:$B,G$3) | H27: =SUMIFS('2. EGRESOS'!$E:$E,'2. EGRESOS'!$K:$K,$A27,'2. EGRESOS'!$B:$B,H$3) | I27: =SUMIFS('2. EGRESOS'!$E:$E,'2. EGRESOS'!$K:$K,$A27,'2. EGRESOS'!$B:$B,I$3) | J27: =SUMIFS('2. EGRESOS'!$E:$E,'2. EGRESOS'!$K:$K,$A27,'2. EGRESOS'!$B:$B,J$3) | ... Z27: =SUMIFS('2. EGRESOS'!$E:$E,'2. EGRESOS'!$K:$K,$A27,'2. EGRESOS'!$B:$B,Z$3)
A28: 1.3.4 | B28: Gas | C28: =SUMIFS('2. EGRESOS'!$E:$E,'2. EGRESOS'!$K:$K,$A28,'2. EGRESOS'!$B:$B,C$3) | D28: =SUMIFS('2. EGRESOS'!$E:$E,'2. EGRESOS'!$K:$K,$A28,'2. EGRESOS'!$B:$B,D$3) | E28: =SUMIFS('2. EGRESOS'!$E:$E,'2. EGRESOS'!$K:$K,$A28,'2. EGRESOS'!$B:$B,E$3) | F28: =SUMIFS('2. EGRESOS'!$E:$E,'2. EGRESOS'!$K:$K,$A28,'2. EGRESOS'!$B:$B,F$3) | G28: =SUMIFS('2. EGRESOS'!$E:$E,'2. EGRESOS'!$K:$K,$A28,'2. EGRESOS'!$B:$B,G$3) | H28: =SUMIFS('2. EGRESOS'!$E:$E,'2. EGRESOS'!$K:$K,$A28,'2. EGRESOS'!$B:$B,H$3) | I28: =SUMIFS('2. EGRESOS'!$E:$E,'2. EGRESOS'!$K:$K,$A28,'2. EGRESOS'!$B:$B,I$3) | J28: =SUMIFS('2. EGRESOS'!$E:$E,'2. EGRESOS'!$K:$K,$A28,'2. EGRESOS'!$B:$B,J$3) | ... Z28: =SUMIFS('2. EGRESOS'!$E:$E,'2. EGRESOS'!$K:$K,$A28,'2. EGRESOS'!$B:$B,Z$3)
A29: 1.3.5 | B29: Telecomunicaciones | C29: =SUMIFS('2. EGRESOS'!$E:$E,'2. EGRESOS'!$K:$K,$A29,'2. EGRESOS'!$B:$B,C$3) | D29: =SUMIFS('2. EGRESOS'!$E:$E,'2. EGRESOS'!$K:$K,$A29,'2. EGRESOS'!$B:$B,D$3) | E29: =SUMIFS('2. EGRESOS'!$E:$E,'2. EGRESOS'!$K:$K,$A29,'2. EGRESOS'!$B:$B,E$3) | F29: =SUMIFS('2. EGRESOS'!$E:$E,'2. EGRESOS'!$K:$K,$A29,'2. EGRESOS'!$B:$B,F$3) | G29: =SUMIFS('2. EGRESOS'!$E:$E,'2. EGRESOS'!$K:$K,$A29,'2. EGRESOS'!$B:$B,G$3) | H29: =SUMIFS('2. EGRESOS'!$E:$E,'2. EGRESOS'!$K:$K,$A29,'2. EGRESOS'!$B:$B,H$3) | I29: =SUMIFS('2. EGRESOS'!$E:$E,'2. EGRESOS'!$K:$K,$A29,'2. EGRESOS'!$B:$B,I$3) | J29: =SUMIFS('2. EGRESOS'!$E:$E,'2. EGRESOS'!$K:$K,$A29,'2. EGRESOS'!$B:$B,J$3) | ... Z29: =SUMIFS('2. EGRESOS'!$E:$E,'2. EGRESOS'!$K:$K,$A29,'2. EGRESOS'!$B:$B,Z$3)
A30: 1.3.6 | B30: Mantenciones | C30: =SUMIFS('2. EGRESOS'!$E:$E,'2. EGRESOS'!$K:$K,$A30,'2. EGRESOS'!$B:$B,C$3) | D30: =SUMIFS('2. EGRESOS'!$E:$E,'2. EGRESOS'!$K:$K,$A30,'2. EGRESOS'!$B:$B,D$3) | E30: =SUMIFS('2. EGRESOS'!$E:$E,'2. EGRESOS'!$K:$K,$A30,'2. EGRESOS'!$B:$B,E$3) | F30: =SUMIFS('2. EGRESOS'!$E:$E,'2. EGRESOS'!$K:$K,$A30,'2. EGRESOS'!$B:$B,F$3) | G30: =SUMIFS('2. EGRESOS'!$E:$E,'2. EGRESOS'!$K:$K,$A30,'2. EGRESOS'!$B:$B,G$3) | H30: =SUMIFS('2. EGRESOS'!$E:$E,'2. EGRESOS'!$K:$K,$A30,'2. EGRESOS'!$B:$B,H$3) | I30: =SUMIFS('2. EGRESOS'!$E:$E,'2. EGRESOS'!$K:$K,$A30,'2. EGRESOS'!$B:$B,I$3) | J30: =SUMIFS('2. EGRESOS'!$E:$E,'2. EGRESOS'!$K:$K,$A30,'2. EGRESOS'!$B:$B,J$3) | ... Z30: =SUMIFS('2. EGRESOS'!$E:$E,'2. EGRESOS'!$K:$K,$A30,'2. EGRESOS'!$B:$B,Z$3)
A31: 1.3.7 | B31: Fumigaciones | C31: =SUMIFS('2. EGRESOS'!$E:$E,'2. EGRESOS'!$K:$K,$A31,'2. EGRESOS'!$B:$B,C$3) | D31: =SUMIFS('2. EGRESOS'!$E:$E,'2. EGRESOS'!$K:$K,$A31,'2. EGRESOS'!$B:$B,D$3) | E31: =SUMIFS('2. EGRESOS'!$E:$E,'2. EGRESOS'!$K:$K,$A31,'2. EGRESOS'!$B:$B,E$3) | F31: =SUMIFS('2. EGRESOS'!$E:$E,'2. EGRESOS'!$K:$K,$A31,'2. EGRESOS'!$B:$B,F$3) | G31: =SUMIFS('2. EGRESOS'!$E:$E,'2. EGRESOS'!$K:$K,$A31,'2. EGRESOS'!$B:$B,G$3) | H31: =SUMIFS('2. EGRESOS'!$E:$E,'2. EGRESOS'!$K:$K,$A31,'2. EGRESOS'!$B:$B,H$3) | I31: =SUMIFS('2. EGRESOS'!$E:$E,'2. EGRESOS'!$K:$K,$A31,'2. EGRESOS'!$B:$B,I$3) | J31: =SUMIFS('2. EGRESOS'!$E:$E,'2. EGRESOS'!$K:$K,$A31,'2. EGRESOS'!$B:$B,J$3) | ... Z31: =SUMIFS('2. EGRESOS'!$E:$E,'2. EGRESOS'!$K:$K,$A31,'2. EGRESOS'!$B:$B,Z$3)
A32: 1.3.8 | B32: Limpieza y Aseo | C32: =SUMIFS('2. EGRESOS'!$E:$E,'2. EGRESOS'!$K:$K,$A32,'2. EGRESOS'!$B:$B,C$3) | D32: =SUMIFS('2. EGRESOS'!$E:$E,'2. EGRESOS'!$K:$K,$A32,'2. EGRESOS'!$B:$B,D$3) | E32: =SUMIFS('2. EGRESOS'!$E:$E,'2. EGRESOS'!$K:$K,$A32,'2. EGRESOS'!$B:$B,E$3) | F32: =SUMIFS('2. EGRESOS'!$E:$E,'2. EGRESOS'!$K:$K,$A32,'2. EGRESOS'!$B:$B,F$3) | G32: =SUMIFS('2. EGRESOS'!$E:$E,'2. EGRESOS'!$K:$K,$A32,'2. EGRESOS'!$B:$B,G$3) | H32: =SUMIFS('2. EGRESOS'!$E:$E,'2. EGRESOS'!$K:$K,$A32,'2. EGRESOS'!$B:$B,H$3) | I32: =SUMIFS('2. EGRESOS'!$E:$E,'2. EGRESOS'!$K:$K,$A32,'2. EGRESOS'!$B:$B,I$3) | J32: =SUMIFS('2. EGRESOS'!$E:$E,'2. EGRESOS'!$K:$K,$A32,'2. EGRESOS'!$B:$B,J$3) | ... Z32: =SUMIFS('2. EGRESOS'!$E:$E,'2. EGRESOS'!$K:$K,$A32,'2. EGRESOS'!$B:$B,Z$3)
A33: 1.3.9 | B33: Seguridad | C33: =SUMIFS('2. EGRESOS'!$E:$E,'2. EGRESOS'!$K:$K,$A33,'2. EGRESOS'!$B:$B,C$3) | D33: =SUMIFS('2. EGRESOS'!$E:$E,'2. EGRESOS'!$K:$K,$A33,'2. EGRESOS'!$B:$B,D$3) | E33: =SUMIFS('2. EGRESOS'!$E:$E,'2. EGRESOS'!$K:$K,$A33,'2. EGRESOS'!$B:$B,E$3) | F33: =SUMIFS('2. EGRESOS'!$E:$E,'2. EGRESOS'!$K:$K,$A33,'2. EGRESOS'!$B:$B,F$3) | G33: =SUMIFS('2. EGRESOS'!$E:$E,'2. EGRESOS'!$K:$K,$A33,'2. EGRESOS'!$B:$B,G$3) | H33: =SUMIFS('2. EGRESOS'!$E:$E,'2. EGRESOS'!$K:$K,$A33,'2. EGRESOS'!$B:$B,H$3) | I33: =SUMIFS('2. EGRESOS'!$E:$E,'2. EGRESOS'!$K:$K,$A33,'2. EGRESOS'!$B:$B,I$3) | J33: =SUMIFS('2. EGRESOS'!$E:$E,'2. EGRESOS'!$K:$K,$A33,'2. EGRESOS'!$B:$B,J$3) | ... Z33: =SUMIFS('2. EGRESOS'!$E:$E,'2. EGRESOS'!$K:$K,$A33,'2. EGRESOS'!$B:$B,Z$3)
A34: 1.3.10 | B34: Equipamiento Local | C34: =SUMIFS('2. EGRESOS'!$E:$E,'2. EGRESOS'!$K:$K,$A34,'2. EGRESOS'!$B:$B,C$3) | D34: =SUMIFS('2. EGRESOS'!$E:$E,'2. EGRESOS'!$K:$K,$A34,'2. EGRESOS'!$B:$B,D$3) | E34: =SUMIFS('2. EGRESOS'!$E:$E,'2. EGRESOS'!$K:$K,$A34,'2. EGRESOS'!$B:$B,E$3) | F34: =SUMIFS('2. EGRESOS'!$E:$E,'2. EGRESOS'!$K:$K,$A34,'2. EGRESOS'!$B:$B,F$3) | G34: =SUMIFS('2. EGRESOS'!$E:$E,'2. EGRESOS'!$K:$K,$A34,'2. EGRESOS'!$B:$B,G$3) | H34: =SUMIFS('2. EGRESOS'!$E:$E,'2. EGRESOS'!$K:$K,$A34,'2. EGRESOS'!$B:$B,H$3) | I34: =SUMIFS('2. EGRESOS'!$E:$E,'2. EGRESOS'!$K:$K,$A34,'2. EGRESOS'!$B:$B,I$3) | J34: =SUMIFS('2. EGRESOS'!$E:$E,'2. EGRESOS'!$K:$K,$A34,'2. EGRESOS'!$B:$B,J$3) | ... Z34: =SUMIFS('2. EGRESOS'!$E:$E,'2. EGRESOS'!$K:$K,$A34,'2. EGRESOS'!$B:$B,Z$3)
A35: CC4 | B35: Carrito | C35: =+SUBTOTAL(9,C36:C40) | D35: =+SUBTOTAL(9,D36:D40) | E35: =+SUBTOTAL(9,E36:E40) | F35: =+SUBTOTAL(9,F36:F40) | G35: =+SUBTOTAL(9,G36:G40) | H35: =+SUBTOTAL(9,H36:H40) | I35: =+SUBTOTAL(9,I36:I40) | J35: =+SUBTOTAL(9,J36:J40) | ... Z35: =+SUBTOTAL(9,Z36:Z40)
A36: 1.4.1 | B36: Inversión Carro | C36: =SUMIFS('2. EGRESOS'!$E:$E,'2. EGRESOS'!$K:$K,$A36,'2. EGRESOS'!$B:$B,C$3) | D36: =SUMIFS('2. EGRESOS'!$E:$E,'2. EGRESOS'!$K:$K,$A36,'2. EGRESOS'!$B:$B,D$3) | E36: =SUMIFS('2. EGRESOS'!$E:$E,'2. EGRESOS'!$K:$K,$A36,'2. EGRESOS'!$B:$B,E$3) | F36: =SUMIFS('2. EGRESOS'!$E:$E,'2. EGRESOS'!$K:$K,$A36,'2. EGRESOS'!$B:$B,F$3) | G36: =SUMIFS('2. EGRESOS'!$E:$E,'2. EGRESOS'!$K:$K,$A36,'2. EGRESOS'!$B:$B,G$3) | H36: =SUMIFS('2. EGRESOS'!$E:$E,'2. EGRESOS'!$K:$K,$A36,'2. EGRESOS'!$B:$B,H$3) | I36: =SUMIFS('2. EGRESOS'!$E:$E,'2. EGRESOS'!$K:$K,$A36,'2. EGRESOS'!$B:$B,I$3) | J36: =SUMIFS('2. EGRESOS'!$E:$E,'2. EGRESOS'!$K:$K,$A36,'2. EGRESOS'!$B:$B,J$3) | ... Z36: =SUMIFS('2. EGRESOS'!$E:$E,'2. EGRESOS'!$K:$K,$A36,'2. EGRESOS'!$B:$B,Z$3)
A37: 1.4.2 | B37: Mantención Carro | C37: =SUMIFS('2. EGRESOS'!$E:$E,'2. EGRESOS'!$K:$K,$A37,'2. EGRESOS'!$B:$B,C$3) | D37: =SUMIFS('2. EGRESOS'!$E:$E,'2. EGRESOS'!$K:$K,$A37,'2. EGRESOS'!$B:$B,D$3) | E37: =SUMIFS('2. EGRESOS'!$E:$E,'2. EGRESOS'!$K:$K,$A37,'2. EGRESOS'!$B:$B,E$3) | F37: =SUMIFS('2. EGRESOS'!$E:$E,'2. EGRESOS'!$K:$K,$A37,'2. EGRESOS'!$B:$B,F$3) | G37: =SUMIFS('2. EGRESOS'!$E:$E,'2. EGRESOS'!$K:$K,$A37,'2. EGRESOS'!$B:$B,G$3) | H37: =SUMIFS('2. EGRESOS'!$E:$E,'2. EGRESOS'!$K:$K,$A37,'2. EGRESOS'!$B:$B,H$3) | I37: =SUMIFS('2. EGRESOS'!$E:$E,'2. EGRESOS'!$K:$K,$A37,'2. EGRESOS'!$B:$B,I$3) | J37: =SUMIFS('2. EGRESOS'!$E:$E,'2. EGRESOS'!$K:$K,$A37,'2. EGRESOS'!$B:$B,J$3) | ... Z37: =SUMIFS('2. EGRESOS'!$E:$E,'2. EGRESOS'!$K:$K,$A37,'2. EGRESOS'!$B:$B,Z$3)
A38: 1.4.3 | B38: Materiales Aseo Carro | C38: =SUMIFS('2. EGRESOS'!$E:$E,'2. EGRESOS'!$K:$K,$A38,'2. EGRESOS'!$B:$B,C$3) | D38: =SUMIFS('2. EGRESOS'!$E:$E,'2. EGRESOS'!$K:$K,$A38,'2. EGRESOS'!$B:$B,D$3) | E38: =SUMIFS('2. EGRESOS'!$E:$E,'2. EGRESOS'!$K:$K,$A38,'2. EGRESOS'!$B:$B,E$3) | F38: =SUMIFS('2. EGRESOS'!$E:$E,'2. EGRESOS'!$K:$K,$A38,'2. EGRESOS'!$B:$B,F$3) | G38: =SUMIFS('2. EGRESOS'!$E:$E,'2. EGRESOS'!$K:$K,$A38,'2. EGRESOS'!$B:$B,G$3) | H38: =SUMIFS('2. EGRESOS'!$E:$E,'2. EGRESOS'!$K:$K,$A38,'2. EGRESOS'!$B:$B,H$3) | I38: =SUMIFS('2. EGRESOS'!$E:$E,'2. EGRESOS'!$K:$K,$A38,'2. EGRESOS'!$B:$B,I$3) | J38: =SUMIFS('2. EGRESOS'!$E:$E,'2. EGRESOS'!$K:$K,$A38,'2. EGRESOS'!$B:$B,J$3) | ... Z38: =SUMIFS('2. EGRESOS'!$E:$E,'2. EGRESOS'!$K:$K,$A38,'2. EGRESOS'!$B:$B,Z$3)
A39: 1.4.4 | B39: Despacho Carro | C39: =SUMIFS('2. EGRESOS'!$E:$E,'2. EGRESOS'!$K:$K,$A39,'2. EGRESOS'!$B:$B,C$3) | D39: =SUMIFS('2. EGRESOS'!$E:$E,'2. EGRESOS'!$K:$K,$A39,'2. EGRESOS'!$B:$B,D$3) | E39: =SUMIFS('2. EGRESOS'!$E:$E,'2. EGRESOS'!$K:$K,$A39,'2. EGRESOS'!$B:$B,E$3) | F39: =SUMIFS('2. EGRESOS'!$E:$E,'2. EGRESOS'!$K:$K,$A39,'2. EGRESOS'!$B:$B,F$3) | G39: =SUMIFS('2. EGRESOS'!$E:$E,'2. EGRESOS'!$K:$K,$A39,'2. EGRESOS'!$B:$B,G$3) | H39: =SUMIFS('2. EGRESOS'!$E:$E,'2. EGRESOS'!$K:$K,$A39,'2. EGRESOS'!$B:$B,H$3) | I39: =SUMIFS('2. EGRESOS'!$E:$E,'2. EGRESOS'!$K:$K,$A39,'2. EGRESOS'!$B:$B,I$3) | J39: =SUMIFS('2. EGRESOS'!$E:$E,'2. EGRESOS'!$K:$K,$A39,'2. EGRESOS'!$B:$B,J$3) | ... Z39: =SUMIFS('2. EGRESOS'!$E:$E,'2. EGRESOS'!$K:$K,$A39,'2. EGRESOS'!$B:$B,Z$3)
A40: 1.4.5 | B40: Sueldos Carro | C40: =SUMIFS('2. EGRESOS'!$E:$E,'2. EGRESOS'!$K:$K,$A40,'2. EGRESOS'!$B:$B,C$3) | D40: =SUMIFS('2. EGRESOS'!$E:$E,'2. EGRESOS'!$K:$K,$A40,'2. EGRESOS'!$B:$B,D$3) | E40: =SUMIFS('2. EGRESOS'!$E:$E,'2. EGRESOS'!$K:$K,$A40,'2. EGRESOS'!$B:$B,E$3) | F40: =SUMIFS('2. EGRESOS'!$E:$E,'2. EGRESOS'!$K:$K,$A40,'2. EGRESOS'!$B:$B,F$3) | G40: =SUMIFS('2. EGRESOS'!$E:$E,'2. EGRESOS'!$K:$K,$A40,'2. EGRESOS'!$B:$B,G$3) | H40: =SUMIFS('2. EGRESOS'!$E:$E,'2. EGRESOS'!$K:$K,$A40,'2. EGRESOS'!$B:$B,H$3) | I40: =SUMIFS('2. EGRESOS'!$E:$E,'2. EGRESOS'!$K:$K,$A40,'2. EGRESOS'!$B:$B,I$3) | J40: =SUMIFS('2. EGRESOS'!$E:$E,'2. EGRESOS'!$K:$K,$A40,'2. EGRESOS'!$B:$B,J$3) | ... Z40: =SUMIFS('2. EGRESOS'!$E:$E,'2. EGRESOS'!$K:$K,$A40,'2. EGRESOS'!$B:$B,Z$3)
A41: CC5 | B41: SAAS | C41: =+SUBTOTAL(9,C42:C43) | D41: =+SUBTOTAL(9,D42:D43) | E41: =+SUBTOTAL(9,E42:E43) | F41: =+SUBTOTAL(9,F42:F43) | G41: =+SUBTOTAL(9,G42:G43) | H41: =+SUBTOTAL(9,H42:H43) | I41: =+SUBTOTAL(9,I42:I43) | J41: =+SUBTOTAL(9,J42:J43) | ... Z41: =+SUBTOTAL(9,Z42:Z43)
A42: 1.5.1 | B42: Plataformas digitales | C42: =SUMIFS('2. EGRESOS'!$E:$E,'2. EGRESOS'!$K:$K,$A42,'2. EGRESOS'!$B:$B,C$3) | D42: =SUMIFS('2. EGRESOS'!$E:$E,'2. EGRESOS'!$K:$K,$A42,'2. EGRESOS'!$B:$B,D$3) | E42: =SUMIFS('2. EGRESOS'!$E:$E,'2. EGRESOS'!$K:$K,$A42,'2. EGRESOS'!$B:$B,E$3) | F42: =SUMIFS('2. EGRESOS'!$E:$E,'2. EGRESOS'!$K:$K,$A42,'2. EGRESOS'!$B:$B,F$3) | G42: =SUMIFS('2. EGRESOS'!$E:$E,'2. EGRESOS'!$K:$K,$A42,'2. EGRESOS'!$B:$B,G$3) | H42: =SUMIFS('2. EGRESOS'!$E:$E,'2. EGRESOS'!$K:$K,$A42,'2. EGRESOS'!$B:$B,H$3) | I42: =SUMIFS('2. EGRESOS'!$E:$E,'2. EGRESOS'!$K:$K,$A42,'2. EGRESOS'!$B:$B,I$3) | J42: =SUMIFS('2. EGRESOS'!$E:$E,'2. EGRESOS'!$K:$K,$A42,'2. EGRESOS'!$B:$B,J$3) | ... Z42: =SUMIFS('2. EGRESOS'!$E:$E,'2. EGRESOS'!$K:$K,$A42,'2. EGRESOS'!$B:$B,Z$3)
A43: 1.5.2 | B43: Variables SAAS | C43: =SUMIFS('2. EGRESOS'!$E:$E,'2. EGRESOS'!$K:$K,$A43,'2. EGRESOS'!$B:$B,C$3) | D43: =SUMIFS('2. EGRESOS'!$E:$E,'2. EGRESOS'!$K:$K,$A43,'2. EGRESOS'!$B:$B,D$3) | E43: =SUMIFS('2. EGRESOS'!$E:$E,'2. EGRESOS'!$K:$K,$A43,'2. EGRESOS'!$B:$B,E$3) | F43: =SUMIFS('2. EGRESOS'!$E:$E,'2. EGRESOS'!$K:$K,$A43,'2. EGRESOS'!$B:$B,F$3) | G43: =SUMIFS('2. EGRESOS'!$E:$E,'2. EGRESOS'!$K:$K,$A43,'2. EGRESOS'!$B:$B,G$3) | H43: =SUMIFS('2. EGRESOS'!$E:$E,'2. EGRESOS'!$K:$K,$A43,'2. EGRESOS'!$B:$B,H$3) | I43: =SUMIFS('2. EGRESOS'!$E:$E,'2. EGRESOS'!$K:$K,$A43,'2. EGRESOS'!$B:$B,I$3) | J43: =SUMIFS('2. EGRESOS'!$E:$E,'2. EGRESOS'!$K:$K,$A43,'2. EGRESOS'!$B:$B,J$3) | ... Z43: =SUMIFS('2. EGRESOS'!$E:$E,'2. EGRESOS'!$K:$K,$A43,'2. EGRESOS'!$B:$B,Z$3)
A44: CC6 | B44: Marketing y Publicidad | C44: =+SUBTOTAL(9,C45:C47) | D44: =+SUBTOTAL(9,D45:D47) | E44: =+SUBTOTAL(9,E45:E47) | F44: =+SUBTOTAL(9,F45:F47) | G44: =+SUBTOTAL(9,G45:G47) | H44: =+SUBTOTAL(9,H45:H47) | I44: =+SUBTOTAL(9,I45:I47) | J44: =+SUBTOTAL(9,J45:J47) | ... Z44: =+SUBTOTAL(9,Z45:Z47)
A45: 1.6.1 | B45: RRSS | C45: =SUMIFS('2. EGRESOS'!$E:$E,'2. EGRESOS'!$K:$K,$A45,'2. EGRESOS'!$B:$B,C$3) | D45: =SUMIFS('2. EGRESOS'!$E:$E,'2. EGRESOS'!$K:$K,$A45,'2. EGRESOS'!$B:$B,D$3) | E45: =SUMIFS('2. EGRESOS'!$E:$E,'2. EGRESOS'!$K:$K,$A45,'2. EGRESOS'!$B:$B,E$3) | F45: =SUMIFS('2. EGRESOS'!$E:$E,'2. EGRESOS'!$K:$K,$A45,'2. EGRESOS'!$B:$B,F$3) | G45: =SUMIFS('2. EGRESOS'!$E:$E,'2. EGRESOS'!$K:$K,$A45,'2. EGRESOS'!$B:$B,G$3) | H45: =SUMIFS('2. EGRESOS'!$E:$E,'2. EGRESOS'!$K:$K,$A45,'2. EGRESOS'!$B:$B,H$3) | I45: =SUMIFS('2. EGRESOS'!$E:$E,'2. EGRESOS'!$K:$K,$A45,'2. EGRESOS'!$B:$B,I$3) | J45: =SUMIFS('2. EGRESOS'!$E:$E,'2. EGRESOS'!$K:$K,$A45,'2. EGRESOS'!$B:$B,J$3) | ... Z45: =SUMIFS('2. EGRESOS'!$E:$E,'2. EGRESOS'!$K:$K,$A45,'2. EGRESOS'!$B:$B,Z$3)
A46: 1.6.2 | B46: Producción Audiosvisual | C46: =SUMIFS('2. EGRESOS'!$E:$E,'2. EGRESOS'!$K:$K,$A46,'2. EGRESOS'!$B:$B,C$3) | D46: =SUMIFS('2. EGRESOS'!$E:$E,'2. EGRESOS'!$K:$K,$A46,'2. EGRESOS'!$B:$B,D$3) | E46: =SUMIFS('2. EGRESOS'!$E:$E,'2. EGRESOS'!$K:$K,$A46,'2. EGRESOS'!$B:$B,E$3) | F46: =SUMIFS('2. EGRESOS'!$E:$E,'2. EGRESOS'!$K:$K,$A46,'2. EGRESOS'!$B:$B,F$3) | G46: =SUMIFS('2. EGRESOS'!$E:$E,'2. EGRESOS'!$K:$K,$A46,'2. EGRESOS'!$B:$B,G$3) | H46: =SUMIFS('2. EGRESOS'!$E:$E,'2. EGRESOS'!$K:$K,$A46,'2. EGRESOS'!$B:$B,H$3) | I46: =SUMIFS('2. EGRESOS'!$E:$E,'2. EGRESOS'!$K:$K,$A46,'2. EGRESOS'!$B:$B,I$3) | J46: =SUMIFS('2. EGRESOS'!$E:$E,'2. EGRESOS'!$K:$K,$A46,'2. EGRESOS'!$B:$B,J$3) | ... Z46: =SUMIFS('2. EGRESOS'!$E:$E,'2. EGRESOS'!$K:$K,$A46,'2. EGRESOS'!$B:$B,Z$3)
A47: 1.6.3 | B47: Ferias y Eventos | C47: =SUMIFS('2. EGRESOS'!$E:$E,'2. EGRESOS'!$K:$K,$A47,'2. EGRESOS'!$B:$B,C$3) | D47: =SUMIFS('2. EGRESOS'!$E:$E,'2. EGRESOS'!$K:$K,$A47,'2. EGRESOS'!$B:$B,D$3) | E47: =SUMIFS('2. EGRESOS'!$E:$E,'2. EGRESOS'!$K:$K,$A47,'2. EGRESOS'!$B:$B,E$3) | F47: =SUMIFS('2. EGRESOS'!$E:$E,'2. EGRESOS'!$K:$K,$A47,'2. EGRESOS'!$B:$B,F$3) | G47: =SUMIFS('2. EGRESOS'!$E:$E,'2. EGRESOS'!$K:$K,$A47,'2. EGRESOS'!$B:$B,G$3) | H47: =SUMIFS('2. EGRESOS'!$E:$E,'2. EGRESOS'!$K:$K,$A47,'2. EGRESOS'!$B:$B,H$3) | I47: =SUMIFS('2. EGRESOS'!$E:$E,'2. EGRESOS'!$K:$K,$A47,'2. EGRESOS'!$B:$B,I$3) | J47: =SUMIFS('2. EGRESOS'!$E:$E,'2. EGRESOS'!$K:$K,$A47,'2. EGRESOS'!$B:$B,J$3) | ... Z47: =SUMIFS('2. EGRESOS'!$E:$E,'2. EGRESOS'!$K:$K,$A47,'2. EGRESOS'!$B:$B,Z$3)
A48: CC7 | B48: Envios y Logistica | C48: =+SUBTOTAL(9,C49:C51) | D48: =+SUBTOTAL(9,D49:D51) | E48: =+SUBTOTAL(9,E49:E51) | F48: =+SUBTOTAL(9,F49:F51) | G48: =+SUBTOTAL(9,G49:G51) | H48: =+SUBTOTAL(9,H49:H51) | I48: =+SUBTOTAL(9,I49:I51) | J48: =+SUBTOTAL(9,J49:J51) | ... Z48: =+SUBTOTAL(9,Z49:Z51)
A49: 1.7.1 | B49: Despachos B2B (Gaspar) | C49: =SUMIFS('2. EGRESOS'!$E:$E,'2. EGRESOS'!$K:$K,$A49,'2. EGRESOS'!$B:$B,C$3) | D49: =SUMIFS('2. EGRESOS'!$E:$E,'2. EGRESOS'!$K:$K,$A49,'2. EGRESOS'!$B:$B,D$3) | E49: =SUMIFS('2. EGRESOS'!$E:$E,'2. EGRESOS'!$K:$K,$A49,'2. EGRESOS'!$B:$B,E$3) | F49: =SUMIFS('2. EGRESOS'!$E:$E,'2. EGRESOS'!$K:$K,$A49,'2. EGRESOS'!$B:$B,F$3) | G49: =SUMIFS('2. EGRESOS'!$E:$E,'2. EGRESOS'!$K:$K,$A49,'2. EGRESOS'!$B:$B,G$3) | H49: =SUMIFS('2. EGRESOS'!$E:$E,'2. EGRESOS'!$K:$K,$A49,'2. EGRESOS'!$B:$B,H$3) | I49: =SUMIFS('2. EGRESOS'!$E:$E,'2. EGRESOS'!$K:$K,$A49,'2. EGRESOS'!$B:$B,I$3) | J49: =SUMIFS('2. EGRESOS'!$E:$E,'2. EGRESOS'!$K:$K,$A49,'2. EGRESOS'!$B:$B,J$3) | ... Z49: =SUMIFS('2. EGRESOS'!$E:$E,'2. EGRESOS'!$K:$K,$A49,'2. EGRESOS'!$B:$B,Z$3)
A50: 1.7.2 | B50: Despachos (B2C) | C50: =SUMIFS('2. EGRESOS'!$E:$E,'2. EGRESOS'!$K:$K,$A50,'2. EGRESOS'!$B:$B,C$3) | D50: =SUMIFS('2. EGRESOS'!$E:$E,'2. EGRESOS'!$K:$K,$A50,'2. EGRESOS'!$B:$B,D$3) | E50: =SUMIFS('2. EGRESOS'!$E:$E,'2. EGRESOS'!$K:$K,$A50,'2. EGRESOS'!$B:$B,E$3) | F50: =SUMIFS('2. EGRESOS'!$E:$E,'2. EGRESOS'!$K:$K,$A50,'2. EGRESOS'!$B:$B,F$3) | G50: =SUMIFS('2. EGRESOS'!$E:$E,'2. EGRESOS'!$K:$K,$A50,'2. EGRESOS'!$B:$B,G$3) | H50: =SUMIFS('2. EGRESOS'!$E:$E,'2. EGRESOS'!$K:$K,$A50,'2. EGRESOS'!$B:$B,H$3) | I50: =SUMIFS('2. EGRESOS'!$E:$E,'2. EGRESOS'!$K:$K,$A50,'2. EGRESOS'!$B:$B,I$3) | J50: =SUMIFS('2. EGRESOS'!$E:$E,'2. EGRESOS'!$K:$K,$A50,'2. EGRESOS'!$B:$B,J$3) | ... Z50: =SUMIFS('2. EGRESOS'!$E:$E,'2. EGRESOS'!$K:$K,$A50,'2. EGRESOS'!$B:$B,Z$3)
A51: 1.7.3 | B51: Transporte personas (empleados) | C51: =SUMIFS('2. EGRESOS'!$E:$E,'2. EGRESOS'!$K:$K,$A51,'2. EGRESOS'!$B:$B,C$3) | D51: =SUMIFS('2. EGRESOS'!$E:$E,'2. EGRESOS'!$K:$K,$A51,'2. EGRESOS'!$B:$B,D$3) | E51: =SUMIFS('2. EGRESOS'!$E:$E,'2. EGRESOS'!$K:$K,$A51,'2. EGRESOS'!$B:$B,E$3) | F51: =SUMIFS('2. EGRESOS'!$E:$E,'2. EGRESOS'!$K:$K,$A51,'2. EGRESOS'!$B:$B,F$3) | G51: =SUMIFS('2. EGRESOS'!$E:$E,'2. EGRESOS'!$K:$K,$A51,'2. EGRESOS'!$B:$B,G$3) | H51: =SUMIFS('2. EGRESOS'!$E:$E,'2. EGRESOS'!$K:$K,$A51,'2. EGRESOS'!$B:$B,H$3) | I51: =SUMIFS('2. EGRESOS'!$E:$E,'2. EGRESOS'!$K:$K,$A51,'2. EGRESOS'!$B:$B,I$3) | J51: =SUMIFS('2. EGRESOS'!$E:$E,'2. EGRESOS'!$K:$K,$A51,'2. EGRESOS'!$B:$B,J$3) | ... Z51: =SUMIFS('2. EGRESOS'!$E:$E,'2. EGRESOS'!$K:$K,$A51,'2. EGRESOS'!$B:$B,Z$3)
A52: CC8 | B52: Comisiones de Venta | C52: =+SUBTOTAL(9,C53:C55) | D52: =+SUBTOTAL(9,D53:D55) | E52: =+SUBTOTAL(9,E53:E55) | F52: =+SUBTOTAL(9,F53:F55) | G52: =+SUBTOTAL(9,G53:G55) | H52: =+SUBTOTAL(9,H53:H55) | I52: =+SUBTOTAL(9,I53:I55) | J52: =+SUBTOTAL(9,J53:J55) | ... Z52: =+SUBTOTAL(9,Z53:Z55)
A53: 1.8.1 | B53: Comision Getnet + TUU | C53: =SUMIFS('2. EGRESOS'!$E:$E,'2. EGRESOS'!$K:$K,$A53,'2. EGRESOS'!$B:$B,C$3) | D53: =SUMIFS('2. EGRESOS'!$E:$E,'2. EGRESOS'!$K:$K,$A53,'2. EGRESOS'!$B:$B,D$3) | E53: =SUMIFS('2. EGRESOS'!$E:$E,'2. EGRESOS'!$K:$K,$A53,'2. EGRESOS'!$B:$B,E$3) | F53: =SUMIFS('2. EGRESOS'!$E:$E,'2. EGRESOS'!$K:$K,$A53,'2. EGRESOS'!$B:$B,F$3) | G53: =SUMIFS('2. EGRESOS'!$E:$E,'2. EGRESOS'!$K:$K,$A53,'2. EGRESOS'!$B:$B,G$3) | H53: =SUMIFS('2. EGRESOS'!$E:$E,'2. EGRESOS'!$K:$K,$A53,'2. EGRESOS'!$B:$B,H$3) | I53: =SUMIFS('2. EGRESOS'!$E:$E,'2. EGRESOS'!$K:$K,$A53,'2. EGRESOS'!$B:$B,I$3) | J53: =SUMIFS('2. EGRESOS'!$E:$E,'2. EGRESOS'!$K:$K,$A53,'2. EGRESOS'!$B:$B,J$3) | ... Z53: =SUMIFS('2. EGRESOS'!$E:$E,'2. EGRESOS'!$K:$K,$A53,'2. EGRESOS'!$B:$B,Z$3)
A54: 1.8.2 | B54: Comision plataformas delivery | C54: =SUMIFS('2. EGRESOS'!$E:$E,'2. EGRESOS'!$K:$K,$A54,'2. EGRESOS'!$B:$B,C$3) | D54: =SUMIFS('2. EGRESOS'!$E:$E,'2. EGRESOS'!$K:$K,$A54,'2. EGRESOS'!$B:$B,D$3) | E54: =SUMIFS('2. EGRESOS'!$E:$E,'2. EGRESOS'!$K:$K,$A54,'2. EGRESOS'!$B:$B,E$3) | F54: =SUMIFS('2. EGRESOS'!$E:$E,'2. EGRESOS'!$K:$K,$A54,'2. EGRESOS'!$B:$B,F$3) | G54: =SUMIFS('2. EGRESOS'!$E:$E,'2. EGRESOS'!$K:$K,$A54,'2. EGRESOS'!$B:$B,G$3) | H54: =SUMIFS('2. EGRESOS'!$E:$E,'2. EGRESOS'!$K:$K,$A54,'2. EGRESOS'!$B:$B,H$3) | I54: =SUMIFS('2. EGRESOS'!$E:$E,'2. EGRESOS'!$K:$K,$A54,'2. EGRESOS'!$B:$B,I$3) | J54: =SUMIFS('2. EGRESOS'!$E:$E,'2. EGRESOS'!$K:$K,$A54,'2. EGRESOS'!$B:$B,J$3) | ... Z54: =SUMIFS('2. EGRESOS'!$E:$E,'2. EGRESOS'!$K:$K,$A54,'2. EGRESOS'!$B:$B,Z$3)
A55: 1.8.3 | B55: Plataformas Digitales (Comision) | C55: =SUMIFS('2. EGRESOS'!$E:$E,'2. EGRESOS'!$K:$K,$A55,'2. EGRESOS'!$B:$B,C$3) | D55: =SUMIFS('2. EGRESOS'!$E:$E,'2. EGRESOS'!$K:$K,$A55,'2. EGRESOS'!$B:$B,D$3) | E55: =SUMIFS('2. EGRESOS'!$E:$E,'2. EGRESOS'!$K:$K,$A55,'2. EGRESOS'!$B:$B,E$3) | F55: =SUMIFS('2. EGRESOS'!$E:$E,'2. EGRESOS'!$K:$K,$A55,'2. EGRESOS'!$B:$B,F$3) | G55: =SUMIFS('2. EGRESOS'!$E:$E,'2. EGRESOS'!$K:$K,$A55,'2. EGRESOS'!$B:$B,G$3) | H55: =SUMIFS('2. EGRESOS'!$E:$E,'2. EGRESOS'!$K:$K,$A55,'2. EGRESOS'!$B:$B,H$3) | I55: =SUMIFS('2. EGRESOS'!$E:$E,'2. EGRESOS'!$K:$K,$A55,'2. EGRESOS'!$B:$B,I$3) | J55: =SUMIFS('2. EGRESOS'!$E:$E,'2. EGRESOS'!$K:$K,$A55,'2. EGRESOS'!$B:$B,J$3) | ... Z55: =SUMIFS('2. EGRESOS'!$E:$E,'2. EGRESOS'!$K:$K,$A55,'2. EGRESOS'!$B:$B,Z$3)
A56: CC9 | B56: Impuestos | C56: =+SUBTOTAL(9,C57:C61) | D56: =+SUBTOTAL(9,D57:D61) | E56: =+SUBTOTAL(9,E57:E61) | F56: =+SUBTOTAL(9,F57:F61) | G56: =+SUBTOTAL(9,G57:G61) | H56: =+SUBTOTAL(9,H57:H61) | I56: =+SUBTOTAL(9,I57:I61) | J56: =+SUBTOTAL(9,J57:J61) | ... Z56: =+SUBTOTAL(9,Z57:Z61)
A57: 1.9.1 | B57: IVA Neto (F29) | C57: =SUMIFS('2. EGRESOS'!$E:$E,'2. EGRESOS'!$K:$K,$A57,'2. EGRESOS'!$B:$B,C$3) | D57: =SUMIFS('2. EGRESOS'!$E:$E,'2. EGRESOS'!$K:$K,$A57,'2. EGRESOS'!$B:$B,D$3) | E57: =SUMIFS('2. EGRESOS'!$E:$E,'2. EGRESOS'!$K:$K,$A57,'2. EGRESOS'!$B:$B,E$3) | F57: =SUMIFS('2. EGRESOS'!$E:$E,'2. EGRESOS'!$K:$K,$A57,'2. EGRESOS'!$B:$B,F$3) | G57: =SUMIFS('2. EGRESOS'!$E:$E,'2. EGRESOS'!$K:$K,$A57,'2. EGRESOS'!$B:$B,G$3) | H57: =SUMIFS('2. EGRESOS'!$E:$E,'2. EGRESOS'!$K:$K,$A57,'2. EGRESOS'!$B:$B,H$3) | I57: =SUMIFS('2. EGRESOS'!$E:$E,'2. EGRESOS'!$K:$K,$A57,'2. EGRESOS'!$B:$B,I$3) | J57: =SUMIFS('2. EGRESOS'!$E:$E,'2. EGRESOS'!$K:$K,$A57,'2. EGRESOS'!$B:$B,J$3) | ... Z57: =SUMIFS('2. EGRESOS'!$E:$E,'2. EGRESOS'!$K:$K,$A57,'2. EGRESOS'!$B:$B,Z$3)
A58: 1.9.2 | B58: Provision Impuesto a la Renta | C58: =SUMIFS('2. EGRESOS'!$E:$E,'2. EGRESOS'!$K:$K,$A58,'2. EGRESOS'!$B:$B,C$3) | D58: =SUMIFS('2. EGRESOS'!$E:$E,'2. EGRESOS'!$K:$K,$A58,'2. EGRESOS'!$B:$B,D$3) | E58: =SUMIFS('2. EGRESOS'!$E:$E,'2. EGRESOS'!$K:$K,$A58,'2. EGRESOS'!$B:$B,E$3) | F58: =SUMIFS('2. EGRESOS'!$E:$E,'2. EGRESOS'!$K:$K,$A58,'2. EGRESOS'!$B:$B,F$3) | G58: =SUMIFS('2. EGRESOS'!$E:$E,'2. EGRESOS'!$K:$K,$A58,'2. EGRESOS'!$B:$B,G$3) | H58: =SUMIFS('2. EGRESOS'!$E:$E,'2. EGRESOS'!$K:$K,$A58,'2. EGRESOS'!$B:$B,H$3) | I58: =SUMIFS('2. EGRESOS'!$E:$E,'2. EGRESOS'!$K:$K,$A58,'2. EGRESOS'!$B:$B,I$3) | J58: =SUMIFS('2. EGRESOS'!$E:$E,'2. EGRESOS'!$K:$K,$A58,'2. EGRESOS'!$B:$B,J$3) | ... Z58: =SUMIFS('2. EGRESOS'!$E:$E,'2. EGRESOS'!$K:$K,$A58,'2. EGRESOS'!$B:$B,Z$3)
A59: 1.9.3 | B59: Impuesto a la Renta | C59: =SUMIFS('2. EGRESOS'!$E:$E,'2. EGRESOS'!$K:$K,$A59,'2. EGRESOS'!$B:$B,C$3) | D59: =SUMIFS('2. EGRESOS'!$E:$E,'2. EGRESOS'!$K:$K,$A59,'2. EGRESOS'!$B:$B,D$3) | E59: =SUMIFS('2. EGRESOS'!$E:$E,'2. EGRESOS'!$K:$K,$A59,'2. EGRESOS'!$B:$B,E$3) | F59: =SUMIFS('2. EGRESOS'!$E:$E,'2. EGRESOS'!$K:$K,$A59,'2. EGRESOS'!$B:$B,F$3) | G59: =SUMIFS('2. EGRESOS'!$E:$E,'2. EGRESOS'!$K:$K,$A59,'2. EGRESOS'!$B:$B,G$3) | H59: =SUMIFS('2. EGRESOS'!$E:$E,'2. EGRESOS'!$K:$K,$A59,'2. EGRESOS'!$B:$B,H$3) | I59: =SUMIFS('2. EGRESOS'!$E:$E,'2. EGRESOS'!$K:$K,$A59,'2. EGRESOS'!$B:$B,I$3) | J59: =SUMIFS('2. EGRESOS'!$E:$E,'2. EGRESOS'!$K:$K,$A59,'2. EGRESOS'!$B:$B,J$3) | ... Z59: =SUMIFS('2. EGRESOS'!$E:$E,'2. EGRESOS'!$K:$K,$A59,'2. EGRESOS'!$B:$B,Z$3)
A60: 1.9.4 | B60: Patente Comercial | C60: =SUMIFS('2. EGRESOS'!$E:$E,'2. EGRESOS'!$K:$K,$A60,'2. EGRESOS'!$B:$B,C$3) | D60: =SUMIFS('2. EGRESOS'!$E:$E,'2. EGRESOS'!$K:$K,$A60,'2. EGRESOS'!$B:$B,D$3) | E60: =SUMIFS('2. EGRESOS'!$E:$E,'2. EGRESOS'!$K:$K,$A60,'2. EGRESOS'!$B:$B,E$3) | F60: =SUMIFS('2. EGRESOS'!$E:$E,'2. EGRESOS'!$K:$K,$A60,'2. EGRESOS'!$B:$B,F$3) | G60: =SUMIFS('2. EGRESOS'!$E:$E,'2. EGRESOS'!$K:$K,$A60,'2. EGRESOS'!$B:$B,G$3) | H60: =SUMIFS('2. EGRESOS'!$E:$E,'2. EGRESOS'!$K:$K,$A60,'2. EGRESOS'!$B:$B,H$3) | I60: =SUMIFS('2. EGRESOS'!$E:$E,'2. EGRESOS'!$K:$K,$A60,'2. EGRESOS'!$B:$B,I$3) | J60: =SUMIFS('2. EGRESOS'!$E:$E,'2. EGRESOS'!$K:$K,$A60,'2. EGRESOS'!$B:$B,J$3) | ... Z60: =SUMIFS('2. EGRESOS'!$E:$E,'2. EGRESOS'!$K:$K,$A60,'2. EGRESOS'!$B:$B,Z$3)
A61: 1.9.5 | B61: Gastos Bancarios | C61: =SUMIFS('2. EGRESOS'!$E:$E,'2. EGRESOS'!$K:$K,$A61,'2. EGRESOS'!$B:$B,C$3) | D61: =SUMIFS('2. EGRESOS'!$E:$E,'2. EGRESOS'!$K:$K,$A61,'2. EGRESOS'!$B:$B,D$3) | E61: =SUMIFS('2. EGRESOS'!$E:$E,'2. EGRESOS'!$K:$K,$A61,'2. EGRESOS'!$B:$B,E$3) | F61: =SUMIFS('2. EGRESOS'!$E:$E,'2. EGRESOS'!$K:$K,$A61,'2. EGRESOS'!$B:$B,F$3) | G61: =SUMIFS('2. EGRESOS'!$E:$E,'2. EGRESOS'!$K:$K,$A61,'2. EGRESOS'!$B:$B,G$3) | H61: =SUMIFS('2. EGRESOS'!$E:$E,'2. EGRESOS'!$K:$K,$A61,'2. EGRESOS'!$B:$B,H$3) | I61: =SUMIFS('2. EGRESOS'!$E:$E,'2. EGRESOS'!$K:$K,$A61,'2. EGRESOS'!$B:$B,I$3) | J61: =SUMIFS('2. EGRESOS'!$E:$E,'2. EGRESOS'!$K:$K,$A61,'2. EGRESOS'!$B:$B,J$3) | ... Z61: =SUMIFS('2. EGRESOS'!$E:$E,'2. EGRESOS'!$K:$K,$A61,'2. EGRESOS'!$B:$B,Z$3)
A62: TOTAL COSTOS | C62: =+SUBTOTAL(9,C14:C61) | D62: =+SUBTOTAL(9,D14:D61) | E62: =+SUBTOTAL(9,E14:E61) | F62: =+SUBTOTAL(9,F14:F61) | G62: =+SUBTOTAL(9,G14:G61) | H62: =+SUBTOTAL(9,H14:H61) | I62: =+SUBTOTAL(9,I14:I61) | J62: =+SUBTOTAL(9,J14:J61) | ... Z62: =+SUBTOTAL(9,Z14:Z61)
A64: MARGEN $ | C64: =C12-C62 | D64: =D12-D62 | E64: =E12-E62 | F64: =F12-F62 | G64: =G12-G62 | H64: =H12-H62 | I64: =I12-I62 | J64: =J12-J62 | ... Z64: =Z12-Z62
A65: MARGEN % | C65: =IF(C12=0,0,C64/C12) | D65: =IF(D12=0,0,D64/D12) | E65: =IF(E12=0,0,E64/E12) | F65: =IF(F12=0,0,F64/F12) | G65: =IF(G12=0,0,G64/G12) | H65: =IF(H12=0,0,H64/H12) | I65: =IF(I12=0,0,I64/I12) | J65: =IF(J12=0,0,J64/J12) | ... Z65: =IF(Z12=0,0,Z64/Z12)

Sheet KPIs
A1: KPIs — FAIT PAR MARIE | Valores Netos sin IVA | Base: Mes Devengo
A2: Indicador | B2: Ref. | C2: Unidad | D2: Benchmark | E2: 2025-01 | F2: 2025-02 | G2: 2025-03 | H2: 2025-04 | I2: 2025-05 | J2: 2025-06 | K2: 2025-07 | L2: 2025-08 | M2: 2025-09 | N2: 2025-10 | O2: 2025-11 | P2: 2025-12 | Q2: 2026-01 | R2: 2026-02 | S2: 2026-03 | T2: 2026-04 | U2: 2026-05 | V2: 2026-06 | W2: 2026-07 | X2: 2026-08 | Y2: 2026-09 | Z2: 2026-10 | AA2: 2026-11 | AB2: 2026-12 | AC2: Prom. mensual
A4: INGRESOS
A5: Venta Neta Total | C5: $ | E5: =SUMIFS('1. INGRESOS'!$H:$H,'1. INGRESOS'!$B:$B,E$2) | F5: =SUMIFS('1. INGRESOS'!$H:$H,'1. INGRESOS'!$B:$B,F$2) | G5: =SUMIFS('1. INGRESOS'!$H:$H,'1. INGRESOS'!$B:$B,G$2) | H5: =SUMIFS('1. INGRESOS'!$H:$H,'1. INGRESOS'!$B:$B,H$2) | I5: =SUMIFS('1. INGRESOS'!$H:$H,'1. INGRESOS'!$B:$B,I$2) | J5: =SUMIFS('1. INGRESOS'!$H:$H,'1. INGRESOS'!$B:$B,J$2) | K5: =SUMIFS('1. INGRESOS'!$H:$H,'1. INGRESOS'!$B:$B,K$2) | L5: =SUMIFS('1. INGRESOS'!$H:$H,'1. INGRESOS'!$B:$B,L$2) | ... AB5: =SUMIFS('1. INGRESOS'!$H:$H,'1. INGRESOS'!$B:$B,AB$2) | AC5: =IFERROR(AVERAGE(E5:U5),"")
A6: HoReCa | B6: =CANALES!$A$3 | C6: $ | E6: =SUMIFS('1. INGRESOS'!$H:$H,'1. INGRESOS'!$B:$B,E$2,'1. INGRESOS'!$K:$K,$B6) | F6: =SUMIFS('1. INGRESOS'!$H:$H,'1. INGRESOS'!$B:$B,F$2,'1. INGRESOS'!$K:$K,$B6) | G6: =SUMIFS('1. INGRESOS'!$H:$H,'1. INGRESOS'!$B:$B,G$2,'1. INGRESOS'!$K:$K,$B6) | H6: =SUMIFS('1. INGRESOS'!$H:$H,'1. INGRESOS'!$B:$B,H$2,'1. INGRESOS'!$K:$K,$B6) | I6: =SUMIFS('1. INGRESOS'!$H:$H,'1. INGRESOS'!$B:$B,I$2,'1. INGRESOS'!$K:$K,$B6) | J6: =SUMIFS('1. INGRESOS'!$H:$H,'1. INGRESOS'!$B:$B,J$2,'1. INGRESOS'!$K:$K,$B6) | K6: =SUMIFS('1. INGRESOS'!$H:$H,'1. INGRESOS'!$B:$B,K$2,'1. INGRESOS'!$K:$K,$B6) | L6: =SUMIFS('1. INGRESOS'!$H:$H,'1. INGRESOS'!$B:$B,L$2,'1. INGRESOS'!$K:$K,$B6) | ... AB6: =SUMIFS('1. INGRESOS'!$H:$H,'1. INGRESOS'!$B:$B,AB$2,'1. INGRESOS'!$K:$K,$B6) | AC6: =IFERROR(AVERAGE(E6:U6),"")
A7: B2C Boutique | B7: =CANALES!$A$4 | C7: $ | E7: =SUMIFS('1. INGRESOS'!$H:$H,'1. INGRESOS'!$B:$B,E$2,'1. INGRESOS'!$K:$K,$B7) | F7: =SUMIFS('1. INGRESOS'!$H:$H,'1. INGRESOS'!$B:$B,F$2,'1. INGRESOS'!$K:$K,$B7) | G7: =SUMIFS('1. INGRESOS'!$H:$H,'1. INGRESOS'!$B:$B,G$2,'1. INGRESOS'!$K:$K,$B7) | H7: =SUMIFS('1. INGRESOS'!$H:$H,'1. INGRESOS'!$B:$B,H$2,'1. INGRESOS'!$K:$K,$B7) | I7: =SUMIFS('1. INGRESOS'!$H:$H,'1. INGRESOS'!$B:$B,I$2,'1. INGRESOS'!$K:$K,$B7) | J7: =SUMIFS('1. INGRESOS'!$H:$H,'1. INGRESOS'!$B:$B,J$2,'1. INGRESOS'!$K:$K,$B7) | K7: =SUMIFS('1. INGRESOS'!$H:$H,'1. INGRESOS'!$B:$B,K$2,'1. INGRESOS'!$K:$K,$B7) | L7: =SUMIFS('1. INGRESOS'!$H:$H,'1. INGRESOS'!$B:$B,L$2,'1. INGRESOS'!$K:$K,$B7) | ... AB7: =SUMIFS('1. INGRESOS'!$H:$H,'1. INGRESOS'!$B:$B,AB$2,'1. INGRESOS'!$K:$K,$B7) | AC7: =IFERROR(AVERAGE(E7:U7),"")
A8: Delivery Apps | B8: =CANALES!$A$5 | C8: $ | E8: =SUMIFS('1. INGRESOS'!$H:$H,'1. INGRESOS'!$B:$B,E$2,'1. INGRESOS'!$K:$K,$B8) | F8: =SUMIFS('1. INGRESOS'!$H:$H,'1. INGRESOS'!$B:$B,F$2,'1. INGRESOS'!$K:$K,$B8) | G8: =SUMIFS('1. INGRESOS'!$H:$H,'1. INGRESOS'!$B:$B,G$2,'1. INGRESOS'!$K:$K,$B8) | H8: =SUMIFS('1. INGRESOS'!$H:$H,'1. INGRESOS'!$B:$B,H$2,'1. INGRESOS'!$K:$K,$B8) | I8: =SUMIFS('1. INGRESOS'!$H:$H,'1. INGRESOS'!$B:$B,I$2,'1. INGRESOS'!$K:$K,$B8) | J8: =SUMIFS('1. INGRESOS'!$H:$H,'1. INGRESOS'!$B:$B,J$2,'1. INGRESOS'!$K:$K,$B8) | K8: =SUMIFS('1. INGRESOS'!$H:$H,'1. INGRESOS'!$B:$B,K$2,'1. INGRESOS'!$K:$K,$B8) | L8: =SUMIFS('1. INGRESOS'!$H:$H,'1. INGRESOS'!$B:$B,L$2,'1. INGRESOS'!$K:$K,$B8) | ... AB8: =SUMIFS('1. INGRESOS'!$H:$H,'1. INGRESOS'!$B:$B,AB$2,'1. INGRESOS'!$K:$K,$B8) | AC8: =IFERROR(AVERAGE(E8:U8),"")
A9: Ferias | B9: =CANALES!$A$6 | C9: $ | E9: =SUMIFS('1. INGRESOS'!$H:$H,'1. INGRESOS'!$B:$B,E$2,'1. INGRESOS'!$K:$K,$B9) | F9: =SUMIFS('1. INGRESOS'!$H:$H,'1. INGRESOS'!$B:$B,F$2,'1. INGRESOS'!$K:$K,$B9) | G9: =SUMIFS('1. INGRESOS'!$H:$H,'1. INGRESOS'!$B:$B,G$2,'1. INGRESOS'!$K:$K,$B9) | H9: =SUMIFS('1. INGRESOS'!$H:$H,'1. INGRESOS'!$B:$B,H$2,'1. INGRESOS'!$K:$K,$B9) | I9: =SUMIFS('1. INGRESOS'!$H:$H,'1. INGRESOS'!$B:$B,I$2,'1. INGRESOS'!$K:$K,$B9) | J9: =SUMIFS('1. INGRESOS'!$H:$H,'1. INGRESOS'!$B:$B,J$2,'1. INGRESOS'!$K:$K,$B9) | K9: =SUMIFS('1. INGRESOS'!$H:$H,'1. INGRESOS'!$B:$B,K$2,'1. INGRESOS'!$K:$K,$B9) | L9: =SUMIFS('1. INGRESOS'!$H:$H,'1. INGRESOS'!$B:$B,L$2,'1. INGRESOS'!$K:$K,$B9) | ... AB9: =SUMIFS('1. INGRESOS'!$H:$H,'1. INGRESOS'!$B:$B,AB$2,'1. INGRESOS'!$K:$K,$B9) | AC9: =IFERROR(AVERAGE(E9:U9),"")
A10: MIX CANAL %
A11: % HoReCa | C11: % | E11: =IF(E$5=0,"",E$6/E$5) | F11: =IF(F$5=0,"",F$6/F$5) | G11: =IF(G$5=0,"",G$6/G$5) | H11: =IF(H$5=0,"",H$6/H$5) | I11: =IF(I$5=0,"",I$6/I$5) | J11: =IF(J$5=0,"",J$6/J$5) | K11: =IF(K$5=0,"",K$6/K$5) | L11: =IF(L$5=0,"",L$6/L$5) | ... AB11: =IF(AB$5=0,"",AB$6/AB$5) | AC11: =IFERROR(AVERAGE(E11:U11),"")
A12: % B2C | C12: % | E12: =IF(E$5=0,"",E$7/E$5) | F12: =IF(F$5=0,"",F$7/F$5) | G12: =IF(G$5=0,"",G$7/G$5) | H12: =IF(H$5=0,"",H$7/H$5) | I12: =IF(I$5=0,"",I$7/I$5) | J12: =IF(J$5=0,"",J$7/J$5) | K12: =IF(K$5=0,"",K$7/K$5) | L12: =IF(L$5=0,"",L$7/L$5) | ... AB12: =IF(AB$5=0,"",AB$7/AB$5) | AC12: =IFERROR(AVERAGE(E12:U12),"")
A13: % Delivery | C13: % | E13: =IF(E$5=0,"",E$8/E$5) | F13: =IF(F$5=0,"",F$8/F$5) | G13: =IF(G$5=0,"",G$8/G$5) | H13: =IF(H$5=0,"",H$8/H$5) | I13: =IF(I$5=0,"",I$8/I$5) | J13: =IF(J$5=0,"",J$8/J$5) | K13: =IF(K$5=0,"",K$8/K$5) | L13: =IF(L$5=0,"",L$8/L$5) | ... AB13: =IF(AB$5=0,"",AB$8/AB$5) | AC13: =IFERROR(AVERAGE(E13:U13),"")
A14: % Ferias | C14: % | E14: =IF(E$5=0,"",E$9/E$5) | F14: =IF(F$5=0,"",F$9/F$5) | G14: =IF(G$5=0,"",G$9/G$5) | H14: =IF(H$5=0,"",H$9/H$5) | I14: =IF(I$5=0,"",I$9/I$5) | J14: =IF(J$5=0,"",J$9/J$5) | K14: =IF(K$5=0,"",K$9/K$5) | L14: =IF(L$5=0,"",L$9/L$5) | ... AB14: =IF(AB$5=0,"",AB$9/AB$5) | AC14: =IFERROR(AVERAGE(E14:U14),"")
A15: VOLUMEN Y TICKETS
A16: N Transacciones Total | C16: # | E16: =COUNTIFS('1. INGRESOS'!$B:$B,E$2) | F16: =COUNTIFS('1. INGRESOS'!$B:$B,F$2) | G16: =COUNTIFS('1. INGRESOS'!$B:$B,G$2) | H16: =COUNTIFS('1. INGRESOS'!$B:$B,H$2) | I16: =COUNTIFS('1. INGRESOS'!$B:$B,I$2) | J16: =COUNTIFS('1. INGRESOS'!$B:$B,J$2) | K16: =COUNTIFS('1. INGRESOS'!$B:$B,K$2) | L16: =COUNTIFS('1. INGRESOS'!$B:$B,L$2) | ... AB16: =COUNTIFS('1. INGRESOS'!$B:$B,AB$2) | AC16: =IFERROR(AVERAGE(E16:U16),"")
A17: N Trans HoReCa | B17: =CANALES!$A$3 | C17: # | E17: =COUNTIFS('1. INGRESOS'!$B:$B,E$2,'1. INGRESOS'!$K:$K,$B17) | F17: =COUNTIFS('1. INGRESOS'!$B:$B,F$2,'1. INGRESOS'!$K:$K,$B17) | G17: =COUNTIFS('1. INGRESOS'!$B:$B,G$2,'1. INGRESOS'!$K:$K,$B17) | H17: =COUNTIFS('1. INGRESOS'!$B:$B,H$2,'1. INGRESOS'!$K:$K,$B17) | I17: =COUNTIFS('1. INGRESOS'!$B:$B,I$2,'1. INGRESOS'!$K:$K,$B17) | J17: =COUNTIFS('1. INGRESOS'!$B:$B,J$2,'1. INGRESOS'!$K:$K,$B17) | K17: =COUNTIFS('1. INGRESOS'!$B:$B,K$2,'1. INGRESOS'!$K:$K,$B17) | L17: =COUNTIFS('1. INGRESOS'!$B:$B,L$2,'1. INGRESOS'!$K:$K,$B17) | ... AB17: =COUNTIFS('1. INGRESOS'!$B:$B,AB$2,'1. INGRESOS'!$K:$K,$B17) | AC17: =IFERROR(AVERAGE(E17:U17),"")
A18: N Trans B2C | B18: =CANALES!$A$4 | C18: # | E18: =COUNTIFS('1. INGRESOS'!$B:$B,E$2,'1. INGRESOS'!$K:$K,$B18) | F18: =COUNTIFS('1. INGRESOS'!$B:$B,F$2,'1. INGRESOS'!$K:$K,$B18) | G18: =COUNTIFS('1. INGRESOS'!$B:$B,G$2,'1. INGRESOS'!$K:$K,$B18) | H18: =COUNTIFS('1. INGRESOS'!$B:$B,H$2,'1. INGRESOS'!$K:$K,$B18) | I18: =COUNTIFS('1. INGRESOS'!$B:$B,I$2,'1. INGRESOS'!$K:$K,$B18) | J18: =COUNTIFS('1. INGRESOS'!$B:$B,J$2,'1. INGRESOS'!$K:$K,$B18) | K18: =COUNTIFS('1. INGRESOS'!$B:$B,K$2,'1. INGRESOS'!$K:$K,$B18) | L18: =COUNTIFS('1. INGRESOS'!$B:$B,L$2,'1. INGRESOS'!$K:$K,$B18) | ... AB18: =COUNTIFS('1. INGRESOS'!$B:$B,AB$2,'1. INGRESOS'!$K:$K,$B18) | AC18: =IFERROR(AVERAGE(E18:U18),"")
A19: N Trans Delivery | B19: =CANALES!$A$5 | C19: # | E19: =COUNTIFS('1. INGRESOS'!$B:$B,E$2,'1. INGRESOS'!$K:$K,$B19) | F19: =COUNTIFS('1. INGRESOS'!$B:$B,F$2,'1. INGRESOS'!$K:$K,$B19) | G19: =COUNTIFS('1. INGRESOS'!$B:$B,G$2,'1. INGRESOS'!$K:$K,$B19) | H19: =COUNTIFS('1. INGRESOS'!$B:$B,H$2,'1. INGRESOS'!$K:$K,$B19) | I19: =COUNTIFS('1. INGRESOS'!$B:$B,I$2,'1. INGRESOS'!$K:$K,$B19) | J19: =COUNTIFS('1. INGRESOS'!$B:$B,J$2,'1. INGRESOS'!$K:$K,$B19) | K19: =COUNTIFS('1. INGRESOS'!$B:$B,K$2,'1. INGRESOS'!$K:$K,$B19) | L19: =COUNTIFS('1. INGRESOS'!$B:$B,L$2,'1. INGRESOS'!$K:$K,$B19) | ... AB19: =COUNTIFS('1. INGRESOS'!$B:$B,AB$2,'1. INGRESOS'!$K:$K,$B19) | AC19: =IFERROR(AVERAGE(E19:U19),"")
A20: Ticket Prom HoReCa | C20: $ | E20: =IF(E$17=0,"",E$6/E$17) | F20: =IF(F$17=0,"",F$6/F$17) | G20: =IF(G$17=0,"",G$6/G$17) | H20: =IF(H$17=0,"",H$6/H$17) | I20: =IF(I$17=0,"",I$6/I$17) | J20: =IF(J$17=0,"",J$6/J$17) | K20: =IF(K$17=0,"",K$6/K$17) | L20: =IF(L$17=0,"",L$6/L$17) | ... AB20: =IF(AB$17=0,"",AB$6/AB$17) | AC20: =IFERROR(AVERAGE(E20:U20),"")
A21: Ticket Prom B2C | C21: $ | E21: =IF(E$18=0,"",E$7/E$18) | F21: =IF(F$18=0,"",F$7/F$18) | G21: =IF(G$18=0,"",G$7/G$18) | H21: =IF(H$18=0,"",H$7/H$18) | I21: =IF(I$18=0,"",I$7/I$18) | J21: =IF(J$18=0,"",J$7/J$18) | K21: =IF(K$18=0,"",K$7/K$18) | L21: =IF(L$18=0,"",L$7/L$18) | ... AB21: =IF(AB$18=0,"",AB$7/AB$18) | AC21: =IFERROR(AVERAGE(E21:U21),"")
A22: Ticket Prom Delivery | C22: $ | E22: =IF(E$19=0,"",E$8/E$19) | F22: =IF(F$19=0,"",F$8/F$19) | G22: =IF(G$19=0,"",G$8/G$19) | H22: =IF(H$19=0,"",H$8/H$19) | I22: =IF(I$19=0,"",I$8/I$19) | J22: =IF(J$19=0,"",J$8/J$19) | K22: =IF(K$19=0,"",K$8/K$19) | L22: =IF(L$19=0,"",L$8/L$19) | ... AB22: =IF(AB$19=0,"",AB$8/AB$19) | AC22: =IFERROR(AVERAGE(E22:U22),"")
A23: Unidades Vendidas (items) | C23: # | E23: 2920 | F23: 3024 | G23: 5926 | H23: 4855 | I23: 3524 | J23: 1189 | K23: 2003 | L23: 995 | M23: 1294 | N23: 1863 | O23: 4321 | P23: 3353 | Q23: 1429 | R23: 1317 | S23: 1931 | T23: 2041 | U23: 1143 | AC23: 2537
A25: EGRESOS POR CENTRO DE COSTO
A26: Total Egresos | C26: $ | E26: =SUMIFS('2. EGRESOS'!$H:$H,'2. EGRESOS'!$B:$B,E$2) | F26: =SUMIFS('2. EGRESOS'!$H:$H,'2. EGRESOS'!$B:$B,F$2) | G26: =SUMIFS('2. EGRESOS'!$H:$H,'2. EGRESOS'!$B:$B,G$2) | H26: =SUMIFS('2. EGRESOS'!$H:$H,'2. EGRESOS'!$B:$B,H$2) | I26: =SUMIFS('2. EGRESOS'!$H:$H,'2. EGRESOS'!$B:$B,I$2) | J26: =SUMIFS('2. EGRESOS'!$H:$H,'2. EGRESOS'!$B:$B,J$2) | K26: =SUMIFS('2. EGRESOS'!$H:$H,'2. EGRESOS'!$B:$B,K$2) | L26: =SUMIFS('2. EGRESOS'!$H:$H,'2. EGRESOS'!$B:$B,L$2) | ... AB26: =SUMIFS('2. EGRESOS'!$H:$H,'2. EGRESOS'!$B:$B,AB$2) | AC26: =IFERROR(AVERAGE(E26:U26),"")
A27: CC1 Costos Producto | B27: =CCs!$A$2 | C27: $ | E27: =SUMIFS('2. EGRESOS'!$H:$H,'2. EGRESOS'!$B:$B,E$2,'2. EGRESOS'!$O:$O,$B27) | F27: =SUMIFS('2. EGRESOS'!$H:$H,'2. EGRESOS'!$B:$B,F$2,'2. EGRESOS'!$O:$O,$B27) | G27: =SUMIFS('2. EGRESOS'!$H:$H,'2. EGRESOS'!$B:$B,G$2,'2. EGRESOS'!$O:$O,$B27) | H27: =SUMIFS('2. EGRESOS'!$H:$H,'2. EGRESOS'!$B:$B,H$2,'2. EGRESOS'!$O:$O,$B27) | I27: =SUMIFS('2. EGRESOS'!$H:$H,'2. EGRESOS'!$B:$B,I$2,'2. EGRESOS'!$O:$O,$B27) | J27: =SUMIFS('2. EGRESOS'!$H:$H,'2. EGRESOS'!$B:$B,J$2,'2. EGRESOS'!$O:$O,$B27) | K27: =SUMIFS('2. EGRESOS'!$H:$H,'2. EGRESOS'!$B:$B,K$2,'2. EGRESOS'!$O:$O,$B27) | L27: =SUMIFS('2. EGRESOS'!$H:$H,'2. EGRESOS'!$B:$B,L$2,'2. EGRESOS'!$O:$O,$B27) | ... AB27: =SUMIFS('2. EGRESOS'!$H:$H,'2. EGRESOS'!$B:$B,AB$2,'2. EGRESOS'!$O:$O,$B27) | AC27: =IFERROR(AVERAGE(E27:U27),"")
A28: CC2 Sueldos y RRHH | B28: =CCs!$A$3 | C28: $ | E28: =SUMIFS('2. EGRESOS'!$H:$H,'2. EGRESOS'!$B:$B,E$2,'2. EGRESOS'!$O:$O,$B28) | F28: =SUMIFS('2. EGRESOS'!$H:$H,'2. EGRESOS'!$B:$B,F$2,'2. EGRESOS'!$O:$O,$B28) | G28: =SUMIFS('2. EGRESOS'!$H:$H,'2. EGRESOS'!$B:$B,G$2,'2. EGRESOS'!$O:$O,$B28) | H28: =SUMIFS('2. EGRESOS'!$H:$H,'2. EGRESOS'!$B:$B,H$2,'2. EGRESOS'!$O:$O,$B28) | I28: =SUMIFS('2. EGRESOS'!$H:$H,'2. EGRESOS'!$B:$B,I$2,'2. EGRESOS'!$O:$O,$B28) | J28: =SUMIFS('2. EGRESOS'!$H:$H,'2. EGRESOS'!$B:$B,J$2,'2. EGRESOS'!$O:$O,$B28) | K28: =SUMIFS('2. EGRESOS'!$H:$H,'2. EGRESOS'!$B:$B,K$2,'2. EGRESOS'!$O:$O,$B28) | L28: =SUMIFS('2. EGRESOS'!$H:$H,'2. EGRESOS'!$B:$B,L$2,'2. EGRESOS'!$O:$O,$B28) | ... AB28: =SUMIFS('2. EGRESOS'!$H:$H,'2. EGRESOS'!$B:$B,AB$2,'2. EGRESOS'!$O:$O,$B28) | AC28: =IFERROR(AVERAGE(E28:U28),"")
A29: CC3 Infraestructura | B29: =CCs!$A$4 | C29: $ | E29: =SUMIFS('2. EGRESOS'!$H:$H,'2. EGRESOS'!$B:$B,E$2,'2. EGRESOS'!$O:$O,$B29) | F29: =SUMIFS('2. EGRESOS'!$H:$H,'2. EGRESOS'!$B:$B,F$2,'2. EGRESOS'!$O:$O,$B29) | G29: =SUMIFS('2. EGRESOS'!$H:$H,'2. EGRESOS'!$B:$B,G$2,'2. EGRESOS'!$O:$O,$B29) | H29: =SUMIFS('2. EGRESOS'!$H:$H,'2. EGRESOS'!$B:$B,H$2,'2. EGRESOS'!$O:$O,$B29) | I29: =SUMIFS('2. EGRESOS'!$H:$H,'2. EGRESOS'!$B:$B,I$2,'2. EGRESOS'!$O:$O,$B29) | J29: =SUMIFS('2. EGRESOS'!$H:$H,'2. EGRESOS'!$B:$B,J$2,'2. EGRESOS'!$O:$O,$B29) | K29: =SUMIFS('2. EGRESOS'!$H:$H,'2. EGRESOS'!$B:$B,K$2,'2. EGRESOS'!$O:$O,$B29) | L29: =SUMIFS('2. EGRESOS'!$H:$H,'2. EGRESOS'!$B:$B,L$2,'2. EGRESOS'!$O:$O,$B29) | ... AB29: =SUMIFS('2. EGRESOS'!$H:$H,'2. EGRESOS'!$B:$B,AB$2,'2. EGRESOS'!$O:$O,$B29) | AC29: =IFERROR(AVERAGE(E29:U29),"")
A30: CC4 SaaS | B30: =CCs!$A$6 | C30: $ | E30: =SUMIFS('2. EGRESOS'!$H:$H,'2. EGRESOS'!$B:$B,E$2,'2. EGRESOS'!$O:$O,$B30) | F30: =SUMIFS('2. EGRESOS'!$H:$H,'2. EGRESOS'!$B:$B,F$2,'2. EGRESOS'!$O:$O,$B30) | G30: =SUMIFS('2. EGRESOS'!$H:$H,'2. EGRESOS'!$B:$B,G$2,'2. EGRESOS'!$O:$O,$B30) | H30: =SUMIFS('2. EGRESOS'!$H:$H,'2. EGRESOS'!$B:$B,H$2,'2. EGRESOS'!$O:$O,$B30) | I30: =SUMIFS('2. EGRESOS'!$H:$H,'2. EGRESOS'!$B:$B,I$2,'2. EGRESOS'!$O:$O,$B30) | J30: =SUMIFS('2. EGRESOS'!$H:$H,'2. EGRESOS'!$B:$B,J$2,'2. EGRESOS'!$O:$O,$B30) | K30: =SUMIFS('2. EGRESOS'!$H:$H,'2. EGRESOS'!$B:$B,K$2,'2. EGRESOS'!$O:$O,$B30) | L30: =SUMIFS('2. EGRESOS'!$H:$H,'2. EGRESOS'!$B:$B,L$2,'2. EGRESOS'!$O:$O,$B30) | ... AB30: =SUMIFS('2. EGRESOS'!$H:$H,'2. EGRESOS'!$B:$B,AB$2,'2. EGRESOS'!$O:$O,$B30) | AC30: =IFERROR(AVERAGE(E30:U30),"")
A31: CC5 Marketing | B31: =CCs!$A$7 | C31: $ | E31: =SUMIFS('2. EGRESOS'!$H:$H,'2. EGRESOS'!$B:$B,E$2,'2. EGRESOS'!$O:$O,$B31) | F31: =SUMIFS('2. EGRESOS'!$H:$H,'2. EGRESOS'!$B:$B,F$2,'2. EGRESOS'!$O:$O,$B31) | G31: =SUMIFS('2. EGRESOS'!$H:$H,'2. EGRESOS'!$B:$B,G$2,'2. EGRESOS'!$O:$O,$B31) | H31: =SUMIFS('2. EGRESOS'!$H:$H,'2. EGRESOS'!$B:$B,H$2,'2. EGRESOS'!$O:$O,$B31) | I31: =SUMIFS('2. EGRESOS'!$H:$H,'2. EGRESOS'!$B:$B,I$2,'2. EGRESOS'!$O:$O,$B31) | J31: =SUMIFS('2. EGRESOS'!$H:$H,'2. EGRESOS'!$B:$B,J$2,'2. EGRESOS'!$O:$O,$B31) | K31: =SUMIFS('2. EGRESOS'!$H:$H,'2. EGRESOS'!$B:$B,K$2,'2. EGRESOS'!$O:$O,$B31) | L31: =SUMIFS('2. EGRESOS'!$H:$H,'2. EGRESOS'!$B:$B,L$2,'2. EGRESOS'!$O:$O,$B31) | ... AB31: =SUMIFS('2. EGRESOS'!$H:$H,'2. EGRESOS'!$B:$B,AB$2,'2. EGRESOS'!$O:$O,$B31) | AC31: =IFERROR(AVERAGE(E31:U31),"")
A32: CC6 Logistica | B32: =CCs!$A$8 | C32: $ | E32: =SUMIFS('2. EGRESOS'!$H:$H,'2. EGRESOS'!$B:$B,E$2,'2. EGRESOS'!$O:$O,$B32) | F32: =SUMIFS('2. EGRESOS'!$H:$H,'2. EGRESOS'!$B:$B,F$2,'2. EGRESOS'!$O:$O,$B32) | G32: =SUMIFS('2. EGRESOS'!$H:$H,'2. EGRESOS'!$B:$B,G$2,'2. EGRESOS'!$O:$O,$B32) | H32: =SUMIFS('2. EGRESOS'!$H:$H,'2. EGRESOS'!$B:$B,H$2,'2. EGRESOS'!$O:$O,$B32) | I32: =SUMIFS('2. EGRESOS'!$H:$H,'2. EGRESOS'!$B:$B,I$2,'2. EGRESOS'!$O:$O,$B32) | J32: =SUMIFS('2. EGRESOS'!$H:$H,'2. EGRESOS'!$B:$B,J$2,'2. EGRESOS'!$O:$O,$B32) | K32: =SUMIFS('2. EGRESOS'!$H:$H,'2. EGRESOS'!$B:$B,K$2,'2. EGRESOS'!$O:$O,$B32) | L32: =SUMIFS('2. EGRESOS'!$H:$H,'2. EGRESOS'!$B:$B,L$2,'2. EGRESOS'!$O:$O,$B32) | ... AB32: =SUMIFS('2. EGRESOS'!$H:$H,'2. EGRESOS'!$B:$B,AB$2,'2. EGRESOS'!$O:$O,$B32) | AC32: =IFERROR(AVERAGE(E32:U32),"")
A33: CC7 Comisiones | B33: =CCs!$A$9 | C33: $ | E33: =SUMIFS('2. EGRESOS'!$H:$H,'2. EGRESOS'!$B:$B,E$2,'2. EGRESOS'!$O:$O,$B33) | F33: =SUMIFS('2. EGRESOS'!$H:$H,'2. EGRESOS'!$B:$B,F$2,'2. EGRESOS'!$O:$O,$B33) | G33: =SUMIFS('2. EGRESOS'!$H:$H,'2. EGRESOS'!$B:$B,G$2,'2. EGRESOS'!$O:$O,$B33) | H33: =SUMIFS('2. EGRESOS'!$H:$H,'2. EGRESOS'!$B:$B,H$2,'2. EGRESOS'!$O:$O,$B33) | I33: =SUMIFS('2. EGRESOS'!$H:$H,'2. EGRESOS'!$B:$B,I$2,'2. EGRESOS'!$O:$O,$B33) | J33: =SUMIFS('2. EGRESOS'!$H:$H,'2. EGRESOS'!$B:$B,J$2,'2. EGRESOS'!$O:$O,$B33) | K33: =SUMIFS('2. EGRESOS'!$H:$H,'2. EGRESOS'!$B:$B,K$2,'2. EGRESOS'!$O:$O,$B33) | L33: =SUMIFS('2. EGRESOS'!$H:$H,'2. EGRESOS'!$B:$B,L$2,'2. EGRESOS'!$O:$O,$B33) | ... AB33: =SUMIFS('2. EGRESOS'!$H:$H,'2. EGRESOS'!$B:$B,AB$2,'2. EGRESOS'!$O:$O,$B33) | AC33: =IFERROR(AVERAGE(E33:U33),"")
A34: CC8 Impuestos | B34: =CCs!$A$10 | C34: $ | E34: =SUMIFS('2. EGRESOS'!$H:$H,'2. EGRESOS'!$B:$B,E$2,'2. EGRESOS'!$O:$O,$B34) | F34: =SUMIFS('2. EGRESOS'!$H:$H,'2. EGRESOS'!$B:$B,F$2,'2. EGRESOS'!$O:$O,$B34) | G34: =SUMIFS('2. EGRESOS'!$H:$H,'2. EGRESOS'!$B:$B,G$2,'2. EGRESOS'!$O:$O,$B34) | H34: =SUMIFS('2. EGRESOS'!$H:$H,'2. EGRESOS'!$B:$B,H$2,'2. EGRESOS'!$O:$O,$B34) | I34: =SUMIFS('2. EGRESOS'!$H:$H,'2. EGRESOS'!$B:$B,I$2,'2. EGRESOS'!$O:$O,$B34) | J34: =SUMIFS('2. EGRESOS'!$H:$H,'2. EGRESOS'!$B:$B,J$2,'2. EGRESOS'!$O:$O,$B34) | K34: =SUMIFS('2. EGRESOS'!$H:$H,'2. EGRESOS'!$B:$B,K$2,'2. EGRESOS'!$O:$O,$B34) | L34: =SUMIFS('2. EGRESOS'!$H:$H,'2. EGRESOS'!$B:$B,L$2,'2. EGRESOS'!$O:$O,$B34) | ... AB34: =SUMIFS('2. EGRESOS'!$H:$H,'2. EGRESOS'!$B:$B,AB$2,'2. EGRESOS'!$O:$O,$B34) | AC34: =IFERROR(AVERAGE(E34:U34),"")
A35: % DE EGRESOS SOBRE VENTA NETA
A36: % CC1 / Venta | C36: % | D36: < 40% | E36: =IF(E$5=0,"",E27/E$5) | F36: =IF(F$5=0,"",F27/F$5) | G36: =IF(G$5=0,"",G27/G$5) | H36: =IF(H$5=0,"",H27/H$5) | I36: =IF(I$5=0,"",I27/I$5) | J36: =IF(J$5=0,"",J27/J$5) | K36: =IF(K$5=0,"",K27/K$5) | L36: =IF(L$5=0,"",L27/L$5) | ... AB36: =IF(AB$5=0,"",AB27/AB$5) | AC36: =IFERROR(AVERAGE(E36:U36),"")
A37: % CC2 / Venta | C37: % | D37: < 32% | E37: =IF(E$5=0,"",E28/E$5) | F37: =IF(F$5=0,"",F28/F$5) | G37: =IF(G$5=0,"",G28/G$5) | H37: =IF(H$5=0,"",H28/H$5) | I37: =IF(I$5=0,"",I28/I$5) | J37: =IF(J$5=0,"",J28/J$5) | K37: =IF(K$5=0,"",K28/K$5) | L37: =IF(L$5=0,"",L28/L$5) | ... AB37: =IF(AB$5=0,"",AB28/AB$5) | AC37: =IFERROR(AVERAGE(E37:U37),"")
A38: % CC3 / Venta | C38: % | D38: < 15% | E38: =IF(E$5=0,"",E29/E$5) | F38: =IF(F$5=0,"",F29/F$5) | G38: =IF(G$5=0,"",G29/G$5) | H38: =IF(H$5=0,"",H29/H$5) | I38: =IF(I$5=0,"",I29/I$5) | J38: =IF(J$5=0,"",J29/J$5) | K38: =IF(K$5=0,"",K29/K$5) | L38: =IF(L$5=0,"",L29/L$5) | ... AB38: =IF(AB$5=0,"",AB29/AB$5) | AC38: =IFERROR(AVERAGE(E38:U38),"")
A39: % CC4 / Venta | C39: % | E39: =IF(E$5=0,"",E30/E$5) | F39: =IF(F$5=0,"",F30/F$5) | G39: =IF(G$5=0,"",G30/G$5) | H39: =IF(H$5=0,"",H30/H$5) | I39: =IF(I$5=0,"",I30/I$5) | J39: =IF(J$5=0,"",J30/J$5) | K39: =IF(K$5=0,"",K30/K$5) | L39: =IF(L$5=0,"",L30/L$5) | ... AB39: =IF(AB$5=0,"",AB30/AB$5) | AC39: =IFERROR(AVERAGE(E39:U39),"")
A40: % CC5 / Venta | C40: % | D40: < 10% | E40: =IF(E$5=0,"",E31/E$5) | F40: =IF(F$5=0,"",F31/F$5) | G40: =IF(G$5=0,"",G31/G$5) | H40: =IF(H$5=0,"",H31/H$5) | I40: =IF(I$5=0,"",I31/I$5) | J40: =IF(J$5=0,"",J31/J$5) | K40: =IF(K$5=0,"",K31/K$5) | L40: =IF(L$5=0,"",L31/L$5) | ... AB40: =IF(AB$5=0,"",AB31/AB$5) | AC40: =IFERROR(AVERAGE(E40:U40),"")
A41: % CC6 / Venta | C41: % | E41: =IF(E$5=0,"",E32/E$5) | F41: =IF(F$5=0,"",F32/F$5) | G41: =IF(G$5=0,"",G32/G$5) | H41: =IF(H$5=0,"",H32/H$5) | I41: =IF(I$5=0,"",I32/I$5) | J41: =IF(J$5=0,"",J32/J$5) | K41: =IF(K$5=0,"",K32/K$5) | L41: =IF(L$5=0,"",L32/L$5) | ... AB41: =IF(AB$5=0,"",AB32/AB$5) | AC41: =IFERROR(AVERAGE(E41:U41),"")
A42: % CC7 / Venta | C42: % | E42: =IF(E$5=0,"",E33/E$5) | F42: =IF(F$5=0,"",F33/F$5) | G42: =IF(G$5=0,"",G33/G$5) | H42: =IF(H$5=0,"",H33/H$5) | I42: =IF(I$5=0,"",I33/I$5) | J42: =IF(J$5=0,"",J33/J$5) | K42: =IF(K$5=0,"",K33/K$5) | L42: =IF(L$5=0,"",L33/L$5) | ... AB42: =IF(AB$5=0,"",AB33/AB$5) | AC42: =IFERROR(AVERAGE(E42:U42),"")
A43: % CC8 / Venta | C43: % | E43: =IF(E$5=0,"",E34/E$5) | F43: =IF(F$5=0,"",F34/F$5) | G43: =IF(G$5=0,"",G34/G$5) | H43: =IF(H$5=0,"",H34/H$5) | I43: =IF(I$5=0,"",I34/I$5) | J43: =IF(J$5=0,"",J34/J$5) | K43: =IF(K$5=0,"",K34/K$5) | L43: =IF(L$5=0,"",L34/L$5) | ... AB43: =IF(AB$5=0,"",AB34/AB$5) | AC43: =IFERROR(AVERAGE(E43:U43),"")
A45: MARGENES Y RATIOS CLAVE
A46: Margen Bruto $ (Venta - CC1) | C46: $ | E46: =IF(E$5=0,"",E$5-E$27) | F46: =IF(F$5=0,"",F$5-F$27) | G46: =IF(G$5=0,"",G$5-G$27) | H46: =IF(H$5=0,"",H$5-H$27) | I46: =IF(I$5=0,"",I$5-I$27) | J46: =IF(J$5=0,"",J$5-J$27) | K46: =IF(K$5=0,"",K$5-K$27) | L46: =IF(L$5=0,"",L$5-L$27) | ... AB46: =IF(AB$5=0,"",AB$5-AB$27) | AC46: =IFERROR(AVERAGE(E46:U46),"")
A47: Margen Bruto % | C47: % | D47: > 55% | E47: =IF(E$5=0,"",E$46/E$5) | F47: =IF(F$5=0,"",F$46/F$5) | G47: =IF(G$5=0,"",G$46/G$5) | H47: =IF(H$5=0,"",H$46/H$5) | I47: =IF(I$5=0,"",I$46/I$5) | J47: =IF(J$5=0,"",J$46/J$5) | K47: =IF(K$5=0,"",K$46/K$5) | L47: =IF(L$5=0,"",L$46/L$5) | ... AB47: =IF(AB$5=0,"",AB$46/AB$5) | AC47: =IFERROR(AVERAGE(E47:U47),"")
A48: Food Cost % (ingredientes) | B48: =PLAN_CUENTAS!$A$2 | C48: % | D48: < 30% | E48: =IF(E$5=0,"",SUMIFS('2. EGRESOS'!$H:$H,'2. EGRESOS'!$B:$B,E$2,'2. EGRESOS'!$M:$M,$B48)/E$5) | F48: =IF(F$5=0,"",SUMIFS('2. EGRESOS'!$H:$H,'2. EGRESOS'!$B:$B,F$2,'2. EGRESOS'!$M:$M,$B48)/F$5) | G48: =IF(G$5=0,"",SUMIFS('2. EGRESOS'!$H:$H,'2. EGRESOS'!$B:$B,G$2,'2. EGRESOS'!$M:$M,$B48)/G$5) | H48: =IF(H$5=0,"",SUMIFS('2. EGRESOS'!$H:$H,'2. EGRESOS'!$B:$B,H$2,'2. EGRESOS'!$M:$M,$B48)/H$5) | I48: =IF(I$5=0,"",SUMIFS('2. EGRESOS'!$H:$H,'2. EGRESOS'!$B:$B,I$2,'2. EGRESOS'!$M:$M,$B48)/I$5) | J48: =IF(J$5=0,"",SUMIFS('2. EGRESOS'!$H:$H,'2. EGRESOS'!$B:$B,J$2,'2. EGRESOS'!$M:$M,$B48)/J$5) | K48: =IF(K$5=0,"",SUMIFS('2. EGRESOS'!$H:$H,'2. EGRESOS'!$B:$B,K$2,'2. EGRESOS'!$M:$M,$B48)/K$5) | L48: =IF(L$5=0,"",SUMIFS('2. EGRESOS'!$H:$H,'2. EGRESOS'!$B:$B,L$2,'2. EGRESOS'!$M:$M,$B48)/L$5) | ... AB48: =IF(AB$5=0,"",SUMIFS('2. EGRESOS'!$H:$H,'2. EGRESOS'!$B:$B,AB$2,'2. EGRESOS'!$M:$M,$B48)/AB$5) | AC48: =IFERROR(AVERAGE(E48:U48),"")
A49: Labor Cost % (CC2 sueldos) | C49: % | D49: < 32% | E49: =IF(E$5=0,"",E$28/E$5) | F49: =IF(F$5=0,"",F$28/F$5) | G49: =IF(G$5=0,"",G$28/G$5) | H49: =IF(H$5=0,"",H$28/H$5) | I49: =IF(I$5=0,"",I$28/I$5) | J49: =IF(J$5=0,"",J$28/J$5) | K49: =IF(K$5=0,"",K$28/K$5) | L49: =IF(L$5=0,"",L$28/L$5) | ... AB49: =IF(AB$5=0,"",AB$28/AB$5) | AC49: =IFERROR(AVERAGE(E49:U49),"")
A50: Prime Cost % (CC1 + CC2) | C50: % | D50: < 65% | E50: =IF(E$5=0,"",(E$27+E$28)/E$5) | F50: =IF(F$5=0,"",(F$27+F$28)/F$5) | G50: =IF(G$5=0,"",(G$27+G$28)/G$5) | H50: =IF(H$5=0,"",(H$27+H$28)/H$5) | I50: =IF(I$5=0,"",(I$27+I$28)/I$5) | J50: =IF(J$5=0,"",(J$27+J$28)/J$5) | K50: =IF(K$5=0,"",(K$27+K$28)/K$5) | L50: =IF(L$5=0,"",(L$27+L$28)/L$5) | ... AB50: =IF(AB$5=0,"",(AB$27+AB$28)/AB$5) | AC50: =IFERROR(AVERAGE(E50:U50),"")
A51: Rent % (arriendo 1.3.1) | B51: =PLAN_CUENTAS!$A$10 | C51: % | D51: < 8% | E51: =IF(E$5=0,"",SUMIFS('2. EGRESOS'!$H:$H,'2. EGRESOS'!$B:$B,E$2,'2. EGRESOS'!$M:$M,$B51)/E$5) | F51: =IF(F$5=0,"",SUMIFS('2. EGRESOS'!$H:$H,'2. EGRESOS'!$B:$B,F$2,'2. EGRESOS'!$M:$M,$B51)/F$5) | G51: =IF(G$5=0,"",SUMIFS('2. EGRESOS'!$H:$H,'2. EGRESOS'!$B:$B,G$2,'2. EGRESOS'!$M:$M,$B51)/G$5) | H51: =IF(H$5=0,"",SUMIFS('2. EGRESOS'!$H:$H,'2. EGRESOS'!$B:$B,H$2,'2. EGRESOS'!$M:$M,$B51)/H$5) | I51: =IF(I$5=0,"",SUMIFS('2. EGRESOS'!$H:$H,'2. EGRESOS'!$B:$B,I$2,'2. EGRESOS'!$M:$M,$B51)/I$5) | J51: =IF(J$5=0,"",SUMIFS('2. EGRESOS'!$H:$H,'2. EGRESOS'!$B:$B,J$2,'2. EGRESOS'!$M:$M,$B51)/J$5) | K51: =IF(K$5=0,"",SUMIFS('2. EGRESOS'!$H:$H,'2. EGRESOS'!$B:$B,K$2,'2. EGRESOS'!$M:$M,$B51)/K$5) | L51: =IF(L$5=0,"",SUMIFS('2. EGRESOS'!$H:$H,'2. EGRESOS'!$B:$B,L$2,'2. EGRESOS'!$M:$M,$B51)/L$5) | ... AB51: =IF(AB$5=0,"",SUMIFS('2. EGRESOS'!$H:$H,'2. EGRESOS'!$B:$B,AB$2,'2. EGRESOS'!$M:$M,$B51)/AB$5) | AC51: =IFERROR(AVERAGE(E51:U51),"")
A52: Marketing % (CC5) | C52: % | D52: < 10% | E52: =IF(E$5=0,"",E$31/E$5) | F52: =IF(F$5=0,"",F$31/F$5) | G52: =IF(G$5=0,"",G$31/G$5) | H52: =IF(H$5=0,"",H$31/H$5) | I52: =IF(I$5=0,"",I$31/I$5) | J52: =IF(J$5=0,"",J$31/J$5) | K52: =IF(K$5=0,"",K$31/K$5) | L52: =IF(L$5=0,"",L$31/L$5) | ... AB52: =IF(AB$5=0,"",AB$31/AB$5) | AC52: =IFERROR(AVERAGE(E52:U52),"")
A53: Comisiones % (CC7) | C53: % | E53: =IF(E$5=0,"",E$33/E$5) | F53: =IF(F$5=0,"",F$33/F$5) | G53: =IF(G$5=0,"",G$33/G$5) | H53: =IF(H$5=0,"",H$33/H$5) | I53: =IF(I$5=0,"",I$33/I$5) | J53: =IF(J$5=0,"",J$33/J$5) | K53: =IF(K$5=0,"",K$33/K$5) | L53: =IF(L$5=0,"",L$33/L$5) | ... AB53: =IF(AB$5=0,"",AB$33/AB$5) | AC53: =IFERROR(AVERAGE(E53:U53),"")
A54: EBIT $ (Venta - Total Egresos) | C54: $ | E54: =IF(E$5=0,"",E$5-E$26) | F54: =IF(F$5=0,"",F$5-F$26) | G54: =IF(G$5=0,"",G$5-G$26) | H54: =IF(H$5=0,"",H$5-H$26) | I54: =IF(I$5=0,"",I$5-I$26) | J54: =IF(J$5=0,"",J$5-J$26) | K54: =IF(K$5=0,"",K$5-K$26) | L54: =IF(L$5=0,"",L$5-L$26) | ... AB54: =IF(AB$5=0,"",AB$5-AB$26) | AC54: =IFERROR(AVERAGE(E54:U54),"")
A55: EBIT % | C55: % | D55: > 10% | E55: =IF(E$5=0,"",E$54/E$5) | F55: =IF(F$5=0,"",F$54/F$5) | G55: =IF(G$5=0,"",G$54/G$5) | H55: =IF(H$5=0,"",H$54/H$5) | I55: =IF(I$5=0,"",I$54/I$5) | J55: =IF(J$5=0,"",J$54/J$5) | K55: =IF(K$5=0,"",K$54/K$5) | L55: =IF(L$5=0,"",L$54/L$5) | ... AB55: =IF(AB$5=0,"",AB$54/AB$5) | AC55: =IFERROR(AVERAGE(E55:U55),"")
A57: P&L POR CANAL | costos directos proporcionales; overhead sin asignar
A58: HoReCa (CH1)
A59: Ingreso Neto HoReCa | C59: $ | E59: =E$6 | F59: =F$6 | G59: =G$6 | H59: =H$6 | I59: =I$6 | J59: =J$6 | K59: =K$6 | L59: =L$6 | ... AB59: =AB$6 | AC59: =IFERROR(AVERAGE(E59:U59),"")
A60: - Food Cost proporcional | C60: $ | E60: =IF(E$5=0,"",-E$27*(E$6/E$5)) | F60: =IF(F$5=0,"",-F$27*(F$6/F$5)) | G60: =IF(G$5=0,"",-G$27*(G$6/G$5)) | H60: =IF(H$5=0,"",-H$27*(H$6/H$5)) | I60: =IF(I$5=0,"",-I$27*(I$6/I$5)) | J60: =IF(J$5=0,"",-J$27*(J$6/J$5)) | K60: =IF(K$5=0,"",-K$27*(K$6/K$5)) | L60: =IF(L$5=0,"",-L$27*(L$6/L$5)) | ... AB60: =IF(AB$5=0,"",-AB$27*(AB$6/AB$5)) | AC60: =IFERROR(AVERAGE(E60:U60),"")
A61: - Comision Getnet (prop. HoReCa) | B61: =PLAN_CUENTAS!$A$34 | C61: $ | E61: =IF((E$6+E$7)=0,"",-SUMIFS('2. EGRESOS'!$H:$H,'2. EGRESOS'!$B:$B,E$2,'2. EGRESOS'!$M:$M,$B61)*(E$6/(E$6+E$7))) | F61: =IF((F$6+F$7)=0,"",-SUMIFS('2. EGRESOS'!$H:$H,'2. EGRESOS'!$B:$B,F$2,'2. EGRESOS'!$M:$M,$B61)*(F$6/(F$6+F$7))) | G61: =IF((G$6+G$7)=0,"",-SUMIFS('2. EGRESOS'!$H:$H,'2. EGRESOS'!$B:$B,G$2,'2. EGRESOS'!$M:$M,$B61)*(G$6/(G$6+G$7))) | H61: =IF((H$6+H$7)=0,"",-SUMIFS('2. EGRESOS'!$H:$H,'2. EGRESOS'!$B:$B,H$2,'2. EGRESOS'!$M:$M,$B61)*(H$6/(H$6+H$7))) | I61: =IF((I$6+I$7)=0,"",-SUMIFS('2. EGRESOS'!$H:$H,'2. EGRESOS'!$B:$B,I$2,'2. EGRESOS'!$M:$M,$B61)*(I$6/(I$6+I$7))) | J61: =IF((J$6+J$7)=0,"",-SUMIFS('2. EGRESOS'!$H:$H,'2. EGRESOS'!$B:$B,J$2,'2. EGRESOS'!$M:$M,$B61)*(J$6/(J$6+J$7))) | K61: =IF((K$6+K$7)=0,"",-SUMIFS('2. EGRESOS'!$H:$H,'2. EGRESOS'!$B:$B,K$2,'2. EGRESOS'!$M:$M,$B61)*(K$6/(K$6+K$7))) | L61: =IF((L$6+L$7)=0,"",-SUMIFS('2. EGRESOS'!$H:$H,'2. EGRESOS'!$B:$B,L$2,'2. EGRESOS'!$M:$M,$B61)*(L$6/(L$6+L$7))) | ... AB61: =IF((AB$6+AB$7)=0,"",-SUMIFS('2. EGRESOS'!$H:$H,'2. EGRESOS'!$B:$B,AB$2,'2. EGRESOS'!$M:$M,$B61)*(AB$6/(AB$6+AB$7))) | AC61: =IFERROR(AVERAGE(E61:U61),"")
A62: - Logistica proporcional (CC6) | C62: $ | E62: =IF(E$5=0,"",-E$32*(E$6/E$5)) | F62: =IF(F$5=0,"",-F$32*(F$6/F$5)) | G62: =IF(G$5=0,"",-G$32*(G$6/G$5)) | H62: =IF(H$5=0,"",-H$32*(H$6/H$5)) | I62: =IF(I$5=0,"",-I$32*(I$6/I$5)) | J62: =IF(J$5=0,"",-J$32*(J$6/J$5)) | K62: =IF(K$5=0,"",-K$32*(K$6/K$5)) | L62: =IF(L$5=0,"",-L$32*(L$6/L$5)) | ... AB62: =IF(AB$5=0,"",-AB$32*(AB$6/AB$5)) | AC62: =IFERROR(AVERAGE(E62:U62),"")
A63: = Contribucion HoReCa $ | C63: $ | E63: =IFERROR(E$59+E$60+E$61+E$62,"") | F63: =IFERROR(F$59+F$60+F$61+F$62,"") | G63: =IFERROR(G$59+G$60+G$61+G$62,"") | H63: =IFERROR(H$59+H$60+H$61+H$62,"") | I63: =IFERROR(I$59+I$60+I$61+I$62,"") | J63: =IFERROR(J$59+J$60+J$61+J$62,"") | K63: =IFERROR(K$59+K$60+K$61+K$62,"") | L63: =IFERROR(L$59+L$60+L$61+L$62,"") | ... AB63: =IFERROR(AB$59+AB$60+AB$61+AB$62,"") | AC63: =IFERROR(AVERAGE(E63:U63),"")
A64: Contribucion HoReCa % | C64: % | E64: =IF(E$59=0,"",E$63/E$59) | F64: =IF(F$59=0,"",F$63/F$59) | G64: =IF(G$59=0,"",G$63/G$59) | H64: =IF(H$59=0,"",H$63/H$59) | I64: =IF(I$59=0,"",I$63/I$59) | J64: =IF(J$59=0,"",J$63/J$59) | K64: =IF(K$59=0,"",K$63/K$59) | L64: =IF(L$59=0,"",L$63/L$59) | ... AB64: =IF(AB$59=0,"",AB$63/AB$59) | AC64: =IFERROR(AVERAGE(E64:U64),"")
A66: B2C Boutique (CH2)
A67: Ingreso Neto B2C | C67: $ | E67: =E$7 | F67: =F$7 | G67: =G$7 | H67: =H$7 | I67: =I$7 | J67: =J$7 | K67: =K$7 | L67: =L$7 | ... AB67: =AB$7 | AC67: =IFERROR(AVERAGE(E67:U67),"")
A68: - Food Cost proporcional | C68: $ | E68: =IF(E$5=0,"",-E$27*(E$7/E$5)) | F68: =IF(F$5=0,"",-F$27*(F$7/F$5)) | G68: =IF(G$5=0,"",-G$27*(G$7/G$5)) | H68: =IF(H$5=0,"",-H$27*(H$7/H$5)) | I68: =IF(I$5=0,"",-I$27*(I$7/I$5)) | J68: =IF(J$5=0,"",-J$27*(J$7/J$5)) | K68: =IF(K$5=0,"",-K$27*(K$7/K$5)) | L68: =IF(L$5=0,"",-L$27*(L$7/L$5)) | ... AB68: =IF(AB$5=0,"",-AB$27*(AB$7/AB$5)) | AC68: =IFERROR(AVERAGE(E68:U68),"")
A69: - Comision Getnet (prop. B2C) | B69: =PLAN_CUENTAS!$A$34 | C69: $ | E69: =IF((E$6+E$7)=0,"",-SUMIFS('2. EGRESOS'!$H:$H,'2. EGRESOS'!$B:$B,E$2,'2. EGRESOS'!$M:$M,$B69)*(E$7/(E$6+E$7))) | F69: =IF((F$6+F$7)=0,"",-SUMIFS('2. EGRESOS'!$H:$H,'2. EGRESOS'!$B:$B,F$2,'2. EGRESOS'!$M:$M,$B69)*(F$7/(F$6+F$7))) | G69: =IF((G$6+G$7)=0,"",-SUMIFS('2. EGRESOS'!$H:$H,'2. EGRESOS'!$B:$B,G$2,'2. EGRESOS'!$M:$M,$B69)*(G$7/(G$6+G$7))) | H69: =IF((H$6+H$7)=0,"",-SUMIFS('2. EGRESOS'!$H:$H,'2. EGRESOS'!$B:$B,H$2,'2. EGRESOS'!$M:$M,$B69)*(H$7/(H$6+H$7))) | I69: =IF((I$6+I$7)=0,"",-SUMIFS('2. EGRESOS'!$H:$H,'2. EGRESOS'!$B:$B,I$2,'2. EGRESOS'!$M:$M,$B69)*(I$7/(I$6+I$7))) | J69: =IF((J$6+J$7)=0,"",-SUMIFS('2. EGRESOS'!$H:$H,'2. EGRESOS'!$B:$B,J$2,'2. EGRESOS'!$M:$M,$B69)*(J$7/(J$6+J$7))) | K69: =IF((K$6+K$7)=0,"",-SUMIFS('2. EGRESOS'!$H:$H,'2. EGRESOS'!$B:$B,K$2,'2. EGRESOS'!$M:$M,$B69)*(K$7/(K$6+K$7))) | L69: =IF((L$6+L$7)=0,"",-SUMIFS('2. EGRESOS'!$H:$H,'2. EGRESOS'!$B:$B,L$2,'2. EGRESOS'!$M:$M,$B69)*(L$7/(L$6+L$7))) | ... AB69: =IF((AB$6+AB$7)=0,"",-SUMIFS('2. EGRESOS'!$H:$H,'2. EGRESOS'!$B:$B,AB$2,'2. EGRESOS'!$M:$M,$B69)*(AB$7/(AB$6+AB$7))) | AC69: =IFERROR(AVERAGE(E69:U69),"")
A70: = Contribucion B2C $ | C70: $ | E70: =IFERROR(E$67+E$68+E$69,"") | F70: =IFERROR(F$67+F$68+F$69,"") | G70: =IFERROR(G$67+G$68+G$69,"") | H70: =IFERROR(H$67+H$68+H$69,"") | I70: =IFERROR(I$67+I$68+I$69,"") | J70: =IFERROR(J$67+J$68+J$69,"") | K70: =IFERROR(K$67+K$68+K$69,"") | L70: =IFERROR(L$67+L$68+L$69,"") | ... AB70: =IFERROR(AB$67+AB$68+AB$69,"") | AC70: =IFERROR(AVERAGE(E70:U70),"")
A71: Contribucion B2C % | C71: % | E71: =IF(E$67=0,"",E$70/E$67) | F71: =IF(F$67=0,"",F$70/F$67) | G71: =IF(G$67=0,"",G$70/G$67) | H71: =IF(H$67=0,"",H$70/H$67) | I71: =IF(I$67=0,"",I$70/I$67) | J71: =IF(J$67=0,"",J$70/J$67) | K71: =IF(K$67=0,"",K$70/K$67) | L71: =IF(L$67=0,"",L$70/L$67) | ... AB71: =IF(AB$67=0,"",AB$70/AB$67) | AC71: =IFERROR(AVERAGE(E71:U71),"")
A73: Delivery Apps — Rappi / Uber Eats / GoodMeal (CH3)
A74: Ingreso Neto Delivery | C74: $ | E74: =E$8 | F74: =F$8 | G74: =G$8 | H74: =H$8 | I74: =I$8 | J74: =J$8 | K74: =K$8 | L74: =L$8 | ... AB74: =AB$8 | AC74: =IFERROR(AVERAGE(E74:U74),"")
A75: - Food Cost proporcional | C75: $ | E75: =IF(E$5=0,"",-E$27*(E$8/E$5)) | F75: =IF(F$5=0,"",-F$27*(F$8/F$5)) | G75: =IF(G$5=0,"",-G$27*(G$8/G$5)) | H75: =IF(H$5=0,"",-H$27*(H$8/H$5)) | I75: =IF(I$5=0,"",-I$27*(I$8/I$5)) | J75: =IF(J$5=0,"",-J$27*(J$8/J$5)) | K75: =IF(K$5=0,"",-K$27*(K$8/K$5)) | L75: =IF(L$5=0,"",-L$27*(L$8/L$5)) | ... AB75: =IF(AB$5=0,"",-AB$27*(AB$8/AB$5)) | AC75: =IFERROR(AVERAGE(E75:U75),"")
A76: - Comision Plataformas (1.8.2+1.8.3+1.8.4) | B76: =PLAN_CUENTAS!$A$35 | C76: $ | E76: =IF(E$74=0,"",-(SUMIFS('2. EGRESOS'!$H:$H,'2. EGRESOS'!$B:$B,E$2,'2. EGRESOS'!$M:$M,$B76)+SUMIFS('2. EGRESOS'!$H:$H,'2. EGRESOS'!$B:$B,E$2,'2. EGRESOS'!$M:$M,PLAN_CUENTAS!$A$36)+SUMIFS('2. EGRESOS'!$H:$H,'2. EGRESOS'!$B:$B,E$2,'2. EGRESOS'!$M:$M,PLAN_CUENTAS!$A$37))) | F76: =IF(F$74=0,"",-(SUMIFS('2. EGRESOS'!$H:$H,'2. EGRESOS'!$B:$B,F$2,'2. EGRESOS'!$M:$M,$B76)+SUMIFS('2. EGRESOS'!$H:$H,'2. EGRESOS'!$B:$B,F$2,'2. EGRESOS'!$M:$M,PLAN_CUENTAS!$A$36)+SUMIFS('2. EGRESOS'!$H:$H,'2. EGRESOS'!$B:$B,F$2,'2. EGRESOS'!$M:$M,PLAN_CUENTAS!$A$37))) | G76: =IF(G$74=0,"",-(SUMIFS('2. EGRESOS'!$H:$H,'2. EGRESOS'!$B:$B,G$2,'2. EGRESOS'!$M:$M,$B76)+SUMIFS('2. EGRESOS'!$H:$H,'2. EGRESOS'!$B:$B,G$2,'2. EGRESOS'!$M:$M,PLAN_CUENTAS!$A$36)+SUMIFS('2. EGRESOS'!$H:$H,'2. EGRESOS'!$B:$B,G$2,'2. EGRESOS'!$M:$M,PLAN_CUENTAS!$A$37))) | H76: =IF(H$74=0,"",-(SUMIFS('2. EGRESOS'!$H:$H,'2. EGRESOS'!$B:$B,H$2,'2. EGRESOS'!$M:$M,$B76)+SUMIFS('2. EGRESOS'!$H:$H,'2. EGRESOS'!$B:$B,H$2,'2. EGRESOS'!$M:$M,PLAN_CUENTAS!$A$36)+SUMIFS('2. EGRESOS'!$H:$H,'2. EGRESOS'!$B:$B,H$2,'2. EGRESOS'!$M:$M,PLAN_CUENTAS!$A$37))) | I76: =IF(I$74=0,"",-(SUMIFS('2. EGRESOS'!$H:$H,'2. EGRESOS'!$B:$B,I$2,'2. EGRESOS'!$M:$M,$B76)+SUMIFS('2. EGRESOS'!$H:$H,'2. EGRESOS'!$B:$B,I$2,'2. EGRESOS'!$M:$M,PLAN_CUENTAS!$A$36)+SUMIFS('2. EGRESOS'!$H:$H,'2. EGRESOS'!$B:$B,I$2,'2. EGRESOS'!$M:$M,PLAN_CUENTAS!$A$37))) | J76: =IF(J$74=0,"",-(SUMIFS('2. EGRESOS'!$H:$H,'2. EGRESOS'!$B:$B,J$2,'2. EGRESOS'!$M:$M,$B76)+SUMIFS('2. EGRESOS'!$H:$H,'2. EGRESOS'!$B:$B,J$2,'2. EGRESOS'!$M:$M,PLAN_CUENTAS!$A$36)+SUMIFS('2. EGRESOS'!$H:$H,'2. EGRESOS'!$B:$B,J$2,'2. EGRESOS'!$M:$M,PLAN_CUENTAS!$A$37))) | K76: =IF(K$74=0,"",-(SUMIFS('2. EGRESOS'!$H:$H,'2. EGRESOS'!$B:$B,K$2,'2. EGRESOS'!$M:$M,$B76)+SUMIFS('2. EGRESOS'!$H:$H,'2. EGRESOS'!$B:$B,K$2,'2. EGRESOS'!$M:$M,PLAN_CUENTAS!$A$36)+SUMIFS('2. EGRESOS'!$H:$H,'2. EGRESOS'!$B:$B,K$2,'2. EGRESOS'!$M:$M,PLAN_CUENTAS!$A$37))) | L76: =IF(L$74=0,"",-(SUMIFS('2. EGRESOS'!$H:$H,'2. EGRESOS'!$B:$B,L$2,'2. EGRESOS'!$M:$M,$B76)+SUMIFS('2. EGRESOS'!$H:$H,'2. EGRESOS'!$B:$B,L$2,'2. EGRESOS'!$M:$M,PLAN_CUENTAS!$A$36)+SUMIFS('2. EGRESOS'!$H:$H,'2. EGRESOS'!$B:$B,L$2,'2. EGRESOS'!$M:$M,PLAN_CUENTAS!$A$37))) | ... AB76: =IF(AB$74=0,"",-(SUMIFS('2. EGRESOS'!$H:$H,'2. EGRESOS'!$B:$B,AB$2,'2. EGRESOS'!$M:$M,$B76)+SUMIFS('2. EGRESOS'!$H:$H,'2. EGRESOS'!$B:$B,AB$2,'2. EGRESOS'!$M:$M,PLAN_CUENTAS!$A$36)+SUMIFS('2. EGRESOS'!$H:$H,'2. EGRESOS'!$B:$B,AB$2,'2. EGRESOS'!$M:$M,PLAN_CUENTAS!$A$37))) | AC76: =IFERROR(AVERAGE(E76:U76),"")
A77: = Contribucion Delivery $ | C77: $ | E77: =IFERROR(E$74+E$75+E$76,"") | F77: =IFERROR(F$74+F$75+F$76,"") | G77: =IFERROR(G$74+G$75+G$76,"") | H77: =IFERROR(H$74+H$75+H$76,"") | I77: =IFERROR(I$74+I$75+I$76,"") | J77: =IFERROR(J$74+J$75+J$76,"") | K77: =IFERROR(K$74+K$75+K$76,"") | L77: =IFERROR(L$74+L$75+L$76,"") | ... AB77: =IFERROR(AB$74+AB$75+AB$76,"") | AC77: =IFERROR(AVERAGE(E77:U77),"")
A78: Contribucion Delivery % | C78: % | E78: =IF(E$74=0,"",E$77/E$74) | F78: =IF(F$74=0,"",F$77/F$74) | G78: =IF(G$74=0,"",G$77/G$74) | H78: =IF(H$74=0,"",H$77/H$74) | I78: =IF(I$74=0,"",I$77/I$74) | J78: =IF(J$74=0,"",J$77/J$74) | K78: =IF(K$74=0,"",K$77/K$74) | L78: =IF(L$74=0,"",L$77/L$74) | ... AB78: =IF(AB$74=0,"",AB$77/AB$74) | AC78: =IFERROR(AVERAGE(E78:U78),"")

Sheet PLAN_CUENTAS
A1: Codigo | B1: Nombre | C1: CC | D1: Notas | F1: Meses
A2: 1.1.1 | B2: Ingredientes | C2: CC1
A3: 1.1.2 | B3: Packaging | C3: CC1
A4: 1.1.3 | B4: Equipamiento de Cocina | C4: CC1
A5: 1.2.1 | B5: Sueldos con Contrato | C5: CC2
A6: 1.2.2 | B6: Honorarios | C6: CC2
A7: 1.2.3 | B7: Asesoria Contable | C7: CC2
A8: 1.2.4 | B8: Uniformes Personal | C8: CC2
A9: 1.2.5 | B9: Prestamos Personal | C9: CC2
A10: 1.3.1 | B10: Arriendo Local | C10: CC3
A11: 1.3.2 | B11: Agua | C11: CC3
A12: 1.3.3 | B12: Luz | C12: CC3
A13: 1.3.4 | B13: Gas | C13: CC3
... A40: 1.9.5 | B40: Gastos Bancarios | C40: CC9
A41: 2.1 | B41: Ventas HoReCa
A42: 2.2 | B42: Ventas Personas (B2C)
A43: 2.3 | B43: Ventas Carrito
A44: 2.4 | B44: Ventas Ferias
A45: 2.5 | B45: Ventas Delivery Apps
A46: 2.6 | B46: Otros Ingresos
A47: 2.7 | B47: Descuentos y devoluciones

Sheet CCs
A1: Codigo | B1: Nombre | C1: Responsable | D1: Descripcion
A2: CC1 | B2: Costos de Producto | C2: Maria de los Angeles / Caro | D2: Ingredientes, packaging, materiales cocina
A3: CC2 | B3: Sueldos y RRHH | C3: Catherine / Maria Jose | D3: Toda la nomina, honorarios, asesoria contable
A4: CC3 | B4: Infraestructura | C4: Maria Jose | D4: Arriendo, consumos, telecomunicaciones, aseo
A5: CC4 | B5: Carrito | C5: Maria Jose
A6: CC5 | B6: SAAS | C6: Catalina / Maria Jose | D6: Software y tecnologia operativa
A7: CC6 | B7: Marketing y Publicidad | C7: Catalina | D7: Pauta, contenido, ferias
A8: CC7 | B8: Envios y Logistica | C8: Gaspar / Operaciones | D8: Envios externos, propios, plataforma delivery
A9: CC8 | B9: Comisiones de Venta | C9: Maria Jose | D9: Comisiones plataformas
A10: CC9 | B10: Impuestos y Tributos | C10: Maria Jose / Contador | D10: F29 IVA+PPM, renta, patentes

Sheet CANALES
A1: Codigo | B1: Nombre | C1: Descripcion | D1: Cuenta
A2: CH0 | B2: Sin Asignar | C2: Prorrateo al cierre de mes segun porcentaje ventas por canal
A3: CH1 | B3: HoReCa | C3: Restaurantes, cafeterias, banqueterias, regalos corporativos | D3: 3.1
A4: CH2 | B4: B2C Personas | C4: Venta local boutique Vitacura | D4: 3.2
A5: CH3 | B5: Delivery Apps | C5: Uber Eats + Rappi | D5: 3.6
A6: CH5 | B6: Ferias | C6: Eventos puntuales | D6: 3.5
A7: CH6 | B7: Carrito | C7: Parque Arauco y otros carritos | D7: 3.3
A8: CH7 | B8: Otros | C8: Ingresos no clasificados en otro canal | D8: 3.7

Sheet PROVEEDORES
A1: Proveedor | B1: Cuenta | C1: CC | D1: Canal | E1: Notas | G1: Agregar nuevos proveedores aqui. El REGISTRO los detecta automaticamente. | H1: RUT
A2: ADKAR SHOP CHILE SPA | H2: 76.876.593-6
A3: ADMIN. DE SUPERMERCADOS EXPRESS LIMITADA | H3: 76.134.946-5
A4: ADMIN. DE SUPERMERCADOS HIPER LIMITADA | H4: 76.134.941-4
A5: ADMINISTRACION Y GESTION DE ESTACIONES D | H5: 88.473.200-K
A6: ADMINISTRADORA DE VENTAS AL DETALLE LTDA | H6: 77.215.640-5
A7: AGENCIA DE DISEÃ?O PLANK LIMITADA | H7: 76.903.312-2
A8: AGUAS CORDILLERA S.A. | H8: 96.809.310-K
A9: AISLANTES Y ENVASES SPA | H9: 77.546.260-4
A10: ALCA SPA | H10: 77.934.110-0
A11: Algodonera Colon Ltda | H11: 91.363.000-9
A12: ALL BAGS CHILE SPA | H12: 77.049.061-8
A13: ALOPRINT SPA | H13: 76.255.554-9
... A20: Artel S.A | H20: 92.642.000-3
A21: Artel S.A.
A22: AT CONTADORES SERVICIOS PROFESIONALES LIMITADA | H22: 76.934.534-5
A23: aufbau.cl | H23: 79.950.280-1
A24: Automotora Costabal y Echenique S.A | H24: 91.139.000-0
A25: AVICOLA Y COMERCIAL EL TOCO LTDA | H25: 78.383.730-7
A26: BANQUETES LOZACC LIMITADA | H26: 76.512.528-6
A27: BERTA ESTER GOLA MIRANDA | H27: 5.935.468-K
A28: B-LUCKY SPA | H28: 77.460.405-7
A29: BOZEN SPA | H29: 78.088.306-5
A30: BOZENLIGHT LIMITADA | H30: 76.726.210-8
A31: BROCHA LIMITADA | H31: 76.471.303-6
A32: BSALE CHILE S A | H32: 76.136.144-9
A33: CAFÃ? DEL PARQUE SPA | H33: 77.406.473-7
... A38: CENCOSUD RETAIL S.A | H38: 81.201.000-K
A39: CENCOSUD RETAIL S.A.
A40: CENTRO DE CONVENCIONES SANTIAGO S.A | H40: 96.946.650-3
A41: CHAVARRI Y HUGOT LTDA | H41: 84.736.800-4
A42: CHERRY KUL SPA | H42: 77.301.956-8
A43: Chilexpress S A | H43: 96.756.430-3
A44: CHILEXPRESS S.A.
A45: CIA COMERCIALIZADORA DE ALIMENTOS ONZA S A | H45: 96.760.560-3
A46: CLAUDIA DE LAS MERCEDES NAVARRO MENESES | H46: 9.788.501-K
A47: CLAVE TRIBUTARIA CONTADORES LIMITADA | H47: 78.065.582-8
A48: CLICK SPA | H48: 76.975.635-3
A49: CLIMATIZACIÃ?N Y REFRIGERACIÃ?N PETER ALEXANDER LEÃ?N MARTINEZ E.I.R.L. | H49: 76.669.817-4
A50: COLORPACK IMPRESORES LIMITADA | H50: 78.996.660-5
A51: COMAAC SPA | H51: 76.774.415-3
A52: COMERCIAL AGAPI SPA | H52: 77.301.568-6
A53: Comercial AgustÃ­n SPA | H53: 76.287.853-4
A54: COMERCIAL ANALAB CHILE SA | H54: 87.963.400-8
A55: COMERCIAL BUSTOS Y PEREZ LIMITADA | H55: 77.478.600-7
A56: COMERCIAL CLOVER I LIMITADA | H56: 76.992.308-K
... A86: CONTRATISTA MANO DE OBRA AGRÃCOLA VÃCTOR MARIPANGUI LUCERO E.I.R.L. | H86: 76.755.481-8
A87: COOPERATIVA AGRICOLA Y LECHERA DE LA UNION LTDA
A88: COOPERATIVA AGRICOLA Y LECHERA DE LA UNION LTDA.
A89: COPEC S.A. | H89: 99.520.000-7
A90: COSTA HERMANOS Y CIA LTDA | H90: 77.274.340-8
A91: CRISTALERÃAS DE CHILE S.A. | H91: 90.331.000-6
A92: CRISTALERIAS TORO SPA | H92: 93.372.000-4
A93: DAGA SPA | H93: 77.769.831-1
A94: DAP DUCASSE DISE?O LTDA. | H94: 76.046.809-6
A95: DCIC SPA | H95: 76.205.592-9
A96: Delivery Hero E-Commerce Chile SPA | H96: 76.211.425-9
A97: DISEÃ?O Y PROTOTIPADO SPA | H97: 77.521.793-6
A98: DISEÃ?OS GRÃFICOS S-LINNE SPA | H98: 77.320.742-9
A99: DISPARO SPA | H99: 76.501.083-7
A100: DISTRIBUIDOR QISHENG SPA | H100: 77.685.577-4
... A154: GRUPO ECO LIMPIO SPA | H154: 77.047.463-9
A155: HAULMER CHILE SPA
A156: HAULMER SPA | H156: 76.795.561-8
A157: HG CONSTRUCTORA SPA | H157: 76.474.307-5
A158: HIPERMERCADOS TOTTUS S.A. | H158: 78.627.210-6
A159: Homs | H159: 77.931.120-1
A160: IGNACIO AZCORBEBEITIA Y CIA LTDA | H160: 84.071.200-1
A161: IKEA | H161: 76.993.859-1
A162: ILOP S A | H162: 80.478.200-1
A163: IMAHE S.A. | H163: 85.110.100-4
A164: Imega Ventus SpA | H164: 99.522.260-4
A165: IMPALSA SpA | H165: 77.545.005-3
A166: IMPORTACIONES Y VENTAS ÃLVARO ANDRÃ?S MORENO PIRARD E.I.R.L. | H166: 76.567.138-8
A167: Importadora Dalia Ltda | H167: 77.787.900-6
... A193: JOSE RIVERO LLAMAZALES Y CIA. LTDA. | H193: 86.520.500-7
A194: JOSE RIVERO LLAMAZALES Y COMPANIA LIMITADA
A195: JOSE VICENTE ARANGUIZ SALINAS | H195: 12.662.619-3
A196: JUAN CARLOS QUIROZ NUNEZ | H196: 8.412.339-0
A197: JUAN RODAMIRO ANDRADE BARRIA | H197: 7.275.067-5
A198: JUGOS RUSTICOS SPA | H198: 76.467.151-1
A199: JUPIX CHILE SPA | H199: 76.991.040-9
A200: KARAMEL ALIMENTOS SPA | H200: 76.633.110-6
A201: Karsharing SpA | H201: 76.530.509-8
A202: KITCHEN CENTER SPA | H202: 96.999.930-7
A203: LA COSTURERÃA DE FRESIA SPA | H203: 77.421.782-7
A204: LA OFERTA COMERCIAL LIMITADA | H204: 96.532.120-9
A205: LATAM AIRLINES GROUP S.A. | H205: 89.862.200-2
A206: LEON VITACURA S.A. | H206: 76.775.026-9
... A228: MUEBLES GAUDENCIO RIVERA CARRANZA LIMITADA | H228: 77.874.731-6
A229: MULTISERVICIO S S SPA
A230: MULTISTORE SPA | H230: 77.896.612-3
A231: MUNDO ETIQUETAS SPA | H231: 76.502.041-7
A232: Nairobi Spa | H232: 76.865.114-0
A233: Nespresso Chile S.A. | H233: 76.113.783-2
A234: NSC SPA | H234: 77.244.111-8
A235: PAISAJE FLORA Y MIEL SPA | H235: 77.423.233-8
A236: PAISAJISMO TERESA MOLLER Y ASOCIADOS LIMITADA | H236: 76.135.980-0
A237: PANIFICADORA LO SALDES S.A. | H237: 79.937.650-4
A238: PASTELERIAS THE CAKE CLUB | H238: 76.686.391-4
...
